Workbook

Sheet Read me
A1: Revert Guide: content verification tracker
A2: One workbook for the review team. Every piece of site text that a scholar, mentor or professional should verify is listed on the 'Review rows' sheet, one text section per row, with the English and the Bengali text side by side, the kind of review it needs, the sources it cites, and yellow columns for your verdict and comments.
A3: Generated | B3: 2026-09-26 from the content files in the repository (last commit da3ea47). Re-run scripts/verification-tracker/build.py to refresh it after content changes, passing --previous with the filled-in copy so the yellow columns are carried over (rows are matched on 'Item key' plus 'JSON location', items on 'Item key', sources and masjids on their ids).
A4: Contents | B4: 2057 text rows across 689 items on 'Review rows'; 1506 sources on 'Sources'; 459 masjid records on 'Masjids'; 58 findings on 'Site team notes'. The counts on 'Items' and 'Summary' are formulas and calculate when the file opens (Excel may ask to save on close because of this).
A5: Colour key | B5: Dark header = generated column (read only). Gold header and pale yellow cells = for the review team to fill in. Grey cells = formulas.
A7: How to use it
A8: • | B8: Open 'Review rows'. Use the filters in the header row to pick your part: filter 'Area' (for example FAQ, Topic, Roadmap step), 'Suggested reviewer' (Scholar, Mentor, Mental health professional, Legal professional, Medical professional) or 'Review needed'. Several values are joined with '; ' in one cell, so type a word into the filter's search box (for example 'Scholar' or 'Medical') rather than picking exact combinations. Most rows are High priority because most of the site is still unreviewed; filter by area or review type to carve out a manageable slice.
A9: • | B9: Read the English text. If you review Bengali, read the Bengali text next to it and judge both the meaning and the translation.
A10: • | B10: Check the claims against 'Sources used' (the ids point to the 'Sources' sheet, which has every link) and against 'Key points to check'.
A11: • | B11: Fill in the yellow columns only: 'English verdict' (Approved, Needs changes, Rejected, Unsure), 'English reviewer' (your name), 'English comments' (what to change and why; quote the exact words). Bengali reviewers use the three Bengali columns the same way.
A12: • | B12: Set 'Done' to Yes once the row is settled in both languages. The 'Items' and 'Summary' sheets count progress automatically.
A13: • | B13: Grey and white columns are generated from the site's content files: do not edit them. If a text is wrong, say so in the comments and the site team will fix the content file named in 'JSON location'.
A14: • | B14: 'Sources' and 'Masjids' are separate sheets with their own verdict columns: sources need a citation check (collection, number, grading, working link); masjids need a directory check (mainstream Sunni, details current).
A15: • | B15: 'Site team notes' lists cross-cutting findings from the preparation of this workbook (duplicate entries, missing source ids, naming-rule slips, facts to confirm, code-defined text). They are for the site team and a scholar where marked; each has a status column.
A16: • | B16: Not covered here: the 99 names of Allah page, whose names and English meanings are fetched from the AlAdhan API at run time rather than stored in the site; the live prayer-times data; and short interface labels (buttons, menu items, form labels). Everything else that a visitor can read is on one of the sheets.
A18: What the generated columns mean
A19: Priority | B19: High: unreviewed text that carries rulings, belief, suicide or self-harm, safety, legal, financial, medical or mental-health guidance. Medium: unreviewed practical text, or source-checked text that still makes religious claims. Low: everything else. A row that mentions suicide, self-harm or a crisis line is always High, whatever its item's priority.
A20: Review needed | B20: The kinds of verification the row needs (see the list below). A row can need several.
A21: Suggested reviewer | B21: Who should look first. Scholars for religious content, mentors for lived-experience and practical guidance, professionals for clinical, legal or medical claims.
A22: Current status (site) | B22: The reviewStatus recorded in the content file today: 'review-needed' = Touches rulings, mental health, safety, legal, financial or sensitive family matters and still needs a qualified reviewer. 'source-checked' = The cited sources were verified against their links; the content itself still awaits a reviewer. 'draft' = Not yet checked at all. 'approved' = A qualified reviewer approved it. 'not tracked' = This part of the site has no review status field yet (stages, glossary entries, site page text). 'not tracked' covers the stages, the glossary, the site page text, the Ramadan planning sections, the resource collections, the seasonal calendar, the source categories and the illustrations.
A23: Bengali status | B23: Translated: Bengali text exists. Missing: no Bengali text for this section (the illustration rows are Missing by design: the images carry English text in every language). Same as English / Not translated: the Bengali file still carries the English words. Not needed: the text is Arabic, a link or a number and needs no translation.
A24: Sources used | B24: The source ids the site cites for this text, with title and organisation, one per line. The column does not wrap, so click the cell (or read the formula bar) to see the whole list, and look the id up on the 'Sources' sheet for the link and the note on what it supports. The 'Items' sheet repeats the list with links.
A25: Key points to check | B25: A machine-generated reading list of the specific claims, citations, numbers and names in the item. It is a pointer, not a verdict. It is shown on the first row of each item (and on the 'Items' sheet), so look there when an item has several rows.
A26: Pre-check flags | B26: Machine-generated warnings about a possible breach of the site's own rules (for example suicide-safe wording, 911 before 9-8-8, a missing source), shown on the first row of each item and on 'Items'. Please confirm or dismiss them in your comments.
A27: Sources (n) | B27: How many source ids the row carries. For tool pages and the Ramadan planning sections, sections without their own ids show the page's source list, which the site defines in the page code; every topic row repeats the topic's whole list because topics cite sources at page level.
A28: Page URL / JSON location | B28: Where the text appears on the site (with an anchor to the section where one exists) and where it lives in the content files, for the site team. 'Content ID' and 'Item key' identify the item; 'Item key' plus 'JSON location' is the stable key for merging a filled-in copy into a rebuilt workbook.
A29: Date done | B29: The date the row was settled, in whatever format you like; it is not counted.
A30: Items sheet | B30: One row per item with formulas counting its rows. Its three yellow columns are for assigning a reviewer to the whole item, an item-level verdict, and notes.
A32: Review types
A33: Fiqh ruling | B33: What is obligatory, permitted or forbidden, and how worship is performed.
A34: Aqidah (belief) | B34: Statements about Allah, prophets, revelation, the afterlife and creed.
A35: Quran or hadith citation | B35: A verse or hadith is quoted, paraphrased or cited: check reference, wording and grading.
A36: Seerah or history | B36: Claims about the Prophet's life, the companions or Islamic history.
A37: Arabic text or transliteration | B37: Arabic script, transliteration or translation of a phrase, dua or term.
A38: Mental health | B38: Emotional wellbeing, anxiety, depression, therapy, grief, waswas.
A39: Suicide-safe language | B39: Suicide or self-harm is mentioned: check wording and that 911 comes before 9-8-8.
A40: Safety or abuse | B40: Domestic violence, coercion, personal safety, emergencies.
A41: Legal (Canada) | B41: Law, rights, wills, marriage law, immigration, workplace or school accommodation.
A42: Financial (zakat, riba, money) | B42: Zakat rules or numbers, interest, mortgages, banking, debt.
A43: Medical or health | B43: Menstruation, illness and fasting, medication, pregnancy, disability, hygiene.
A44: Family, marriage or intimacy | B44: Marriage, spouses, divorce, parenting, intimacy, telling family.
... A48: Site policy or legal notice | B48: About, privacy, terms, accessibility and source policy statements.
A50: House rules the content must follow
A51: • | B51: Mainstream Sunni scholarship only. Differences between the four Sunni schools are acknowledged without choosing one. No Shia or Ahmadiyya source or institution.
A52: • | B52: Headings lead with plain English and put the Arabic term in brackets, for example 'Washing before prayer (wudu)'. Ghusl is a full-body wash, never a shower.
A53: • | B53: Suicide-safe writing: say 'died by suicide' and 'thoughts of suicide'; never 'committed suicide'. Give 911 first for immediate danger, then 9-8-8 (call or text). Never frame suicidal thoughts as a sin. Keep clinical and religious guidance in separate sentences.
A54: • | B54: Every religious claim carries source ids that point at sources.json. Quran and hadith links use Quran.com and Sunnah.com. Nothing is invented.
A55: • | B55: Tone: encouraging and non-judgemental, written for someone in their first year as a Muslim in Canada.
A57: বাংলা পর্যালোচকদের জন্য সংক্ষিপ্ত নির্দেশনা
A58: • | B58: 'Review rows' শিটে যান। শিরোনাম সারির ফিল্টার দিয়ে আপনার অংশ বেছে নিন: 'Area' (যেমন FAQ, Topic, Roadmap step), 'Suggested reviewer' (Scholar, Mentor ইত্যাদি) বা 'Priority'। প্রথমে High দিয়ে শুরু করুন।
A59: • | B59: 'English text' কলামের ইংরেজি লেখা এবং তার পাশে 'Bengali text (বাংলা)' কলামের বাংলা অনুবাদ পড়ুন। অর্থ ঠিক আছে কি না এবং অনুবাদ সঠিক কি না, দুটোই দেখুন।
A60: • | B60: 'Sources used' কলামে দেওয়া সূত্রগুলোর সঙ্গে দাবিগুলো মিলিয়ে দেখুন। প্রতিটি সূত্রের লিংক 'Sources' শিটে আছে। 'Key points to check' কলামে কোন কোন বিষয় যাচাই করতে হবে তার তালিকা আছে।
A61: • | B61: শুধু হলুদ কলামগুলো পূরণ করুন। ইংরেজি লেখার জন্য 'English verdict', 'English reviewer', 'English comments'; বাংলা অনুবাদের জন্য 'Bengali verdict', 'Bengali reviewer', 'Bengali comments'। সিদ্ধান্ত: Approved (অনুমোদিত), Needs changes (পরিবর্তন দরকার), Rejected (বাতিল), Unsure (অন্য পর্যালোচকের মত দরকার)। মন্তব্যে ঠিক কোন শব্দ বদলাতে হবে এবং কেন, তা লিখুন।
A62: • | B62: দুই ভাষার কাজ শেষ হলে 'Done' কলামে Yes দিন। 'Items' ও 'Summary' শিটে অগ্রগতি স্বয়ংক্রিয়ভাবে গণনা হয়।
A63: • | B63: ধূসর ও সাদা কলামগুলো সাইটের কনটেন্ট ফাইল থেকে স্বয়ংক্রিয়ভাবে তৈরি; সেগুলো সম্পাদনা করবেন না। কোনো লেখা ভুল হলে মন্তব্যে লিখুন, সাইট টিম কনটেন্ট ফাইল ঠিক করবে।
A64: • | B64: 'Bengali status' কলামে Missing, Same as English বা Not translated থাকলে বুঝবেন সেই অংশের বাংলা অনুবাদ এখনো নেই বা অসম্পূর্ণ।

Sheet Summary
A1: Revert Guide content verification: progress summary
A2: All numbers are formulas over the other sheets and update as the team fills in the yellow columns.
A4: Area | B4: Items | C4: Text rows | D4: High priority rows | E4: Rows done | F4: % done | G4: EN approved | H4: BN approved
A5: Roadmap stage | B5: =COUNTIF(Items!$B$2:$B$690,$A5) -> 6 | C5: =COUNTIF('Review rows'!$B$2:$B$2058,$A5) -> 66 | D5: =COUNTIFS('Review rows'!$B$2:$B$2058,$A5,'Review rows'!$H$2:$H$2058,"High") -> 24 | E5: =COUNTIFS('Review rows'!$B$2:$B$2058,$A5,'Review rows'!$V$2:$V$2058,"Yes") -> 0 | F5: =IF(C5=0,0,E5/C5) -> 0 | G5: =COUNTIFS('Review rows'!$B$2:$B$2058,$A5,'Review rows'!$P$2:$P$2058,"Approved") -> 0 | H5: =COUNTIFS('Review rows'!$B$2:$B$2058,$A5,'Review rows'!$S$2:$S$2058,"Approved") -> 0
A6: Roadmap step | B6: =COUNTIF(Items!$B$2:$B$690,$A6) -> 20 | C6: =COUNTIF('Review rows'!$B$2:$B$2058,$A6) -> 286 | D6: =COUNTIFS('Review rows'!$B$2:$B$2058,$A6,'Review rows'!$H$2:$H$2058,"High") -> 193 | E6: =COUNTIFS('Review rows'!$B$2:$B$2058,$A6,'Review rows'!$V$2:$V$2058,"Yes") -> 0 | F6: =IF(C6=0,0,E6/C6) -> 0 | G6: =COUNTIFS('Review rows'!$B$2:$B$2058,$A6,'Review rows'!$P$2:$P$2058,"Approved") -> 0 | H6: =COUNTIFS('Review rows'!$B$2:$B$2058,$A6,'Review rows'!$S$2:$S$2058,"Approved") -> 0
A7: Topic | B7: =COUNTIF(Items!$B$2:$B$690,$A7) -> 22 | C7: =COUNTIF('Review rows'!$B$2:$B$2058,$A7) -> 228 | D7: =COUNTIFS('Review rows'!$B$2:$B$2058,$A7,'Review rows'!$H$2:$H$2058,"High") -> 221 | E7: =COUNTIFS('Review rows'!$B$2:$B$2058,$A7,'Review rows'!$V$2:$V$2058,"Yes") -> 0 | F7: =IF(C7=0,0,E7/C7) -> 0 | G7: =COUNTIFS('Review rows'!$B$2:$B$2058,$A7,'Review rows'!$P$2:$P$2058,"Approved") -> 0 | H7: =COUNTIFS('Review rows'!$B$2:$B$2058,$A7,'Review rows'!$S$2:$S$2058,"Approved") -> 0
A8: Life guide | B8: =COUNTIF(Items!$B$2:$B$690,$A8) -> 22 | C8: =COUNTIF('Review rows'!$B$2:$B$2058,$A8) -> 383 | D8: =COUNTIFS('Review rows'!$B$2:$B$2058,$A8,'Review rows'!$H$2:$H$2058,"High") -> 383 | E8: =COUNTIFS('Review rows'!$B$2:$B$2058,$A8,'Review rows'!$V$2:$V$2058,"Yes") -> 0 | F8: =IF(C8=0,0,E8/C8) -> 0 | G8: =COUNTIFS('Review rows'!$B$2:$B$2058,$A8,'Review rows'!$P$2:$P$2058,"Approved") -> 0 | H8: =COUNTIFS('Review rows'!$B$2:$B$2058,$A8,'Review rows'!$S$2:$S$2058,"Approved") -> 0
A9: Seasonal guide | B9: =COUNTIF(Items!$B$2:$B$690,$A9) -> 8 | C9: =COUNTIF('Review rows'!$B$2:$B$2058,$A9) -> 112 | D9: =COUNTIFS('Review rows'!$B$2:$B$2058,$A9,'Review rows'!$H$2:$H$2058,"High") -> 87 | E9: =COUNTIFS('Review rows'!$B$2:$B$2058,$A9,'Review rows'!$V$2:$V$2058,"Yes") -> 0 | F9: =IF(C9=0,0,E9/C9) -> 0 | G9: =COUNTIFS('Review rows'!$B$2:$B$2058,$A9,'Review rows'!$P$2:$P$2058,"Approved") -> 0 | H9: =COUNTIFS('Review rows'!$B$2:$B$2058,$A9,'Review rows'!$S$2:$S$2058,"Approved") -> 0
A10: FAQ | B10: =COUNTIF(Items!$B$2:$B$690,$A10) -> 222 | C10: =COUNTIF('Review rows'!$B$2:$B$2058,$A10) -> 222 | D10: =COUNTIFS('Review rows'!$B$2:$B$2058,$A10,'Review rows'!$H$2:$H$2058,"High") -> 163 | E10: =COUNTIFS('Review rows'!$B$2:$B$2058,$A10,'Review rows'!$V$2:$V$2058,"Yes") -> 0 | F10: =IF(C10=0,0,E10/C10) -> 0 | G10: =COUNTIFS('Review rows'!$B$2:$B$2058,$A10,'Review rows'!$P$2:$P$2058,"Approved") -> 0 | H10: =COUNTIFS('Review rows'!$B$2:$B$2058,$A10,'Review rows'!$S$2:$S$2058,"Approved") -> 0
A11: Glossary | B11: =COUNTIF(Items!$B$2:$B$690,$A11) -> 188 | C11: =COUNTIF('Review rows'!$B$2:$B$2058,$A11) -> 188 | D11: =COUNTIFS('Review rows'!$B$2:$B$2058,$A11,'Review rows'!$H$2:$H$2058,"High") -> 85 | E11: =COUNTIFS('Review rows'!$B$2:$B$2058,$A11,'Review rows'!$V$2:$V$2058,"Yes") -> 0 | F11: =IF(C11=0,0,E11/C11) -> 0 | G11: =COUNTIFS('Review rows'!$B$2:$B$2058,$A11,'Review rows'!$P$2:$P$2058,"Approved") -> 0 | H11: =COUNTIFS('Review rows'!$B$2:$B$2058,$A11,'Review rows'!$S$2:$S$2058,"Approved") -> 0
A12: Tool page | B12: =COUNTIF(Items!$B$2:$B$690,$A12) -> 4 | C12: =COUNTIF('Review rows'!$B$2:$B$2058,$A12) -> 166 | D12: =COUNTIFS('Review rows'!$B$2:$B$2058,$A12,'Review rows'!$H$2:$H$2058,"High") -> 166 | E12: =COUNTIFS('Review rows'!$B$2:$B$2058,$A12,'Review rows'!$V$2:$V$2058,"Yes") -> 0 | F12: =IF(C12=0,0,E12/C12) -> 0 | G12: =COUNTIFS('Review rows'!$B$2:$B$2058,$A12,'Review rows'!$P$2:$P$2058,"Approved") -> 0 | H12: =COUNTIFS('Review rows'!$B$2:$B$2058,$A12,'Review rows'!$S$2:$S$2058,"Approved") -> 0
A13: Tool page text | B13: =COUNTIF(Items!$B$2:$B$690,$A13) -> 44 | C13: =COUNTIF('Review rows'!$B$2:$B$2058,$A13) -> 49 | D13: =COUNTIFS('Review rows'!$B$2:$B$2058,$A13,'Review rows'!$H$2:$H$2058,"High") -> 21 | E13: =COUNTIFS('Review rows'!$B$2:$B$2058,$A13,'Review rows'!$V$2:$V$2058,"Yes") -> 0 | F13: =IF(C13=0,0,E13/C13) -> 0 | G13: =COUNTIFS('Review rows'!$B$2:$B$2058,$A13,'Review rows'!$P$2:$P$2058,"Approved") -> 0 | H13: =COUNTIFS('Review rows'!$B$2:$B$2058,$A13,'Review rows'!$S$2:$S$2058,"Approved") -> 0
A14: Ramadan guide page | B14: =COUNTIF(Items!$B$2:$B$690,$A14) -> 13 | C14: =COUNTIF('Review rows'!$B$2:$B$2058,$A14) -> 25 | D14: =COUNTIFS('Review rows'!$B$2:$B$2058,$A14,'Review rows'!$H$2:$H$2058,"High") -> 25 | E14: =COUNTIFS('Review rows'!$B$2:$B$2058,$A14,'Review rows'!$V$2:$V$2058,"Yes") -> 0 | F14: =IF(C14=0,0,E14/C14) -> 0 | G14: =COUNTIFS('Review rows'!$B$2:$B$2058,$A14,'Review rows'!$P$2:$P$2058,"Approved") -> 0 | H14: =COUNTIFS('Review rows'!$B$2:$B$2058,$A14,'Review rows'!$S$2:$S$2058,"Approved") -> 0
A15: Mental health page | B15: =COUNTIF(Items!$B$2:$B$690,$A15) -> 8 | C15: =COUNTIF('Review rows'!$B$2:$B$2058,$A15) -> 40 | D15: =COUNTIFS('Review rows'!$B$2:$B$2058,$A15,'Review rows'!$H$2:$H$2058,"High") -> 39 | E15: =COUNTIFS('Review rows'!$B$2:$B$2058,$A15,'Review rows'!$V$2:$V$2058,"Yes") -> 0 | F15: =IF(C15=0,0,E15/C15) -> 0 | G15: =COUNTIFS('Review rows'!$B$2:$B$2058,$A15,'Review rows'!$P$2:$P$2058,"Approved") -> 0 | H15: =COUNTIFS('Review rows'!$B$2:$B$2058,$A15,'Review rows'!$S$2:$S$2058,"Approved") -> 0
A16: Help & community pages | B16: =COUNTIF(Items!$B$2:$B$690,$A16) -> 24 | C16: =COUNTIF('Review rows'!$B$2:$B$2058,$A16) -> 24 | D16: =COUNTIFS('Review rows'!$B$2:$B$2058,$A16,'Review rows'!$H$2:$H$2058,"High") -> 11 | E16: =COUNTIFS('Review rows'!$B$2:$B$2058,$A16,'Review rows'!$V$2:$V$2058,"Yes") -> 0 | F16: =IF(C16=0,0,E16/C16) -> 0 | G16: =COUNTIFS('Review rows'!$B$2:$B$2058,$A16,'Review rows'!$P$2:$P$2058,"Approved") -> 0 | H16: =COUNTIFS('Review rows'!$B$2:$B$2058,$A16,'Review rows'!$S$2:$S$2058,"Approved") -> 0
... A24: Illustration text (SVG) | B24: =COUNTIF(Items!$B$2:$B$690,$A24) -> 10 | C24: =COUNTIF('Review rows'!$B$2:$B$2058,$A24) -> 20 | D24: =COUNTIFS('Review rows'!$B$2:$B$2058,$A24,'Review rows'!$H$2:$H$2058,"High") -> 20 | E24: =COUNTIFS('Review rows'!$B$2:$B$2058,$A24,'Review rows'!$V$2:$V$2058,"Yes") -> 0 | F24: =IF(C24=0,0,E24/C24) -> 0 | G24: =COUNTIFS('Review rows'!$B$2:$B$2058,$A24,'Review rows'!$P$2:$P$2058,"Approved") -> 0 | H24: =COUNTIFS('Review rows'!$B$2:$B$2058,$A24,'Review rows'!$S$2:$S$2058,"Approved") -> 0
A25: Total | B25: =SUM(B5:B24) -> 689 | C25: =SUM(C5:C24) -> 2057 | D25: =SUM(D5:D24) -> 1477 | E25: =SUM(E5:E24) -> 0 | F25: =IF(C25=0,0,E25/C25) -> 0 | G25: =SUM(G5:G24) -> 0 | H25: =SUM(H5:H24) -> 0
A27: Review type | B27: Text rows | C27: Rows done | D27: % done
A28: Fiqh ruling | B28: =COUNTIF('Review rows'!$I$2:$I$2058,"*"&$A28&"*") -> 1282 | C28: =COUNTIFS('Review rows'!$I$2:$I$2058,"*"&$A28&"*",'Review rows'!$V$2:$V$2058,"Yes") -> 0 | D28: =IF(B28=0,0,C28/B28) -> 0
A29: Aqidah (belief) | B29: =COUNTIF('Review rows'!$I$2:$I$2058,"*"&$A29&"*") -> 362 | C29: =COUNTIFS('Review rows'!$I$2:$I$2058,"*"&$A29&"*",'Review rows'!$V$2:$V$2058,"Yes") -> 0 | D29: =IF(B29=0,0,C29/B29) -> 0
A30: Quran or hadith citation | B30: =COUNTIF('Review rows'!$I$2:$I$2058,"*"&$A30&"*") -> 422 | C30: =COUNTIFS('Review rows'!$I$2:$I$2058,"*"&$A30&"*",'Review rows'!$V$2:$V$2058,"Yes") -> 0 | D30: =IF(B30=0,0,C30/B30) -> 0
A31: Seerah or history | B31: =COUNTIF('Review rows'!$I$2:$I$2058,"*"&$A31&"*") -> 107 | C31: =COUNTIFS('Review rows'!$I$2:$I$2058,"*"&$A31&"*",'Review rows'!$V$2:$V$2058,"Yes") -> 0 | D31: =IF(B31=0,0,C31/B31) -> 0
A32: Arabic text or transliteration | B32: =COUNTIF('Review rows'!$I$2:$I$2058,"*"&$A32&"*") -> 274 | C32: =COUNTIFS('Review rows'!$I$2:$I$2058,"*"&$A32&"*",'Review rows'!$V$2:$V$2058,"Yes") -> 0 | D32: =IF(B32=0,0,C32/B32) -> 0
A33: Mental health | B33: =COUNTIF('Review rows'!$I$2:$I$2058,"*"&$A33&"*") -> 593 | C33: =COUNTIFS('Review rows'!$I$2:$I$2058,"*"&$A33&"*",'Review rows'!$V$2:$V$2058,"Yes") -> 0 | D33: =IF(B33=0,0,C33/B33) -> 0
A34: Suicide-safe language | B34: =COUNTIF('Review rows'!$I$2:$I$2058,"*"&$A34&"*") -> 51 | C34: =COUNTIFS('Review rows'!$I$2:$I$2058,"*"&$A34&"*",'Review rows'!$V$2:$V$2058,"Yes") -> 0 | D34: =IF(B34=0,0,C34/B34) -> 0
A35: Safety or abuse | B35: =COUNTIF('Review rows'!$I$2:$I$2058,"*"&$A35&"*") -> 571 | C35: =COUNTIFS('Review rows'!$I$2:$I$2058,"*"&$A35&"*",'Review rows'!$V$2:$V$2058,"Yes") -> 0 | D35: =IF(B35=0,0,C35/B35) -> 0
A36: Legal (Canada) | B36: =COUNTIF('Review rows'!$I$2:$I$2058,"*"&$A36&"*") -> 379 | C36: =COUNTIFS('Review rows'!$I$2:$I$2058,"*"&$A36&"*",'Review rows'!$V$2:$V$2058,"Yes") -> 0 | D36: =IF(B36=0,0,C36/B36) -> 0
A37: Financial (zakat, riba, money) | B37: =COUNTIF('Review rows'!$I$2:$I$2058,"*"&$A37&"*") -> 256 | C37: =COUNTIFS('Review rows'!$I$2:$I$2058,"*"&$A37&"*",'Review rows'!$V$2:$V$2058,"Yes") -> 0 | D37: =IF(B37=0,0,C37/B37) -> 0
A38: Medical or health | B38: =COUNTIF('Review rows'!$I$2:$I$2058,"*"&$A38&"*") -> 339 | C38: =COUNTIFS('Review rows'!$I$2:$I$2058,"*"&$A38&"*",'Review rows'!$V$2:$V$2058,"Yes") -> 0 | D38: =IF(B38=0,0,C38/B38) -> 0
A39: Family, marriage or intimacy | B39: =COUNTIF('Review rows'!$I$2:$I$2058,"*"&$A39&"*") -> 458 | C39: =COUNTIFS('Review rows'!$I$2:$I$2058,"*"&$A39&"*",'Review rows'!$V$2:$V$2058,"Yes") -> 0 | D39: =IF(B39=0,0,C39/B39) -> 0
... A43: Site policy or legal notice | B43: =COUNTIF('Review rows'!$I$2:$I$2058,"*"&$A43&"*") -> 137 | C43: =COUNTIFS('Review rows'!$I$2:$I$2058,"*"&$A43&"*",'Review rows'!$V$2:$V$2058,"Yes") -> 0 | D43: =IF(B43=0,0,C43/B43) -> 0
A45: Suggested reviewer | B45: Text rows | C45: Rows done | D45: % done
A46: Scholar | B46: =COUNTIF('Review rows'!$J$2:$J$2058,"*"&$A46&"*") -> 1789 | C46: =COUNTIFS('Review rows'!$J$2:$J$2058,"*"&$A46&"*",'Review rows'!$V$2:$V$2058,"Yes") -> 0 | D46: =IF(B46=0,0,C46/B46) -> 0
A47: Mentor | B47: =COUNTIF('Review rows'!$J$2:$J$2058,"*"&$A47&"*") -> 1334 | C47: =COUNTIFS('Review rows'!$J$2:$J$2058,"*"&$A47&"*",'Review rows'!$V$2:$V$2058,"Yes") -> 0 | D47: =IF(B47=0,0,C47/B47) -> 0
A48: Mental health professional | B48: =COUNTIF('Review rows'!$J$2:$J$2058,"*"&$A48&"*") -> 603 | C48: =COUNTIFS('Review rows'!$J$2:$J$2058,"*"&$A48&"*",'Review rows'!$V$2:$V$2058,"Yes") -> 0 | D48: =IF(B48=0,0,C48/B48) -> 0
A49: Legal professional | B49: =COUNTIF('Review rows'!$J$2:$J$2058,"*"&$A49&"*") -> 405 | C49: =COUNTIFS('Review rows'!$J$2:$J$2058,"*"&$A49&"*",'Review rows'!$V$2:$V$2058,"Yes") -> 0 | D49: =IF(B49=0,0,C49/B49) -> 0
A50: Medical professional | B50: =COUNTIF('Review rows'!$J$2:$J$2058,"*"&$A50&"*") -> 339 | C50: =COUNTIFS('Review rows'!$J$2:$J$2058,"*"&$A50&"*",'Review rows'!$V$2:$V$2058,"Yes") -> 0 | D50: =IF(B50=0,0,C50/B50) -> 0
A52: Priority | B52: Text rows | C52: Rows done | D52: % done
A53: High | B53: =COUNTIF('Review rows'!$H$2:$H$2058,$A53) -> 1477 | C53: =COUNTIFS('Review rows'!$H$2:$H$2058,$A53,'Review rows'!$V$2:$V$2058,"Yes") -> 0 | D53: =IF(B53=0,0,C53/B53) -> 0
A54: Medium | B54: =COUNTIF('Review rows'!$H$2:$H$2058,$A54) -> 558 | C54: =COUNTIFS('Review rows'!$H$2:$H$2058,$A54,'Review rows'!$V$2:$V$2058,"Yes") -> 0 | D54: =IF(B54=0,0,C54/B54) -> 0
A55: Low | B55: =COUNTIF('Review rows'!$H$2:$H$2058,$A55) -> 22 | C55: =COUNTIFS('Review rows'!$H$2:$H$2058,$A55,'Review rows'!$V$2:$V$2058,"Yes") -> 0 | D55: =IF(B55=0,0,C55/B55) -> 0
A57: Bengali translation status | B57: Text rows
A58: Translated | B58: =COUNTIF('Review rows'!$G$2:$G$2058,$A58) -> 2037
A59: Missing | B59: =COUNTIF('Review rows'!$G$2:$G$2058,$A59) -> 20
A60: Same as English | B60: =COUNTIF('Review rows'!$G$2:$G$2058,$A60) -> 0
A61: Not translated | B61: =COUNTIF('Review rows'!$G$2:$G$2058,$A61) -> 0
A62: Not needed | B62: =COUNTIF('Review rows'!$G$2:$G$2058,$A62) -> 0
A64: Verdicts | B64: English | C64: Bengali
A65: Approved | B65: =COUNTIF('Review rows'!$P$2:$P$2058,$A65) -> 0 | C65: =COUNTIF('Review rows'!$S$2:$S$2058,$A65) -> 0
A66: Needs changes | B66: =COUNTIF('Review rows'!$P$2:$P$2058,$A66) -> 0 | C66: =COUNTIF('Review rows'!$S$2:$S$2058,$A66) -> 0
A67: Rejected | B67: =COUNTIF('Review rows'!$P$2:$P$2058,$A67) -> 0 | C67: =COUNTIF('Review rows'!$S$2:$S$2058,$A67) -> 0
A68: Unsure* | B68: =COUNTIF('Review rows'!$P$2:$P$2058,$A68) -> 0 | C68: =COUNTIF('Review rows'!$S$2:$S$2058,$A68) -> 0
A70: Other sheets | B70: Records | C70: Marked review-needed | D70: Verdicts given
A71: Sources | B71: 1506 | C71: =COUNTIF(Sources!$I$2:$I$1507,"review-needed") -> 206 | D71: =COUNTA(Sources!$M2:$M1507) -> 0
A72: Masjids | B72: 459 | C72: =COUNTIF(Masjids!$N$2:$N$460,"review-needed") -> 166 | D72: =COUNTA(Masjids!$P2:$P460) -> 0

Sheet Review rows
A1: Row ID | B1: Area | C1: Item | D1: Section | E1: English text | F1: Bengali text (বাংলা) | G1: Bengali status | H1: Priority | I1: Review needed | J1: Suggested reviewer | K1: Current status (site) | L1: Sources (n) | M1: Sources used (id — title) | N1: Key points to check | O1: Pre-check flags | P1: English verdict | Q1: English reviewer | R1: English comments | S1: Bengali verdict | T1: Bengali reviewer | U1: Bengali comments | V1: Done | W1: Date done | X1: Page URL | Y1: Content ID | Z1: JSON location | AA1: Item key
A2: R0001 | B2: Roadmap stage | C2: Faith and a fresh start | D2: Title, subtitle and description | E2: Faith and a fresh start Day 0-1 Duration: 1-2 days The first day or two is about protecting what just happened. Keep your faith close, stay calm, make Ghusl, and pick one or two next steps you trust. You do not have to rebuild your whole life by tomorrow. | F2: ঈমান আর নতুন শুরু দিন 0-1 Duration: 1-2 দিন প্রথম এক-দুই দিন হলো সদ্য যা ঘটেছে তা রক্ষা করার সময়। ঈমানকে কাছে রাখুন, শান্ত থাকুন, গোসল করুন, আর বিশ্বাস করেন এমন এক বা দুটি পরের ধাপ বেছে নিন। কালকের মধ্যে পুরো জীবন নতুন করে গড়তে হবে না। | G2: Translated | H2: High | I2: Fiqh ruling; Safety or abuse; External resource or teacher; Tone and pastoral wording | J2: Scholar; Mentor | K2: not tracked | L2: 3 | M2: new-muslim-academy — New Muslim Academy (New Muslim Academy) whyislam — WhyIslam (Islamic Circle of North America) new-muslim-guide — New Muslim Guide (New Muslim Guide) | N2: • Says changing your name is not required (scholars usually add: unless the name's meaning conflicts with Islam). • Says make Ghusl 'when you feel ready'; the wudu-ghusl tool says it is required before prayer if you were in a state needing ghusl. • Recommends Mustafa Umar's 'Welcome to Islam', described as a free 32-page guide on his website; confirm page count and free access. • Ask-for-help triggers include not feeling safe telling family and needing a witness or certificate; no contacts are named. | X2: https://www.revertguide.com/en/roadmap/day-0-1 | Y2: day-0-1 | Z2: locales/en/stages.json › [id=day-0-1].title/subtitle/description | AA2: stage:day-0-1
A3: R0002 | B3: Roadmap stage | C3: Faith and a fresh start | D3: Main goal | E3: Know what your Shahada means, get through the first 24 hours gently, and make Ghusl when you feel ready. | F3: আপনার শাহাদার অর্থ জানা, প্রথম 24 ঘণ্টা নরমভাবে পার করা, আর প্রস্তুত হলে গোসল করা। | G3: Translated | H3: High | I3: Fiqh ruling; Safety or abuse; External resource or teacher; Tone and pastoral wording | J3: Scholar; Mentor | K3: not tracked | L3: 3 | M3: new-muslim-academy — New Muslim Academy (New Muslim Academy) whyislam — WhyIslam (Islamic Circle of North America) new-muslim-guide — New Muslim Guide (New Muslim Guide) | X3: https://www.revertguide.com/en/roadmap/day-0-1#overview-heading | Y3: day-0-1 | Z3: locales/en/stages.json › [id=day-0-1].mainGoal | AA3: stage:day-0-1
A4: R0003 | B4: Roadmap stage | C4: Faith and a fresh start | D4: Success looks like | E4: You know you are Muslim, you have one simple next step, and you are not forcing yourself to learn all of it at once. | F4: আপনি জানেন আপনি মুসলিম, আপনার সামনে একটি সহজ পরের ধাপ আছে, আর একসাথে সব শেখার জন্য নিজের ওপর জোর খাটাচ্ছেন না। | G4: Translated | H4: High | I4: Fiqh ruling; Safety or abuse; External resource or teacher; Tone and pastoral wording | J4: Scholar; Mentor | K4: not tracked | L4: 3 | M4: new-muslim-academy — New Muslim Academy (New Muslim Academy) whyislam — WhyIslam (Islamic Circle of North America) new-muslim-guide — New Muslim Guide (New Muslim Guide) | X4: https://www.revertguide.com/en/roadmap/day-0-1#overview-heading | Y4: day-0-1 | Z4: locales/en/stages.json › [id=day-0-1].success | AA4: stage:day-0-1
A5: R0004 | B5: Roadmap stage | C5: Faith and a fresh start | D5: Don't worry about | E5: • Long prayers can wait. Nobody expects you to have them memorized. • You do not have to change your name. It is not required. • You do not have to announce anything to anyone yet. • You will not know every rule for a long time, and that is how it goes for everyone. | F5: • লম্বা নামাজ অপেক্ষা করতে পারে। কেউ আশা করে না সেগুলো আপনার মুখস্থ। • নাম বদলাতে হবে না। এটি আবশ্যক নয়। • এখনই কাউকে কিছু ঘোষণা দিতে হবে না। • অনেক দিন পর্যন্ত আপনি সব নিয়ম জানবেন না, আর সবার ক্ষেত্রেই এমন হয়। | G5: Translated | H5: High | I5: Fiqh ruling; Safety or abuse; External resource or teacher; Tone and pastoral wording | J5: Scholar; Mentor | K5: not tracked | L5: 3 | M5: new-muslim-academy — New Muslim Academy (New Muslim Academy) whyislam — WhyIslam (Islamic Circle of North America) new-muslim-guide — New Muslim Guide (New Muslim Guide) | X5: https://www.revertguide.com/en/roadmap/day-0-1#overview-heading | Y5: day-0-1 | Z5: locales/en/stages.json › [id=day-0-1].dontWorry | AA5: stage:day-0-1
A6: R0005 | B6: Roadmap stage | C6: Faith and a fresh start | D6: Focus now | E6: • Hold on to what the Shahada means to you. • Make Ghusl when you have time to do it calmly. • Pick one person or one masjid you can contact. | F6: • শাহাদা আপনার কাছে কী, তা আঁকড়ে ধরুন। • শান্তভাবে করার মতো সময় পেলে গোসল করুন। • যোগাযোগ করা যায় এমন একজন মানুষ বা একটি মসজিদ বেছে নিন। | G6: Translated | H6: High | I6: Fiqh ruling; Safety or abuse; External resource or teacher; Tone and pastoral wording | J6: Scholar; Mentor | K6: not tracked | L6: 3 | M6: new-muslim-academy — New Muslim Academy (New Muslim Academy) whyislam — WhyIslam (Islamic Circle of North America) new-muslim-guide — New Muslim Guide (New Muslim Guide) | X6: https://www.revertguide.com/en/roadmap/day-0-1#stage-guidance-heading | Y6: day-0-1 | Z6: locales/en/stages.json › [id=day-0-1].focusNow | AA6: stage:day-0-1
A7: R0006 | B7: Roadmap stage | C7: Faith and a fresh start | D7: Can wait | E7: • Detailed rulings and the arguments around them. • Changing your name, your wardrobe, or your whole routine at once. • Explaining Islam to everyone you know. | F7: • বিস্তারিত বিধান আর সেগুলো ঘিরে তর্ক। • একসাথে নাম, পোশাক বা পুরো রুটিন বদলানো। • পরিচিত সবাইকে ইসলাম বোঝানো। | G7: Translated | H7: High | I7: Fiqh ruling; Safety or abuse; External resource or teacher; Tone and pastoral wording | J7: Scholar; Mentor | K7: not tracked | L7: 3 | M7: new-muslim-academy — New Muslim Academy (New Muslim Academy) whyislam — WhyIslam (Islamic Circle of North America) new-muslim-guide — New Muslim Guide (New Muslim Guide) | X7: https://www.revertguide.com/en/roadmap/day-0-1#stage-guidance-heading | Y7: day-0-1 | Z7: locales/en/stages.json › [id=day-0-1].canWait | AA7: stage:day-0-1
A8: R0007 | B8: Roadmap stage | C8: Faith and a fresh start | D8: Ask for help if | E8: • You do not feel safe telling your family. • You are not sure how to do Ghusl. • You need a witness, a certificate, or a way into a local community. | F8: • পরিবারকে জানানো নিরাপদ মনে না হয়। • কীভাবে গোসল করবেন নিশ্চিত না হন। • সাক্ষী, সনদ বা স্থানীয় কমিউনিটিতে ঢোকার পথ দরকার হয়। | G8: Translated | H8: High | I8: Fiqh ruling; Safety or abuse; External resource or teacher; Tone and pastoral wording | J8: Scholar; Mentor | K8: not tracked | L8: 3 | M8: new-muslim-academy — New Muslim Academy (New Muslim Academy) whyislam — WhyIslam (Islamic Circle of North America) new-muslim-guide — New Muslim Guide (New Muslim Guide) | X8: https://www.revertguide.com/en/roadmap/day-0-1#stage-guidance-heading | Y8: day-0-1 | Z8: locales/en/stages.json › [id=day-0-1].askHelpIf | AA8: stage:day-0-1
A9: R0008 | B9: Roadmap stage | C9: Faith and a fresh start | D9: Learning path: main resource | E9: Welcome to Islam: A Step-by-Step Guide for New Muslims A 32-page guide by Mustafa Umar, a scholar and imam, written for your first month. You can read the whole thing free on his website. Link: https://mustafaumar.com/downloads/welcome-to-islam/ | F9: Welcome to Islam: A Step-by-Step Guide for New Muslims (নতুন মুসলিমদের জন্য ধাপে ধাপে গাইড) আলেম ও ইমাম মুস্তাফা উমরের লেখা 32 পৃষ্ঠার একটি গাইড, আপনার প্রথম মাসের জন্য। তার ওয়েবসাইটে পুরোটা বিনামূল্যে পড়া যায়। | G9: Translated | H9: High | I9: Fiqh ruling; Safety or abuse; External resource or teacher; Tone and pastoral wording | J9: Scholar; Mentor | K9: not tracked | L9: 3 | M9: new-muslim-academy — New Muslim Academy (New Muslim Academy) whyislam — WhyIslam (Islamic Circle of North America) new-muslim-guide — New Muslim Guide (New Muslim Guide) | X9: https://www.revertguide.com/en/roadmap/day-0-1#learning-path-heading | Y9: day-0-1 | Z9: locales/en/stages.json › [id=day-0-1].learningPath.main | AA9: stage:day-0-1
A10: R0009 | B10: Roadmap stage | C10: Faith and a fresh start | D10: Learning path: optional resource | E10: Your first 24 hours If you would rather read something shorter, this step covers what matters today and what can wait. | F10: আপনার প্রথম 24 ঘণ্টা আরও ছোট কিছু পড়তে চাইলে এই ধাপে আছে আজ কী জরুরি আর কী অপেক্ষা করতে পারে। | G10: Translated | H10: High | I10: Fiqh ruling; Safety or abuse; External resource or teacher; Tone and pastoral wording | J10: Scholar; Mentor | K10: not tracked | L10: 3 | M10: new-muslim-academy — New Muslim Academy (New Muslim Academy) whyislam — WhyIslam (Islamic Circle of North America) new-muslim-guide — New Muslim Guide (New Muslim Guide) | X10: https://www.revertguide.com/en/roadmap/day-0-1#learning-path-heading | Y10: day-0-1 | Z10: locales/en/stages.json › [id=day-0-1].learningPath.optional | AA10: stage:day-0-1
A11: R0010 | B11: Roadmap stage | C11: Faith and a fresh start | D11: Learning path: guardrails | E11: • No course, no app and no Arabic study is needed today. • Rest is part of this stage. You do not have to learn everything this week. | F11: • আজ কোনো কোর্স, অ্যাপ বা আরবি পড়াশোনার দরকার নেই। • বিশ্রাম এই পর্যায়েরই অংশ। এই সপ্তাহে সব শিখতে হবে না। | G11: Translated | H11: High | I11: Fiqh ruling; Safety or abuse; External resource or teacher; Tone and pastoral wording | J11: Scholar; Mentor | K11: not tracked | L11: 3 | M11: new-muslim-academy — New Muslim Academy (New Muslim Academy) whyislam — WhyIslam (Islamic Circle of North America) new-muslim-guide — New Muslim Guide (New Muslim Guide) | X11: https://www.revertguide.com/en/roadmap/day-0-1#learning-path-heading | Y11: day-0-1 | Z11: locales/en/stages.json › [id=day-0-1].learningPath.guardrails | AA11: stage:day-0-1
A12: R0011 | B12: Roadmap stage | C12: Faith and a fresh start | D12: Good next questions | E12: • What do I do first? → /topics/new-muslim-basics • How do I talk to family? → /topics/family-and-identity | F12: • প্রথমে কী করব? → /topics/new-muslim-basics • পরিবারের সাথে কীভাবে কথা বলব? → /topics/family-and-identity | G12: Translated | H12: High | I12: Fiqh ruling; Safety or abuse; External resource or teacher; Tone and pastoral wording | J12: Scholar; Mentor | K12: not tracked | L12: 3 | M12: new-muslim-academy — New Muslim Academy (New Muslim Academy) whyislam — WhyIslam (Islamic Circle of North America) new-muslim-guide — New Muslim Guide (New Muslim Guide) | X12: https://www.revertguide.com/en/roadmap/day-0-1#good-questions-heading | Y12: day-0-1 | Z12: locales/en/stages.json › [id=day-0-1].goodNextQuestions | AA12: stage:day-0-1
A13: R0012 | B13: Roadmap stage | C13: Getting the basics in place | D13: Title, subtitle and description | E13: Getting the basics in place Week 1 Duration: About 1 week This week is for gentle practice. You learn the shape of prayer, visit or at least phone a masjid, and start using short remembrance. None of it has to be done perfectly. | F13: মূল বিষয়গুলো জায়গামতো বসানো সপ্তাহ 1 Duration: প্রায় 1 সপ্তাহ এই সপ্তাহ নরম অনুশীলনের। আপনি নামাজের গঠন শিখবেন, একটি মসজিদে যাবেন বা অন্তত ফোন করবেন, আর ছোট ছোট জিকির শুরু করবেন। কোনোটিই নিখুঁত হতে হবে না। | G13: Translated | H13: Medium | I13: External resource or teacher; Tone and pastoral wording | J13: Scholar; Mentor | K13: not tracked | L13: 3 | M13: new-muslim-guide — New Muslim Guide (New Muslim Guide) seekersguidance — SeekersGuidance (SeekersGuidance) whyislam — WhyIslam (Islamic Circle of North America) | N13: • Says missing prayers while still learning is normal, and optional practices can wait until the required ones feel steady. • Recommends Quran.com's free 'Seven Days, Seven Verses' Al-Fatihah plan, readable without an account. • Recommends the New Muslim Academy prayer course and says it needs an account and the site uses analytics and an advertising pixel; confirm still true. | X13: https://www.revertguide.com/en/roadmap/week-1 | Y13: week-1 | Z13: locales/en/stages.json › [id=week-1].title/subtitle/description | AA13: stage:week-1
A14: R0013 | B14: Roadmap stage | C14: Getting the basics in place | D14: Main goal | E14: Start praying in a way you can actually keep up, and make one first contact with other Muslims. | F14: এমনভাবে নামাজ শুরু করা যা সত্যিই ধরে রাখতে পারবেন, আর অন্য মুসলিমদের সাথে প্রথম যোগাযোগ করা। | G14: Translated | H14: Medium | I14: External resource or teacher; Tone and pastoral wording | J14: Scholar; Mentor | K14: not tracked | L14: 3 | M14: new-muslim-guide — New Muslim Guide (New Muslim Guide) seekersguidance — SeekersGuidance (SeekersGuidance) whyislam — WhyIslam (Islamic Circle of North America) | X14: https://www.revertguide.com/en/roadmap/week-1#overview-heading | Y14: week-1 | Z14: locales/en/stages.json › [id=week-1].mainGoal | AA14: stage:week-1
A15: R0014 | B15: Roadmap stage | C15: Getting the basics in place | D15: Success looks like | E15: You are praying in some form and you know where to go locally when you need help. | F15: আপনি কোনো না কোনো রূপে নামাজ পড়ছেন, আর সাহায্য দরকার হলে স্থানীয়ভাবে কোথায় যাবেন তা জানেন। | G15: Translated | H15: Medium | I15: External resource or teacher; Tone and pastoral wording | J15: Scholar; Mentor | K15: not tracked | L15: 3 | M15: new-muslim-guide — New Muslim Guide (New Muslim Guide) seekersguidance — SeekersGuidance (SeekersGuidance) whyislam — WhyIslam (Islamic Circle of North America) | X15: https://www.revertguide.com/en/roadmap/week-1#overview-heading | Y15: week-1 | Z15: locales/en/stages.json › [id=week-1].success | AA15: stage:week-1
A16: R0015 | B16: Roadmap stage | C16: Getting the basics in place | D16: Don't worry about | E16: • Your Arabic pronunciation does not have to be right yet. • Missing prayers while you are still learning is normal. • Feeling out of place at the masjid the first few times is normal too. • Optional practices can wait until the required ones feel steady. | F16: • আপনার আরবি উচ্চারণ এখনো ঠিক হতে হবে না। • শেখা চলাকালীন নামাজ ছুটে যাওয়া স্বাভাবিক। • প্রথম কয়েকবার মসজিদে বেমানান লাগাও স্বাভাবিক। • ফরজগুলো স্থির না হওয়া পর্যন্ত নফল আমল অপেক্ষা করতে পারে। | G16: Translated | H16: Medium | I16: External resource or teacher; Tone and pastoral wording | J16: Scholar; Mentor | K16: not tracked | L16: 3 | M16: new-muslim-guide — New Muslim Guide (New Muslim Guide) seekersguidance — SeekersGuidance (SeekersGuidance) whyislam — WhyIslam (Islamic Circle of North America) | X16: https://www.revertguide.com/en/roadmap/week-1#overview-heading | Y16: week-1 | Z16: locales/en/stages.json › [id=week-1].dontWorry | AA16: stage:week-1
A17: R0016 | B17: Roadmap stage | C17: Getting the basics in place | D17: Focus now | E17: • Learn the prayer times and the basic movements. • Find one masjid or one mentor you can ask questions. • Use short dua and dhikr to keep your heart in it. | F17: • নামাজের সময় আর মূল নড়াচড়াগুলো শিখুন। • প্রশ্ন করা যায় এমন একটি মসজিদ বা একজন মেন্টর খুঁজুন। • মন ধরে রাখতে ছোট দোয়া আর জিকির ব্যবহার করুন। | G17: Translated | H17: Medium | I17: External resource or teacher; Tone and pastoral wording | J17: Scholar; Mentor | K17: not tracked | L17: 3 | M17: new-muslim-guide — New Muslim Guide (New Muslim Guide) seekersguidance — SeekersGuidance (SeekersGuidance) whyislam — WhyIslam (Islamic Circle of North America) | X17: https://www.revertguide.com/en/roadmap/week-1#stage-guidance-heading | Y17: week-1 | Z17: locales/en/stages.json › [id=week-1].focusNow | AA17: stage:week-1
A18: R0017 | B18: Roadmap stage | C18: Getting the basics in place | D18: Can wait | E18: • Optional prayers and the finer differences of opinion. • Learning every custom at every masjid. • Big Arabic memorization goals. | F18: • নফল নামাজ আর মতভেদের সূক্ষ্ম খুঁটিনাটি। • প্রতিটি মসজিদের প্রতিটি প্রথা শেখা। • বড় বড় আরবি মুখস্থের লক্ষ্য। | G18: Translated | H18: Medium | I18: External resource or teacher; Tone and pastoral wording | J18: Scholar; Mentor | K18: not tracked | L18: 3 | M18: new-muslim-guide — New Muslim Guide (New Muslim Guide) seekersguidance — SeekersGuidance (SeekersGuidance) whyislam — WhyIslam (Islamic Circle of North America) | X18: https://www.revertguide.com/en/roadmap/week-1#stage-guidance-heading | Y18: week-1 | Z18: locales/en/stages.json › [id=week-1].canWait | AA18: stage:week-1
A19: R0018 | B19: Roadmap stage | C19: Getting the basics in place | D19: Ask for help if | E19: • The basics of prayer still confuse you. • Walking into a masjid makes you nervous. • Work or school makes prayer times hard to hit. | F19: • নামাজের মূল বিষয়গুলো এখনো বিভ্রান্ত করে। • মসজিদে ঢুকতে ভয় ভয় লাগে। • কাজ বা স্কুলের কারণে নামাজের সময় ধরা কঠিন হয়। | G19: Translated | H19: Medium | I19: External resource or teacher; Tone and pastoral wording | J19: Scholar; Mentor | K19: not tracked | L19: 3 | M19: new-muslim-guide — New Muslim Guide (New Muslim Guide) seekersguidance — SeekersGuidance (SeekersGuidance) whyislam — WhyIslam (Islamic Circle of North America) | X19: https://www.revertguide.com/en/roadmap/week-1#stage-guidance-heading | Y19: week-1 | Z19: locales/en/stages.json › [id=week-1].askHelpIf | AA19: stage:week-1
A20: R0019 | B20: Roadmap stage | C20: Getting the basics in place | D20: Learning path: main resource | E20: Seven Days, Seven Verses (Al-Fatihah) A free Quran.com plan that takes one verse of Al-Fatihah a day, word by word with its meaning, in under ten minutes. You can read it without an account. Listen to a clear reciter and repeat after them. Link: https://quran.com/learning-plans/seven-days-seven-verses-living-the-message-of-al-fatihah | F20: Seven Days, Seven Verses (সাত দিনে সূরা আল-ফাতিহার সাত আয়াত) Quran.com-এর একটি বিনামূল্যের পরিকল্পনা, যাতে দিনে সূরা আল-ফাতিহার একটি আয়াত, শব্দে শব্দে অর্থসহ, দশ মিনিটেরও কম সময়ে পড়া হয়। অ্যাকাউন্ট ছাড়াই পড়া যায়। স্পষ্ট তিলাওয়াতকারী কারও পড়া শুনুন আর তার পরে পরে বলুন। | G20: Translated | H20: Medium | I20: External resource or teacher; Tone and pastoral wording | J20: Scholar; Mentor | K20: not tracked | L20: 3 | M20: new-muslim-guide — New Muslim Guide (New Muslim Guide) seekersguidance — SeekersGuidance (SeekersGuidance) whyislam — WhyIslam (Islamic Circle of North America) | X20: https://www.revertguide.com/en/roadmap/week-1#learning-path-heading | Y20: week-1 | Z20: locales/en/stages.json › [id=week-1].learningPath.main | AA20: stage:week-1
A21: R0020 | B21: Roadmap stage | C21: Getting the basics in place | D21: Learning path: optional resource | E21: New Muslim Academy prayer course A free course that starts with wudu and prayer videos and short quizzes. You need an account, and the site uses analytics and an advertising pixel. Link: https://www.newmuslimacademy.org/ | F21: New Muslim Academy-র নামাজ কোর্স একটি বিনামূল্যের কোর্স, যা ওযু আর নামাজের ভিডিও আর ছোট কুইজ দিয়ে শুরু হয়। একটি অ্যাকাউন্ট লাগে, আর সাইটটি অ্যানালিটিক্স আর একটি বিজ্ঞাপনী পিক্সেল ব্যবহার করে। | G21: Translated | H21: Medium | I21: External resource or teacher; Tone and pastoral wording | J21: Scholar; Mentor | K21: not tracked | L21: 3 | M21: new-muslim-guide — New Muslim Guide (New Muslim Guide) seekersguidance — SeekersGuidance (SeekersGuidance) whyislam — WhyIslam (Islamic Circle of North America) | X21: https://www.revertguide.com/en/roadmap/week-1#learning-path-heading | Y21: week-1 | Z21: locales/en/stages.json › [id=week-1].learningPath.optional | AA21: stage:week-1
A22: R0021 | B22: Roadmap stage | C22: Getting the basics in place | D22: Learning path: guardrails | E22: • Learn the shape of the prayer first. Memorising takes weeks, and that is normal. • One course at a time is plenty. | F22: • আগে নামাজের গঠন শিখুন। মুখস্থ করতে কয়েক সপ্তাহ লাগে, আর তা স্বাভাবিক। • এক সময়ে একটি কোর্সই যথেষ্ট। | G22: Translated | H22: Medium | I22: External resource or teacher; Tone and pastoral wording | J22: Scholar; Mentor | K22: not tracked | L22: 3 | M22: new-muslim-guide — New Muslim Guide (New Muslim Guide) seekersguidance — SeekersGuidance (SeekersGuidance) whyislam — WhyIslam (Islamic Circle of North America) | X22: https://www.revertguide.com/en/roadmap/week-1#learning-path-heading | Y22: week-1 | Z22: locales/en/stages.json › [id=week-1].learningPath.guardrails | AA22: stage:week-1
A23: R0022 | B23: Roadmap stage | C23: Getting the basics in place | D23: Good next questions | E23: • How do I visit a masjid? → /topics/masjid-and-community • How do I build prayer slowly? → /topics/prayer | F23: • কীভাবে মসজিদে যাব? → /topics/masjid-and-community • কীভাবে ধীরে ধীরে নামাজ গড়ে তুলব? → /topics/prayer | G23: Translated | H23: Medium | I23: External resource or teacher; Tone and pastoral wording | J23: Scholar; Mentor | K23: not tracked | L23: 3 | M23: new-muslim-guide — New Muslim Guide (New Muslim Guide) seekersguidance — SeekersGuidance (SeekersGuidance) whyislam — WhyIslam (Islamic Circle of North America) | X23: https://www.revertguide.com/en/roadmap/week-1#good-questions-heading | Y23: week-1 | Z23: locales/en/stages.json › [id=week-1].goodNextQuestions | AA23: stage:week-1
A24: R0023 | B24: Roadmap stage | C24: Settling into practice | D24: Title, subtitle and description | E24: Settling into practice Weeks 2-4 Duration: 2-3 weeks Things are starting to settle. Now you add the Quran, work out what to say to family, and find a healthier way to handle the questions that come up without drowning in them. | F24: আমলে থিতু হওয়া সপ্তাহ 2-4 Duration: 2-3 সপ্তাহ সবকিছু থিতু হতে শুরু করেছে। এখন কুরআন যোগ করবেন, পরিবারকে কী বলবেন ঠিক করবেন, আর যে প্রশ্নগুলো আসে সেগুলোয় ডুবে না গিয়ে সামলানোর একটি সুস্থ উপায় খুঁজবেন। | G24: Translated | H24: Medium | I24: External resource or teacher; Tone and pastoral wording | J24: Scholar; Mentor | K24: not tracked | L24: 3 | M24: quran-com — Quran.com (Quran Foundation) yaqeen-institute — Yaqeen Institute (Yaqeen Institute for Islamic Research) seekersguidance — SeekersGuidance (SeekersGuidance) | N24: • Recommends a masjid Arabic-reading class (letters, vowels, joining, short surahs) with The Clear Quran or Abdel Haleem's translation. • Recommends New Muslim Academy live Quran classes: free, evenings Eastern time, brothers and sisters taught separately, sign-up form first. • Ask-for-help triggers include family pressure turning unsafe or controlling and doubts that stop you functioning; no contacts are named. • Guardrails: free before paid, and be careful with one-to-one tutoring from academies you cannot check. | X24: https://www.revertguide.com/en/roadmap/week-2-3 | Y24: week-2-3 | Z24: locales/en/stages.json › [id=week-2-3].title/subtitle/description | AA24: stage:week-2-3
A25: R0024 | B25: Roadmap stage | C25: Settling into practice | D25: Main goal | E25: Start a small Quran habit, get ready for the conversations with family and friends, and learn how to ask a question well. | F25: কুরআনের একটি ছোট অভ্যাস শুরু করা, পরিবার ও বন্ধুদের সাথে আলাপের জন্য তৈরি হওয়া, আর ভালোভাবে প্রশ্ন করা শেখা। | G25: Translated | H25: Medium | I25: External resource or teacher; Tone and pastoral wording | J25: Scholar; Mentor | K25: not tracked | L25: 3 | M25: quran-com — Quran.com (Quran Foundation) yaqeen-institute — Yaqeen Institute (Yaqeen Institute for Islamic Research) seekersguidance — SeekersGuidance (SeekersGuidance) | X25: https://www.revertguide.com/en/roadmap/week-2-3#overview-heading | Y25: week-2-3 | Z25: locales/en/stages.json › [id=week-2-3].mainGoal | AA25: stage:week-2-3
A26: R0025 | B26: Roadmap stage | C26: Settling into practice | D26: Success looks like | E26: You read or listen to some Quran regularly, you have a line or two ready for the people closest to you, and doubts do not knock you over the way they did. | F26: আপনি নিয়মিত কিছু কুরআন পড়েন বা শোনেন, সবচেয়ে কাছের মানুষদের জন্য এক-দুই লাইন তৈরি আছে, আর সংশয় আগের মতো আপনাকে ধরাশায়ী করে না। | G26: Translated | H26: Medium | I26: External resource or teacher; Tone and pastoral wording | J26: Scholar; Mentor | K26: not tracked | L26: 3 | M26: quran-com — Quran.com (Quran Foundation) yaqeen-institute — Yaqeen Institute (Yaqeen Institute for Islamic Research) seekersguidance — SeekersGuidance (SeekersGuidance) | X26: https://www.revertguide.com/en/roadmap/week-2-3#overview-heading | Y26: week-2-3 | Z26: locales/en/stages.json › [id=week-2-3].success | AA26: stage:week-2-3
A27: R0026 | B27: Roadmap stage | C27: Settling into practice | D27: Don't worry about | E27: • Reading Arabic fluently is a long way off for almost everyone. • You will not understand every verse. Neither does anyone else on a first read. • Faith going up and down does not mean it is failing. • You do not have to win any arguments. | F27: • সাবলীলভাবে আরবি পড়া প্রায় সবার জন্যই অনেক দূরের ব্যাপার। • আপনি প্রতিটি আয়াত বুঝবেন না। প্রথমবার পড়ে অন্য কেউও বোঝেন না। • ঈমান ওঠানামা করা মানে তা ব্যর্থ হচ্ছে না। • কোনো তর্কে জিততে হবে না। | G27: Translated | H27: Medium | I27: External resource or teacher; Tone and pastoral wording | J27: Scholar; Mentor | K27: not tracked | L27: 3 | M27: quran-com — Quran.com (Quran Foundation) yaqeen-institute — Yaqeen Institute (Yaqeen Institute for Islamic Research) seekersguidance — SeekersGuidance (SeekersGuidance) | X27: https://www.revertguide.com/en/roadmap/week-2-3#overview-heading | Y27: week-2-3 | Z27: locales/en/stages.json › [id=week-2-3].dontWorry | AA27: stage:week-2-3
A28: R0027 | B28: Roadmap stage | C28: Settling into practice | D28: Focus now | E28: • Read or listen to a little Quran on a regular basis. • Decide who needs to know about your Islam, and when. • Take the hard questions to people who actually know. | F28: • নিয়মিত একটু একটু কুরআন পড়ুন বা শুনুন। • আপনার ইসলাম সম্পর্কে কার জানা দরকার, আর কখন, তা ঠিক করুন। • কঠিন প্রশ্নগুলো তাদের কাছে নিয়ে যান যারা সত্যিই জানেন। | G28: Translated | H28: Medium | I28: External resource or teacher; Tone and pastoral wording | J28: Scholar; Mentor | K28: not tracked | L28: 3 | M28: quran-com — Quran.com (Quran Foundation) yaqeen-institute — Yaqeen Institute (Yaqeen Institute for Islamic Research) seekersguidance — SeekersGuidance (SeekersGuidance) | X28: https://www.revertguide.com/en/roadmap/week-2-3#stage-guidance-heading | Y28: week-2-3 | Z28: locales/en/stages.json › [id=week-2-3].focusNow | AA28: stage:week-2-3
A29: R0028 | B29: Roadmap stage | C29: Settling into practice | D29: Can wait | E29: • Public debates and internet arguments. • Tafsir study and Arabic grammar. • Answering every family objection on the spot. | F29: • প্রকাশ্য বিতর্ক আর ইন্টারনেটের তর্ক। • তাফসির পড়া আর আরবি ব্যাকরণ। • পরিবারের প্রতিটি আপত্তির সঙ্গে সঙ্গে জবাব দেওয়া। | G29: Translated | H29: Medium | I29: External resource or teacher; Tone and pastoral wording | J29: Scholar; Mentor | K29: not tracked | L29: 3 | M29: quran-com — Quran.com (Quran Foundation) yaqeen-institute — Yaqeen Institute (Yaqeen Institute for Islamic Research) seekersguidance — SeekersGuidance (SeekersGuidance) | X29: https://www.revertguide.com/en/roadmap/week-2-3#stage-guidance-heading | Y29: week-2-3 | Z29: locales/en/stages.json › [id=week-2-3].canWait | AA29: stage:week-2-3
A30: R0029 | B30: Roadmap stage | C30: Settling into practice | D30: Ask for help if | E30: • Family pressure turns unsafe or controlling. • Doubts are stopping you from functioning. • You cannot tell which sources are reliable. | F30: • পরিবারের চাপ অনিরাপদ বা নিয়ন্ত্রণমূলক হয়ে ওঠে। • সংশয় আপনাকে দৈনন্দিন কাজ করতে দিচ্ছে না। • কোন সূত্রগুলো নির্ভরযোগ্য বুঝতে পারছেন না। | G30: Translated | H30: High | I30: Safety or abuse; External resource or teacher; Tone and pastoral wording | J30: Scholar; Mentor | K30: not tracked | L30: 3 | M30: quran-com — Quran.com (Quran Foundation) yaqeen-institute — Yaqeen Institute (Yaqeen Institute for Islamic Research) seekersguidance — SeekersGuidance (SeekersGuidance) | X30: https://www.revertguide.com/en/roadmap/week-2-3#stage-guidance-heading | Y30: week-2-3 | Z30: locales/en/stages.json › [id=week-2-3].askHelpIf | AA30: stage:week-2-3
A31: R0030 | B31: Roadmap stage | C31: Settling into practice | D31: Learning path: main resource | E31: A beginners' Quran reading class at a masjid Ask your local masjid whether it runs a class for learning to read Arabic. Most start with the letters, then the vowel marks, then joining letters, then short surahs. Alongside it, pick one translation, such as The Clear Quran or Abdel Haleem's, and read a little each day. | F31: মসজিদে নতুনদের কুরআন পড়ার ক্লাস আপনার এলাকার মসজিদে জিজ্ঞেস করুন আরবি পড়া শেখার কোনো ক্লাস চালায় কি না। বেশিরভাগ ক্লাস অক্ষর দিয়ে শুরু হয়, তারপর স্বরচিহ্ন, তারপর অক্ষর জোড়া, তারপর ছোট সূরা। এর পাশাপাশি একটি অনুবাদ বেছে নিন, যেমন The Clear Quran বা আবদেল হালিমের অনুবাদ, আর প্রতিদিন একটু পড়ুন। | G31: Translated | H31: Medium | I31: Quran or hadith citation; External resource or teacher; Tone and pastoral wording | J31: Scholar; Mentor | K31: not tracked | L31: 3 | M31: quran-com — Quran.com (Quran Foundation) yaqeen-institute — Yaqeen Institute (Yaqeen Institute for Islamic Research) seekersguidance — SeekersGuidance (SeekersGuidance) | X31: https://www.revertguide.com/en/roadmap/week-2-3#learning-path-heading | Y31: week-2-3 | Z31: locales/en/stages.json › [id=week-2-3].learningPath.main | AA31: stage:week-2-3
A32: R0031 | B32: Roadmap stage | C32: Settling into practice | D32: Learning path: optional resource | E32: New Muslim Academy live Quran classes Free small-group classes online in the evening, Eastern time, with brothers and sisters taught separately. They cover Al-Fatihah and short surahs. You fill in a sign-up form first. Link: https://www.newmuslimacademy.org/sisters-quran-classes/ | F32: New Muslim Academy-র লাইভ কুরআন ক্লাস সন্ধ্যায়, পূর্বাঞ্চলীয় সময়ে, অনলাইনে ছোট দলের বিনামূল্যের ক্লাস, ভাই আর বোনদের আলাদাভাবে পড়ানো হয়। সূরা আল-ফাতিহা আর ছোট সূরাগুলো শেখানো হয়। আগে একটি নিবন্ধন ফর্ম পূরণ করতে হয়। | G32: Translated | H32: Medium | I32: Quran or hadith citation; External resource or teacher; Tone and pastoral wording | J32: Scholar; Mentor | K32: not tracked | L32: 3 | M32: quran-com — Quran.com (Quran Foundation) yaqeen-institute — Yaqeen Institute (Yaqeen Institute for Islamic Research) seekersguidance — SeekersGuidance (SeekersGuidance) | X32: https://www.revertguide.com/en/roadmap/week-2-3#learning-path-heading | Y32: week-2-3 | Z32: locales/en/stages.json › [id=week-2-3].learningPath.optional | AA32: stage:week-2-3
A33: R0032 | B33: Roadmap stage | C33: Settling into practice | D33: Learning path: guardrails | E33: • Free before paid. You do not need a paid online tutor to start. • Be careful with one-to-one tutoring from academies you cannot check. | F33: • টাকার আগে বিনামূল্যেরটা। শুরু করতে টাকা দিয়ে অনলাইন শিক্ষক লাগবে না। • যাচাই করতে পারেন না এমন একাডেমির একান্ত টিউশনের ব্যাপারে সাবধান থাকুন। | G33: Translated | H33: Medium | I33: External resource or teacher; Tone and pastoral wording | J33: Scholar; Mentor | K33: not tracked | L33: 3 | M33: quran-com — Quran.com (Quran Foundation) yaqeen-institute — Yaqeen Institute (Yaqeen Institute for Islamic Research) seekersguidance — SeekersGuidance (SeekersGuidance) | X33: https://www.revertguide.com/en/roadmap/week-2-3#learning-path-heading | Y33: week-2-3 | Z33: locales/en/stages.json › [id=week-2-3].learningPath.guardrails | AA33: stage:week-2-3
A34: R0033 | B34: Roadmap stage | C34: Settling into practice | D34: Good next questions | E34: • What if I have doubts? → /topics/questions-and-doubts • How do I protect family ties? → /topics/family-and-identity | F34: • সংশয় এলে কী করব? → /topics/questions-and-doubts • কীভাবে আত্মীয়তার সম্পর্ক রক্ষা করব? → /topics/family-and-identity | G34: Translated | H34: Medium | I34: External resource or teacher; Tone and pastoral wording | J34: Scholar; Mentor | K34: not tracked | L34: 3 | M34: quran-com — Quran.com (Quran Foundation) yaqeen-institute — Yaqeen Institute (Yaqeen Institute for Islamic Research) seekersguidance — SeekersGuidance (SeekersGuidance) | X34: https://www.revertguide.com/en/roadmap/week-2-3#good-questions-heading | Y34: week-2-3 | Z34: locales/en/stages.json › [id=week-2-3].goodNextQuestions | AA34: stage:week-2-3
A35: R0034 | B35: Roadmap stage | C35: Islam in daily life | D35: Title, subtitle and description | E35: Islam in daily life Months 2-3 Duration: 1-2 months Here Islam works its way into ordinary days: what you eat, how you get ready for fasting, how you dress, and where you draw practical lines. Set the pace so you can keep it up. | F35: দৈনন্দিন জীবনে ইসলাম মাস 2-3 Duration: 1-2 মাস এখানে ইসলাম সাধারণ দিনগুলোর ভেতরে ঢুকে পড়ে: কী খান, রোজার জন্য কীভাবে তৈরি হন, কী পরেন, আর কোথায় ব্যবহারিক সীমা টানেন। এমন গতি ঠিক করুন যা ধরে রাখতে পারবেন। | G35: Translated | H35: Medium | I35: External resource or teacher; Tone and pastoral wording | J35: Scholar; Mentor | K35: not tracked | L35: 2 | M35: new-muslim-guide — New Muslim Guide (New Muslim Guide) seekersguidance — SeekersGuidance (SeekersGuidance) | N35: • Recommends New Muslim Academy core courses or SeekersGuidance's free live 'Essentials of Faith, Worship, and Spirituality', Saturdays 10:00 Eastern; confirm the schedule. • Recommends Quran.com learning plans for short surahs such as Al-Ikhlas, Al-Falaq and An-Nas. • Ask-for-help triggers: food or clothing pressure risking safety at home, a medical condition affecting fasting, a ruling on work, school or money. • Guardrail: choose a prayer times app that keeps your location on your phone and has no ads. | X35: https://www.revertguide.com/en/roadmap/month-1-2 | Y35: month-1-2 | Z35: locales/en/stages.json › [id=month-1-2].title/subtitle/description | AA35: stage:month-1-2
A36: R0035 | B36: Roadmap stage | C36: Islam in daily life | D36: Main goal | E36: Learn the halal basics, get ready for fasting, and treat modesty as something you grow into rather than something to panic about. | F36: হালালের মূল বিষয় শেখা, রোজার জন্য তৈরি হওয়া, আর শালীনতাকে আতঙ্কের বিষয় না ভেবে ধীরে ধীরে অভ্যস্ত হওয়ার বিষয় হিসেবে দেখা। | G36: Translated | H36: Medium | I36: Mental health; External resource or teacher; Tone and pastoral wording | J36: Scholar; Mentor; Mental health professional | K36: not tracked | L36: 2 | M36: new-muslim-guide — New Muslim Guide (New Muslim Guide) seekersguidance — SeekersGuidance (SeekersGuidance) | X36: https://www.revertguide.com/en/roadmap/month-1-2#overview-heading | Y36: month-1-2 | Z36: locales/en/stages.json › [id=month-1-2].mainGoal | AA36: stage:month-1-2
A37: R0036 | B37: Roadmap stage | C37: Islam in daily life | D37: Success looks like | E37: You can shop and order food without stress, you know how fasting works at a beginner level, and you can tell which lifestyle questions need a local answer. | F37: চাপ ছাড়াই বাজার করতে আর খাবার অর্ডার দিতে পারেন, নতুনদের স্তরে রোজা কীভাবে কাজ করে জানেন, আর বুঝতে পারেন জীবনযাপনের কোন প্রশ্নের স্থানীয় উত্তর দরকার। | G37: Translated | H37: Medium | I37: External resource or teacher; Tone and pastoral wording | J37: Scholar; Mentor | K37: not tracked | L37: 2 | M37: new-muslim-guide — New Muslim Guide (New Muslim Guide) seekersguidance — SeekersGuidance (SeekersGuidance) | X37: https://www.revertguide.com/en/roadmap/month-1-2#overview-heading | Y37: month-1-2 | Z37: locales/en/stages.json › [id=month-1-2].success | AA37: stage:month-1-2
A38: R0037 | B38: Roadmap stage | C38: Islam in daily life | D38: Don't worry about | E38: • Your whole pantry does not have to change overnight. • One unclear ingredient is not an emergency. • How fast someone else changed their clothing has nothing to do with you. • Random online comments are not the place to sort out questions about fasting and hardship. | F38: • রাতারাতি পুরো রান্নাঘরের মজুত বদলাতে হবে না। • একটি অস্পষ্ট উপাদান জরুরি অবস্থা নয়। • অন্য কেউ কত দ্রুত পোশাক বদলেছেন, তার সাথে আপনার কোনো সম্পর্ক নেই। • রোজা আর কষ্টকর অবস্থা নিয়ে প্রশ্নের মীমাংসার জায়গা অনলাইনের এলোমেলো মন্তব্য নয়। | G38: Translated | H38: High | I38: Safety or abuse; External resource or teacher; Tone and pastoral wording | J38: Scholar; Mentor | K38: not tracked | L38: 2 | M38: new-muslim-guide — New Muslim Guide (New Muslim Guide) seekersguidance — SeekersGuidance (SeekersGuidance) | X38: https://www.revertguide.com/en/roadmap/month-1-2#overview-heading | Y38: month-1-2 | Z38: locales/en/stages.json › [id=month-1-2].dontWorry | AA38: stage:month-1-2
A39: R0038 | B39: Roadmap stage | C39: Islam in daily life | D39: Focus now | E39: • Steer clear of the clearly haram foods and get comfortable with simple halal choices. • Learn how fasting works before Ramadan or your first voluntary fast. • Change one thing at a time with clothing, and keep it sustainable. | F39: • স্পষ্টভাবে হারাম খাবার থেকে দূরে থাকুন, আর সহজ হালাল বিকল্পে স্বচ্ছন্দ হোন। • রমজান বা প্রথম নফল রোজার আগে রোজা কীভাবে কাজ করে শিখুন। • পোশাকে এক সময়ে একটি জিনিস বদলান, আর তা টেকসই রাখুন। | G39: Translated | H39: Medium | I39: External resource or teacher; Tone and pastoral wording | J39: Scholar; Mentor | K39: not tracked | L39: 2 | M39: new-muslim-guide — New Muslim Guide (New Muslim Guide) seekersguidance — SeekersGuidance (SeekersGuidance) | X39: https://www.revertguide.com/en/roadmap/month-1-2#stage-guidance-heading | Y39: month-1-2 | Z39: locales/en/stages.json › [id=month-1-2].focusNow | AA39: stage:month-1-2
A40: R0039 | B40: Roadmap stage | C40: Islam in daily life | D40: Can wait | E40: • Arguments about certification standards. • Detailed zakat and money rulings. • Clothing debates between different cultures. | F40: • প্রত্যয়নের মানদণ্ড নিয়ে তর্ক। • যাকাত আর টাকাপয়সার বিস্তারিত বিধান। • বিভিন্ন সংস্কৃতির মধ্যে পোশাক নিয়ে বিতর্ক। | G40: Translated | H40: Medium | I40: Financial (zakat, riba, money); External resource or teacher; Tone and pastoral wording | J40: Scholar; Mentor | K40: not tracked | L40: 2 | M40: new-muslim-guide — New Muslim Guide (New Muslim Guide) seekersguidance — SeekersGuidance (SeekersGuidance) | X40: https://www.revertguide.com/en/roadmap/month-1-2#stage-guidance-heading | Y40: month-1-2 | Z40: locales/en/stages.json › [id=month-1-2].canWait | AA40: stage:month-1-2
A41: R0040 | B41: Roadmap stage | C41: Islam in daily life | D41: Ask for help if | E41: • Pressure about food or clothing is putting your safety at home at risk. • A medical condition might affect fasting. • You need a ruling about work, school, or money. | F41: • খাবার বা পোশাক নিয়ে চাপ বাড়িতে আপনার নিরাপত্তাকে ঝুঁকিতে ফেলছে। • কোনো অসুখ রোজায় প্রভাব ফেলতে পারে। • কাজ, স্কুল বা টাকাপয়সা নিয়ে বিধান দরকার। | G41: Translated | H41: Medium | I41: External resource or teacher; Tone and pastoral wording | J41: Scholar; Mentor | K41: not tracked | L41: 2 | M41: new-muslim-guide — New Muslim Guide (New Muslim Guide) seekersguidance — SeekersGuidance (SeekersGuidance) | X41: https://www.revertguide.com/en/roadmap/month-1-2#stage-guidance-heading | Y41: month-1-2 | Z41: locales/en/stages.json › [id=month-1-2].askHelpIf | AA41: stage:month-1-2
A42: R0041 | B42: Roadmap stage | C42: Islam in daily life | D42: Learning path: main resource | E42: One structured course Finish the New Muslim Academy core courses, or join SeekersGuidance's free live course Essentials of Faith, Worship, and Spirituality, taught on Saturdays at 10:00 Eastern time. Pick one, not both. Link: https://seekersguidance.org/live | F42: একটি গোছানো কোর্স New Muslim Academy-র মূল কোর্সগুলো শেষ করুন, অথবা SeekersGuidance-এর বিনামূল্যের লাইভ কোর্স Essentials of Faith, Worship, and Spirituality-তে যোগ দিন, যা শনিবার পূর্বাঞ্চলীয় সময় সকাল 10:00টায় পড়ানো হয়। একটি বেছে নিন, দুটো নয়। | G42: Translated | H42: Medium | I42: External resource or teacher; Tone and pastoral wording | J42: Scholar; Mentor | K42: not tracked | L42: 2 | M42: new-muslim-guide — New Muslim Guide (New Muslim Guide) seekersguidance — SeekersGuidance (SeekersGuidance) | X42: https://www.revertguide.com/en/roadmap/month-1-2#learning-path-heading | Y42: month-1-2 | Z42: locales/en/stages.json › [id=month-1-2].learningPath.main | AA42: stage:month-1-2
A43: R0042 | B43: Roadmap stage | C43: Islam in daily life | D43: Learning path: optional resource | E43: Quran.com learning plans for short surahs Free plans on the short surahs many people recite in prayer, such as Al-Ikhlas, Al-Falaq and An-Nas, so you know what you are saying. Link: https://quran.com/learning-plans | F43: ছোট সূরাগুলোর জন্য Quran.com-এর শেখার পরিকল্পনা নামাজে অনেকে যে ছোট সূরাগুলো পড়েন, যেমন আল-ইখলাস, আল-ফালাক আর আন-নাস, সেগুলোর বিনামূল্যের পরিকল্পনা, যাতে জানেন আপনি কী বলছেন। | G43: Translated | H43: Medium | I43: Quran or hadith citation; External resource or teacher; Tone and pastoral wording | J43: Scholar; Mentor | K43: not tracked | L43: 2 | M43: new-muslim-guide — New Muslim Guide (New Muslim Guide) seekersguidance — SeekersGuidance (SeekersGuidance) | X43: https://www.revertguide.com/en/roadmap/month-1-2#learning-path-heading | Y43: month-1-2 | Z43: locales/en/stages.json › [id=month-1-2].learningPath.optional | AA43: stage:month-1-2
A44: R0043 | B44: Roadmap stage | C44: Islam in daily life | D44: Learning path: guardrails | E44: • Only one course at a time. • If you want a prayer times app, choose one that keeps your location on your phone and has no ads. | F44: • এক সময়ে শুধু একটি কোর্স। • নামাজের সময়ের অ্যাপ চাইলে এমন একটি বেছে নিন যা আপনার অবস্থান ফোনেই রাখে আর বিজ্ঞাপন দেখায় না। | G44: Translated | H44: Medium | I44: External resource or teacher; Tone and pastoral wording | J44: Scholar; Mentor | K44: not tracked | L44: 2 | M44: new-muslim-guide — New Muslim Guide (New Muslim Guide) seekersguidance — SeekersGuidance (SeekersGuidance) | X44: https://www.revertguide.com/en/roadmap/month-1-2#learning-path-heading | Y44: month-1-2 | Z44: locales/en/stages.json › [id=month-1-2].learningPath.guardrails | AA44: stage:month-1-2
A45: R0044 | B45: Roadmap stage | C45: Islam in daily life | D45: Good next questions | E45: • How do I eat halal in practice? → /topics/halal-living • How do I approach modesty? → /topics/modesty | F45: • বাস্তবে কীভাবে হালাল খাব? → /topics/halal-living • শালীনতাকে কীভাবে দেখব? → /topics/modesty | G45: Translated | H45: Medium | I45: External resource or teacher; Tone and pastoral wording | J45: Scholar; Mentor | K45: not tracked | L45: 2 | M45: new-muslim-guide — New Muslim Guide (New Muslim Guide) seekersguidance — SeekersGuidance (SeekersGuidance) | X45: https://www.revertguide.com/en/roadmap/month-1-2#good-questions-heading | Y45: month-1-2 | Z45: locales/en/stages.json › [id=month-1-2].goodNextQuestions | AA45: stage:month-1-2
A46: R0045 | B46: Roadmap stage | C46: Character and steady learning | D46: Title, subtitle and description | E46: Character and steady learning Months 4-6 Duration: 2-3 months The practice is starting to feel familiar. This stage is about character, learning from people worth learning from, and asking better questions so you keep growing without spinning out. | F46: চরিত্র আর স্থির শেখা মাস 4-6 Duration: 2-3 মাস আমলগুলো পরিচিত লাগতে শুরু করেছে। এই পর্যায় চরিত্র, শেখার মতো মানুষদের কাছ থেকে শেখা, আর আরও ভালো প্রশ্ন করা নিয়ে, যাতে দিশেহারা না হয়ে বেড়ে উঠতে থাকেন। | G46: Translated | H46: Medium | I46: External resource or teacher; Tone and pastoral wording | J46: Scholar; Mentor | K46: not tracked | L46: 3 | M46: seekersguidance — SeekersGuidance (SeekersGuidance) yaqeen-institute — Yaqeen Institute (Yaqeen Institute for Islamic Research) sunnah-com — Sunnah.com (Sunnah.com) | N46: • Recommends Yaqeen Institute's free ebook 'Qur'an 30 for 30: Thematic Tafsir' by Dr. Omar Suleiman and Sh. Ismail Kamdar. • Recommends a local halaqa; guardrails say learn from a teacher you can meet or check, and skip debate channels in the first months. | X46: https://www.revertguide.com/en/roadmap/month-3-6 | Y46: month-3-6 | Z46: locales/en/stages.json › [id=month-3-6].title/subtitle/description | AA46: stage:month-3-6
A47: R0046 | B47: Roadmap stage | C47: Character and steady learning | D47: Main goal | E47: Work on your character, learn how to put a question to someone qualified, and settle on a steady way to keep learning. | F47: চরিত্র নিয়ে কাজ করা, যোগ্য কারও কাছে প্রশ্ন তুলে ধরা শেখা, আর শেখা চালিয়ে যাওয়ার একটি স্থির পথ ঠিক করা। | G47: Translated | H47: Medium | I47: External resource or teacher; Tone and pastoral wording | J47: Scholar; Mentor | K47: not tracked | L47: 3 | M47: seekersguidance — SeekersGuidance (SeekersGuidance) yaqeen-institute — Yaqeen Institute (Yaqeen Institute for Islamic Research) sunnah-com — Sunnah.com (Sunnah.com) | X47: https://www.revertguide.com/en/roadmap/month-3-6#overview-heading | Y47: month-3-6 | Z47: locales/en/stages.json › [id=month-3-6].mainGoal | AA47: stage:month-3-6
A48: R0047 | B48: Roadmap stage | C48: Character and steady learning | D48: Success looks like | E48: You can see a difference in how you treat people day to day, and you know where your learning goes next without it swallowing you. | F48: প্রতিদিন মানুষের সাথে আচরণে পার্থক্য দেখতে পান, আর জানেন আপনার শেখা এরপর কোন দিকে যাবে, তা আপনাকে গ্রাস না করেই। | G48: Translated | H48: Medium | I48: External resource or teacher; Tone and pastoral wording | J48: Scholar; Mentor | K48: not tracked | L48: 3 | M48: seekersguidance — SeekersGuidance (SeekersGuidance) yaqeen-institute — Yaqeen Institute (Yaqeen Institute for Islamic Research) sunnah-com — Sunnah.com (Sunnah.com) | X48: https://www.revertguide.com/en/roadmap/month-3-6#overview-heading | Y48: month-3-6 | Z48: locales/en/stages.json › [id=month-3-6].success | AA48: stage:month-3-6
A49: R0048 | B49: Roadmap stage | C49: Character and steady learning | D49: Don't worry about | E49: • You are not trying to become a scholar. • You will not know every opinion on every question. • Questions still coming up is a sign you are paying attention. • Islam is not meant to run as constant self-criticism. | F49: • আপনি আলেম হওয়ার চেষ্টা করছেন না। • প্রতিটি প্রশ্নে প্রতিটি মত আপনি জানবেন না। • প্রশ্ন আসতে থাকা মানে আপনি মনোযোগ দিচ্ছেন। • ইসলাম সারাক্ষণ আত্মসমালোচনা হিসেবে চলার জন্য নয়। | G49: Translated | H49: Medium | I49: External resource or teacher; Tone and pastoral wording | J49: Scholar; Mentor | K49: not tracked | L49: 3 | M49: seekersguidance — SeekersGuidance (SeekersGuidance) yaqeen-institute — Yaqeen Institute (Yaqeen Institute for Islamic Research) sunnah-com — Sunnah.com (Sunnah.com) | X49: https://www.revertguide.com/en/roadmap/month-3-6#overview-heading | Y49: month-3-6 | Z49: locales/en/stages.json › [id=month-3-6].dontWorry | AA49: stage:month-3-6
A50: R0049 | B50: Roadmap stage | C50: Character and steady learning | D50: Focus now | E50: • Be honest, be patient, keep praying, and treat people well. • Learn how to put a personal question into clear words. • Pick one class, one teacher, or one book and stay with it. | F50: • সৎ থাকুন, ধৈর্য ধরুন, নামাজ চালিয়ে যান, আর মানুষের সাথে ভালো আচরণ করুন। • ব্যক্তিগত প্রশ্ন কীভাবে স্পষ্ট ভাষায় তুলে ধরবেন শিখুন। • একটি ক্লাস, একজন শিক্ষক বা একটি বই বেছে নিয়ে তাতে লেগে থাকুন। | G50: Translated | H50: Medium | I50: External resource or teacher; Tone and pastoral wording | J50: Scholar; Mentor | K50: not tracked | L50: 3 | M50: seekersguidance — SeekersGuidance (SeekersGuidance) yaqeen-institute — Yaqeen Institute (Yaqeen Institute for Islamic Research) sunnah-com — Sunnah.com (Sunnah.com) | X50: https://www.revertguide.com/en/roadmap/month-3-6#stage-guidance-heading | Y50: month-3-6 | Z50: locales/en/stages.json › [id=month-3-6].focusNow | AA50: stage:month-3-6
A51: R0050 | B51: Roadmap stage | C51: Character and steady learning | D51: Can wait | E51: • Advanced theology and legal disagreements. • Keeping up with every speaker online. • Having an answer ready for every controversial topic. | F51: • উচ্চতর আকিদা আর ফিকহি মতভেদ। • অনলাইনের প্রত্যেক বক্তার সাথে তাল মেলানো। • প্রতিটি বিতর্কিত বিষয়ের উত্তর তৈরি রাখা। | G51: Translated | H51: Medium | I51: Legal (Canada); External resource or teacher; Tone and pastoral wording | J51: Scholar; Mentor; Legal professional | K51: not tracked | L51: 3 | M51: seekersguidance — SeekersGuidance (SeekersGuidance) yaqeen-institute — Yaqeen Institute (Yaqeen Institute for Islamic Research) sunnah-com — Sunnah.com (Sunnah.com) | X51: https://www.revertguide.com/en/roadmap/month-3-6#stage-guidance-heading | Y51: month-3-6 | Z51: locales/en/stages.json › [id=month-3-6].canWait | AA51: stage:month-3-6
A52: R0051 | B52: Roadmap stage | C52: Character and steady learning | D52: Ask for help if | E52: • You are getting conflicting answers and feel stuck. • A ruling affects your family, marriage, work, or money. • Something about your community feels pressuring or unhealthy. | F52: • পরস্পরবিরোধী উত্তর পাচ্ছেন আর আটকে গেছেন মনে হচ্ছে। • কোনো বিধান আপনার পরিবার, বিয়ে, কাজ বা টাকাপয়সায় প্রভাব ফেলে। • আপনার কমিউনিটির কিছু চাপের বা অসুস্থ মনে হয়। | G52: Translated | H52: Medium | I52: Family, marriage or intimacy; External resource or teacher; Tone and pastoral wording | J52: Scholar; Mentor | K52: not tracked | L52: 3 | M52: seekersguidance — SeekersGuidance (SeekersGuidance) yaqeen-institute — Yaqeen Institute (Yaqeen Institute for Islamic Research) sunnah-com — Sunnah.com (Sunnah.com) | X52: https://www.revertguide.com/en/roadmap/month-3-6#stage-guidance-heading | Y52: month-3-6 | Z52: locales/en/stages.json › [id=month-3-6].askHelpIf | AA52: stage:month-3-6
A53: R0052 | B53: Roadmap stage | C53: Character and steady learning | D53: Learning path: main resource | E53: A local halaqa or masjid class A regular study circle with a teacher you can meet and ask questions. Ask at your masjid what runs each week and whether it suits beginners. | F53: স্থানীয় হালাকা বা মসজিদের ক্লাস এমন শিক্ষকের সাথে নিয়মিত পাঠচক্র, যার সাথে দেখা করতে আর প্রশ্ন করতে পারবেন। আপনার মসজিদে জিজ্ঞেস করুন প্রতি সপ্তাহে কী হয় আর তা নতুনদের উপযোগী কি না। | G53: Translated | H53: Medium | I53: External resource or teacher; Tone and pastoral wording | J53: Scholar; Mentor | K53: not tracked | L53: 3 | M53: seekersguidance — SeekersGuidance (SeekersGuidance) yaqeen-institute — Yaqeen Institute (Yaqeen Institute for Islamic Research) sunnah-com — Sunnah.com (Sunnah.com) | X53: https://www.revertguide.com/en/roadmap/month-3-6#learning-path-heading | Y53: month-3-6 | Z53: locales/en/stages.json › [id=month-3-6].learningPath.main | AA53: stage:month-3-6
A54: R0053 | B54: Roadmap stage | C54: Character and steady learning | D54: Learning path: optional resource | E54: Qur'an 30 for 30: Thematic Tafsir A free ebook from Yaqeen Institute by Dr. Omar Suleiman and Sh. Ismail Kamdar. It gives an overview of each of the 30 parts of the Quran. Link: https://yaqeeninstitute.ca/read/books/quran-30-for-30-thematic-tafsir | F54: Qur'an 30 for 30: Thematic Tafsir (বিষয়ভিত্তিক তাফসির) Yaqeen Institute-এর একটি বিনামূল্যের ই-বুক, ড. ওমর সুলাইমান আর শায়খ ইসমাইল কামদারের লেখা। এতে কুরআনের 30টি পারার প্রতিটির সংক্ষিপ্ত পরিচিতি আছে। | G54: Translated | H54: Medium | I54: Quran or hadith citation; External resource or teacher; Tone and pastoral wording | J54: Scholar; Mentor | K54: not tracked | L54: 3 | M54: seekersguidance — SeekersGuidance (SeekersGuidance) yaqeen-institute — Yaqeen Institute (Yaqeen Institute for Islamic Research) sunnah-com — Sunnah.com (Sunnah.com) | X54: https://www.revertguide.com/en/roadmap/month-3-6#learning-path-heading | Y54: month-3-6 | Z54: locales/en/stages.json › [id=month-3-6].learningPath.optional | AA54: stage:month-3-6
A55: R0054 | B55: Roadmap stage | C55: Character and steady learning | D55: Learning path: guardrails | E55: • Learn from a teacher you can meet or check before a stranger online. • Skip debate channels in these first months. | F55: • অনলাইনের অচেনা কারও আগে এমন শিক্ষকের কাছ থেকে শিখুন যার সাথে দেখা করতে বা যাকে যাচাই করতে পারেন। • এই প্রথম মাসগুলোতে বিতর্কের চ্যানেল এড়িয়ে চলুন। | G55: Translated | H55: Medium | I55: External resource or teacher; Tone and pastoral wording | J55: Scholar; Mentor | K55: not tracked | L55: 3 | M55: seekersguidance — SeekersGuidance (SeekersGuidance) yaqeen-institute — Yaqeen Institute (Yaqeen Institute for Islamic Research) sunnah-com — Sunnah.com (Sunnah.com) | X55: https://www.revertguide.com/en/roadmap/month-3-6#learning-path-heading | Y55: month-3-6 | Z55: locales/en/stages.json › [id=month-3-6].learningPath.guardrails | AA55: stage:month-3-6
A56: R0055 | B56: Roadmap stage | C56: Character and steady learning | D56: Good next questions | E56: • How do I ask good questions? → /topics/questions-and-doubts • Who was the Prophet? → /topics/prophet-muhammad | F56: • কীভাবে ভালো প্রশ্ন করব? → /topics/questions-and-doubts • নবী (সা.) কে ছিলেন? → /topics/prophet-muhammad | G56: Translated | H56: Medium | I56: External resource or teacher; Tone and pastoral wording | J56: Scholar; Mentor | K56: not tracked | L56: 3 | M56: seekersguidance — SeekersGuidance (SeekersGuidance) yaqeen-institute — Yaqeen Institute (Yaqeen Institute for Islamic Research) sunnah-com — Sunnah.com (Sunnah.com) | X56: https://www.revertguide.com/en/roadmap/month-3-6#good-questions-heading | Y56: month-3-6 | Z56: locales/en/stages.json › [id=month-3-6].goodNextQuestions | AA56: stage:month-3-6
A57: R0056 | B57: Roadmap stage | C57: Growth over a lifetime | D57: Title, subtitle and description | E57: Growth over a lifetime Beyond 6 months Duration: Ongoing Islam is a lifelong path. This stage looks at the bigger responsibilities ahead, zakat and Hajj, while keeping your learning at a pace you can hold. | F57: সারাজীবনের বেড়ে ওঠা 6 মাসের পরে Duration: চলমান ইসলাম সারাজীবনের পথ। এই পর্যায় সামনের বড় দায়িত্বগুলোর দিকে তাকায়, যাকাত আর হজ, আর আপনার শেখাকে এমন গতিতে রাখে যা ধরে রাখতে পারবেন। | G57: Translated | H57: High | I57: Fiqh ruling; Financial (zakat, riba, money); External resource or teacher | J57: Scholar; Mentor | K57: not tracked | L57: 3 | M57: quran-zakat-9-60 — Quran 9:60 - Zakat recipient categories (Quran.com) cra-charities-listing — List of charities and other qualified donees (Canada Revenue Agency) seekersguidance — SeekersGuidance (SeekersGuidance) | N57: • Says Hajj is not owed until you are able to go, and zakat does not apply below the threshold (nisab). • Recommends MAC eLearning, free online courses from the Muslim Association of Canada. • Recommends Tafsir Ibn Kathir abridged (30th part), a paid Darussalam print book. | X57: https://www.revertguide.com/en/roadmap/month-6-plus | Y57: month-6-plus | Z57: locales/en/stages.json › [id=month-6-plus].title/subtitle/description | AA57: stage:month-6-plus
A58: R0057 | B58: Roadmap stage | C58: Growth over a lifetime | D58: Main goal | E58: Get a picture of the pillars still ahead of you and keep learning with people who are qualified to teach. | F58: সামনে যে স্তম্ভগুলো বাকি তার একটি ছবি পাওয়া, আর শেখানোর যোগ্য মানুষদের সাথে শেখা চালিয়ে যাওয়া। | G58: Translated | H58: High | I58: Fiqh ruling; Financial (zakat, riba, money); External resource or teacher | J58: Scholar; Mentor | K58: not tracked | L58: 3 | M58: quran-zakat-9-60 — Quran 9:60 - Zakat recipient categories (Quran.com) cra-charities-listing — List of charities and other qualified donees (Canada Revenue Agency) seekersguidance — SeekersGuidance (SeekersGuidance) | X58: https://www.revertguide.com/en/roadmap/month-6-plus#overview-heading | Y58: month-6-plus | Z58: locales/en/stages.json › [id=month-6-plus].mainGoal | AA58: stage:month-6-plus
A59: R0058 | B59: Roadmap stage | C59: Growth over a lifetime | D59: Success looks like | E59: You know zakat and Hajj become real obligations once the conditions apply to you, and you know to have your own situation checked by someone qualified. | F59: আপনি জানেন শর্তগুলো আপনার ক্ষেত্রে প্রযোজ্য হলে যাকাত আর হজ সত্যিকারের দায়িত্ব হয়ে যায়, আর জানেন নিজের অবস্থা যোগ্য কাউকে দিয়ে যাচাই করিয়ে নিতে হবে। | G59: Translated | H59: High | I59: Fiqh ruling; Financial (zakat, riba, money); External resource or teacher | J59: Scholar; Mentor | K59: not tracked | L59: 3 | M59: quran-zakat-9-60 — Quran 9:60 - Zakat recipient categories (Quran.com) cra-charities-listing — List of charities and other qualified donees (Canada Revenue Agency) seekersguidance — SeekersGuidance (SeekersGuidance) | X59: https://www.revertguide.com/en/roadmap/month-6-plus#overview-heading | Y59: month-6-plus | Z59: locales/en/stages.json › [id=month-6-plus].success | AA59: stage:month-6-plus
A60: R0059 | B60: Roadmap stage | C60: Growth over a lifetime | D60: Don't worry about | E60: • Hajj is not owed until you are able to go. • Zakat does not apply if you are under the threshold. • There is no point where you finish the religion. You keep growing for the rest of your life. | F60: • যাওয়ার সামর্থ্য না হওয়া পর্যন্ত হজ ফরজ নয়। • সীমার নিচে থাকলে যাকাত প্রযোজ্য নয়। • এমন কোনো মুহূর্ত নেই যখন দ্বীন শেষ করে ফেলবেন। সারাজীবন বেড়ে উঠতে থাকবেন। | G60: Translated | H60: High | I60: Fiqh ruling; Financial (zakat, riba, money); External resource or teacher | J60: Scholar; Mentor | K60: not tracked | L60: 3 | M60: quran-zakat-9-60 — Quran 9:60 - Zakat recipient categories (Quran.com) cra-charities-listing — List of charities and other qualified donees (Canada Revenue Agency) seekersguidance — SeekersGuidance (SeekersGuidance) | X60: https://www.revertguide.com/en/roadmap/month-6-plus#overview-heading | Y60: month-6-plus | Z60: locales/en/stages.json › [id=month-6-plus].dontWorry | AA60: stage:month-6-plus
A61: R0060 | B61: Roadmap stage | C61: Growth over a lifetime | D61: Focus now | E61: • Keep prayer and character steady. • Learn the big picture of zakat and Hajj. • Stay close to teachers and a community you trust. | F61: • নামাজ আর চরিত্র স্থির রাখুন। • যাকাত আর হজের বড় ছবিটা জানুন। • বিশ্বস্ত শিক্ষক আর কমিউনিটির কাছাকাছি থাকুন। | G61: Translated | H61: High | I61: Fiqh ruling; Financial (zakat, riba, money); External resource or teacher | J61: Scholar; Mentor | K61: not tracked | L61: 3 | M61: quran-zakat-9-60 — Quran 9:60 - Zakat recipient categories (Quran.com) cra-charities-listing — List of charities and other qualified donees (Canada Revenue Agency) seekersguidance — SeekersGuidance (SeekersGuidance) | X61: https://www.revertguide.com/en/roadmap/month-6-plus#stage-guidance-heading | Y61: month-6-plus | Z61: locales/en/stages.json › [id=month-6-plus].focusNow | AA61: stage:month-6-plus
A62: R0061 | B62: Roadmap stage | C62: Growth over a lifetime | D62: Can wait | E62: • Working out detailed zakat sums without anyone reviewing your finances. • Planning Hajj before you can afford it and manage it physically. • Specializing in anything until you want to. | F62: • কেউ আপনার আর্থিক অবস্থা পর্যালোচনা না করে যাকাতের বিস্তারিত হিসাব করা। • খরচ বহন আর শারীরিকভাবে সামলাতে পারার আগেই হজের পরিকল্পনা করা। • নিজে না চাওয়া পর্যন্ত কোনো বিষয়ে বিশেষজ্ঞ হওয়া। | G62: Translated | H62: High | I62: Fiqh ruling; Financial (zakat, riba, money); External resource or teacher | J62: Scholar; Mentor | K62: not tracked | L62: 3 | M62: quran-zakat-9-60 — Quran 9:60 - Zakat recipient categories (Quran.com) cra-charities-listing — List of charities and other qualified donees (Canada Revenue Agency) seekersguidance — SeekersGuidance (SeekersGuidance) | X62: https://www.revertguide.com/en/roadmap/month-6-plus#stage-guidance-heading | Y62: month-6-plus | Z62: locales/en/stages.json › [id=month-6-plus].canWait | AA62: stage:month-6-plus
A63: R0062 | B63: Roadmap stage | C63: Growth over a lifetime | D63: Ask for help if | E63: • You think zakat may now apply to you. • You are planning Hajj or Umrah. • You need guidance that touches money or law. | F63: • মনে হয় এখন আপনার ওপর যাকাত প্রযোজ্য হতে পারে। • হজ বা উমরাহর পরিকল্পনা করছেন। • টাকাপয়সা বা আইন জড়িত কোনো দিকনির্দেশনা দরকার। | G63: Translated | H63: High | I63: Fiqh ruling; Financial (zakat, riba, money); External resource or teacher | J63: Scholar; Mentor | K63: not tracked | L63: 3 | M63: quran-zakat-9-60 — Quran 9:60 - Zakat recipient categories (Quran.com) cra-charities-listing — List of charities and other qualified donees (Canada Revenue Agency) seekersguidance — SeekersGuidance (SeekersGuidance) | X63: https://www.revertguide.com/en/roadmap/month-6-plus#stage-guidance-heading | Y63: month-6-plus | Z63: locales/en/stages.json › [id=month-6-plus].askHelpIf | AA63: stage:month-6-plus
A64: R0063 | B64: Roadmap stage | C64: Growth over a lifetime | D64: Learning path: main resource | E64: MAC eLearning Free online courses from the Muslim Association of Canada on the Quran, Islamic sciences, family and history. Go at your own pace. Link: https://elearning.macnet.ca/ | F64: MAC eLearning (অনলাইন শিক্ষা) Muslim Association of Canada-র বিনামূল্যের অনলাইন কোর্স, কুরআন, ইসলামি জ্ঞানের বিভিন্ন শাখা, পরিবার আর ইতিহাস নিয়ে। নিজের গতিতে এগোন। | G64: Translated | H64: High | I64: Fiqh ruling; Financial (zakat, riba, money); External resource or teacher | J64: Scholar; Mentor | K64: not tracked | L64: 3 | M64: quran-zakat-9-60 — Quran 9:60 - Zakat recipient categories (Quran.com) cra-charities-listing — List of charities and other qualified donees (Canada Revenue Agency) seekersguidance — SeekersGuidance (SeekersGuidance) | X64: https://www.revertguide.com/en/roadmap/month-6-plus#learning-path-heading | Y64: month-6-plus | Z64: locales/en/stages.json › [id=month-6-plus].learningPath.main | AA64: stage:month-6-plus
A65: R0064 | B65: Roadmap stage | C65: Growth over a lifetime | D65: Learning path: optional resource | E65: Tafsir Ibn Kathir, abridged: the 30th part A classical explanation of the short surahs in the last part of the Quran, the ones you probably already recite. It is a paid print book from Darussalam. Link: https://darussalam.com/tafsir-ibn-kathir-abridged-30th-part/ | F65: Tafsir Ibn Kathir, সংক্ষিপ্ত: 30তম পারা কুরআনের শেষ পারার ছোট সূরাগুলোর একটি ধ্রুপদি ব্যাখ্যা, যে সূরাগুলো আপনি সম্ভবত ইতিমধ্যে পড়েন। এটি Darussalam-এর টাকা দিয়ে কেনা ছাপা বই। | G65: Translated | H65: High | I65: Fiqh ruling; Quran or hadith citation; Financial (zakat, riba, money); External resource or teacher | J65: Scholar; Mentor | K65: not tracked | L65: 3 | M65: quran-zakat-9-60 — Quran 9:60 - Zakat recipient categories (Quran.com) cra-charities-listing — List of charities and other qualified donees (Canada Revenue Agency) seekersguidance — SeekersGuidance (SeekersGuidance) | X65: https://www.revertguide.com/en/roadmap/month-6-plus#learning-path-heading | Y65: month-6-plus | Z65: locales/en/stages.json › [id=month-6-plus].learningPath.optional | AA65: stage:month-6-plus
A66: R0065 | B66: Roadmap stage | C66: Growth over a lifetime | D66: Learning path: guardrails | E66: • It is fine to take weeks off and come back. • Go deeper in one subject at a time, with a teacher when you can. | F66: • কয়েক সপ্তাহ বিরতি নিয়ে আবার ফিরে আসাও ঠিক আছে। • এক সময়ে একটি বিষয়ে গভীরে যান, সম্ভব হলে একজন শিক্ষকের সাথে। | G66: Translated | H66: High | I66: Fiqh ruling; Financial (zakat, riba, money); External resource or teacher | J66: Scholar; Mentor | K66: not tracked | L66: 3 | M66: quran-zakat-9-60 — Quran 9:60 - Zakat recipient categories (Quran.com) cra-charities-listing — List of charities and other qualified donees (Canada Revenue Agency) seekersguidance — SeekersGuidance (SeekersGuidance) | X66: https://www.revertguide.com/en/roadmap/month-6-plus#learning-path-heading | Y66: month-6-plus | Z66: locales/en/stages.json › [id=month-6-plus].learningPath.guardrails | AA66: stage:month-6-plus
A67: R0066 | B67: Roadmap stage | C67: Growth over a lifetime | D67: Good next questions | E67: • How do I live halal long term? → /topics/halal-living • How do I keep learning? → /topics/questions-and-doubts | F67: • দীর্ঘমেয়াদে কীভাবে হালাল জীবন কাটাব? → /topics/halal-living • কীভাবে শেখা চালিয়ে যাব? → /topics/questions-and-doubts | G67: Translated | H67: High | I67: Fiqh ruling; Financial (zakat, riba, money); External resource or teacher | J67: Scholar; Mentor | K67: not tracked | L67: 3 | M67: quran-zakat-9-60 — Quran 9:60 - Zakat recipient categories (Quran.com) cra-charities-listing — List of charities and other qualified donees (Canada Revenue Agency) seekersguidance — SeekersGuidance (SeekersGuidance) | X67: https://www.revertguide.com/en/roadmap/month-6-plus#good-questions-heading | Y67: month-6-plus | Z67: locales/en/stages.json › [id=month-6-plus].goodNextQuestions | AA67: stage:month-6-plus
A68: R0067 | B68: Roadmap step | C68: Ask an imam a good question | D68: Title | E68: Ask an imam a good question Time estimate: 10 to 20 minutes to prepare a clear question | F68: ইমামকে একটি ভালো প্রশ্ন করুন Time estimate: একটি স্পষ্ট প্রশ্ন তৈরি করতে 10 থেকে 20 মিনিট | G68: Translated | H68: Medium | I68: External resource or teacher; Tone and pastoral wording | J68: Scholar; Mentor | K68: source-checked | L68: 3 | M68: seekersguidance — SeekersGuidance (SeekersGuidance) new-muslim-academy — New Muslim Academy (New Muslim Academy) whyislam — WhyIslam (Islamic Circle of North America) | N68: • Says marriage, divorce, inheritance, zakat, abuse, medical and legal matters all need careful review, with professional help for medical, legal or financial issues. • Says online answers often differ because they follow different schools or someone else's situation, so note the source and school of each. • Recommends SeekersGuidance, New Muslim Academy and ICNA New Muslim Support (a US-based organisation) as resource cards. | X68: https://www.revertguide.com/en/roadmap/month-3-6/asking-an-imam | Y68: asking-an-imam | Z68: locales/en/steps/asking-an-imam.json › title, timeEstimate | AA68: step:asking-an-imam
A69: R0068 | B69: Roadmap step | C69: Ask an imam a good question | D69: Why it matters | E69: A clear question gets a better answer. If you learn how to put something to an imam or a qualified teacher, you save yourself confusion, you get guidance that fits your actual life, and you can tell when a matter needs looking at properly rather than in passing. | F69: স্পষ্ট প্রশ্নে ভালো উত্তর আসে। ইমাম বা যোগ্য শিক্ষকের কাছে কোনো বিষয় কীভাবে তুলে ধরতে হয় শিখে নিলে আপনি বিভ্রান্তি থেকে বাঁচবেন, আপনার আসল জীবনের সাথে মেলে এমন দিকনির্দেশনা পাবেন, আর বুঝতে পারবেন কখন কোনো বিষয় পাশ কাটিয়ে নয়, ঠিকভাবে খতিয়ে দেখা দরকার। | G69: Translated | H69: Medium | I69: External resource or teacher; Tone and pastoral wording | J69: Scholar; Mentor | K69: source-checked | L69: 3 | M69: seekersguidance — SeekersGuidance (SeekersGuidance) new-muslim-academy — New Muslim Academy (New Muslim Academy) whyislam — WhyIslam (Islamic Circle of North America) | X69: https://www.revertguide.com/en/roadmap/month-3-6/asking-an-imam#why-heading | Y69: asking-an-imam | Z69: locales/en/steps/asking-an-imam.json › whyMatters | AA69: step:asking-an-imam
A70: R0069 | B70: Roadmap step | C70: Ask an imam a good question | D70: Action 1 of 3 | E70: Write the situation out plainly • Say what happened, what you need to decide, and where you live. • Mention deadlines, family pressure, health problems, or money details if they bear on it. • Leave out private details that do not change the answer. | F70: পরিস্থিতিটা সহজ করে লিখে ফেলুন • কী ঘটেছে, কী সিদ্ধান্ত নিতে হবে, আর আপনি কোথায় থাকেন তা বলুন। • সময়সীমা, পরিবারের চাপ, স্বাস্থ্যের সমস্যা বা টাকাপয়সার খুঁটিনাটি প্রাসঙ্গিক হলে উল্লেখ করুন। • যে ব্যক্তিগত তথ্য উত্তর বদলায় না, তা বাদ দিন। | G70: Translated | H70: Medium | I70: External resource or teacher; Tone and pastoral wording | J70: Scholar; Mentor | K70: source-checked | L70: 3 | M70: seekersguidance — SeekersGuidance (SeekersGuidance) new-muslim-academy — New Muslim Academy (New Muslim Academy) whyislam — WhyIslam (Islamic Circle of North America) | X70: https://www.revertguide.com/en/roadmap/month-3-6/asking-an-imam#actions-heading | Y70: asking-an-imam | Z70: locales/en/steps/asking-an-imam.json › exactActions[0] | AA70: step:asking-an-imam
A71: R0070 | B71: Roadmap step | C71: Ask an imam a good question | D71: Action 2 of 3 | E71: Ask what comes first • Say you are a new Muslim and you want the practical next step. • Ask what has to happen now and what can wait. • Ask whether there are differences of opinion you should know about, without needing the full detail. | F71: আগে কী করতে হবে জিজ্ঞেস করুন • বলুন আপনি একজন নতুন মুসলিম আর ব্যবহারিক পরের ধাপটা জানতে চান। • জিজ্ঞেস করুন এখনই কী করতে হবে আর কী অপেক্ষা করতে পারে। • জিজ্ঞেস করুন এমন কোনো মতভেদ আছে কি না যা আপনার জানা উচিত, পুরো বিস্তারিত না চেয়ে। | G71: Translated | H71: Medium | I71: External resource or teacher; Tone and pastoral wording | J71: Scholar; Mentor | K71: source-checked | L71: 3 | M71: seekersguidance — SeekersGuidance (SeekersGuidance) new-muslim-academy — New Muslim Academy (New Muslim Academy) whyislam — WhyIslam (Islamic Circle of North America) | X71: https://www.revertguide.com/en/roadmap/month-3-6/asking-an-imam#actions-heading | Y71: asking-an-imam | Z71: locales/en/steps/asking-an-imam.json › exactActions[1] | AA71: step:asking-an-imam
A72: R0071 | B72: Roadmap step | C72: Ask an imam a good question | D72: Action 3 of 3 | E72: Double-check before you act on the big things • Marriage, divorce, inheritance, zakat, abuse, medical problems, and anything legal all need careful review. • Do not make a major life decision on the strength of anonymous comments. • Get professional help when the issue is medical, legal, or financial. | F72: বড় বিষয়ে কাজ করার আগে আরেকবার যাচাই করুন • বিয়ে, তালাক, উত্তরাধিকার, যাকাত, নির্যাতন, চিকিৎসার সমস্যা আর আইনি যেকোনো বিষয়ে যত্নের সাথে পর্যালোচনা দরকার। • নামহীন মন্তব্যের ভরসায় জীবনের বড় কোনো সিদ্ধান্ত নেবেন না। • বিষয়টি চিকিৎসা, আইনি বা আর্থিক হলে পেশাদার সাহায্য নিন। | G72: Translated | H72: High | I72: Safety or abuse; Legal (Canada); Financial (zakat, riba, money); Family, marriage or intimacy; External resource or teacher; Tone and pastoral wording | J72: Scholar; Mentor; Legal professional | K72: source-checked | L72: 3 | M72: seekersguidance — SeekersGuidance (SeekersGuidance) new-muslim-academy — New Muslim Academy (New Muslim Academy) whyislam — WhyIslam (Islamic Circle of North America) | X72: https://www.revertguide.com/en/roadmap/month-3-6/asking-an-imam#actions-heading | Y72: asking-an-imam | Z72: locales/en/steps/asking-an-imam.json › exactActions[2] | AA72: step:asking-an-imam
A73: R0072 | B73: Roadmap step | C73: Ask an imam a good question | D73: Obstacle 1 of 2 | E73: Problem: I feel embarrassed asking basic questions Solution: Basic questions are exactly what a teacher expects from a beginner. Asking plainly beats sitting in silent confusion. | F73: Problem: সাধারণ প্রশ্ন করতে আমার লজ্জা লাগে Solution: একজন শিক্ষক নতুনদের কাছ থেকে ঠিক সাধারণ প্রশ্নই আশা করেন। চুপচাপ বিভ্রান্ত হয়ে বসে থাকার চেয়ে সোজাসুজি জিজ্ঞেস করা ভালো। | G73: Translated | H73: Medium | I73: External resource or teacher; Tone and pastoral wording | J73: Scholar; Mentor | K73: source-checked | L73: 3 | M73: seekersguidance — SeekersGuidance (SeekersGuidance) new-muslim-academy — New Muslim Academy (New Muslim Academy) whyislam — WhyIslam (Islamic Circle of North America) | X73: https://www.revertguide.com/en/roadmap/month-3-6/asking-an-imam#obstacles-heading | Y73: asking-an-imam | Z73: locales/en/steps/asking-an-imam.json › obstacles[0] | AA73: step:asking-an-imam
A74: R0073 | B74: Roadmap step | C74: Ask an imam a good question | D74: Obstacle 2 of 2 | E74: Problem: I received different answers Solution: Ask the teacher which answer applies to your situation and which parts can wait. If you need more than that, take it to a qualified local scholar who knows your context. Online answers often differ because they follow different schools or answer someone else's situation, so note the source and the school of each before you ask. | F74: Problem: আমি ভিন্ন ভিন্ন উত্তর পেয়েছি Solution: শিক্ষককে জিজ্ঞেস করুন কোন উত্তরটি আপনার পরিস্থিতিতে প্রযোজ্য আর কোন অংশগুলো অপেক্ষা করতে পারে। এর বেশি দরকার হলে বিষয়টি এমন একজন যোগ্য স্থানীয় আলেমের কাছে নিয়ে যান যিনি আপনার প্রেক্ষাপট জানেন। অনলাইনের উত্তরগুলো প্রায়ই আলাদা হয়, কারণ সেগুলো ভিন্ন মাযহাব অনুসরণ করে বা অন্য কারও পরিস্থিতির উত্তর দেয়, তাই জিজ্ঞেস করার আগে প্রতিটির সূত্র আর মাযহাব লিখে রাখুন। | G74: Translated | H74: Medium | I74: External resource or teacher; Tone and pastoral wording | J74: Scholar; Mentor | K74: source-checked | L74: 3 | M74: seekersguidance — SeekersGuidance (SeekersGuidance) new-muslim-academy — New Muslim Academy (New Muslim Academy) whyislam — WhyIslam (Islamic Circle of North America) | X74: https://www.revertguide.com/en/roadmap/month-3-6/asking-an-imam#obstacles-heading | Y74: asking-an-imam | Z74: locales/en/steps/asking-an-imam.json › obstacles[1] | AA74: step:asking-an-imam
A75: R0074 | B75: Roadmap step | C75: Ask an imam a good question | D75: Tiny version | E75: Write down three things: what happened, what you need to decide, and that you are a new Muslim. | F75: তিনটি কথা লিখে ফেলুন: কী ঘটেছে, কী সিদ্ধান্ত নিতে হবে, আর আপনি একজন নতুন মুসলিম। | G75: Translated | H75: Medium | I75: External resource or teacher; Tone and pastoral wording | J75: Scholar; Mentor | K75: source-checked | L75: 3 | M75: seekersguidance — SeekersGuidance (SeekersGuidance) new-muslim-academy — New Muslim Academy (New Muslim Academy) whyislam — WhyIslam (Islamic Circle of North America) | X75: https://www.revertguide.com/en/roadmap/month-3-6/asking-an-imam#obstacles-heading | Y75: asking-an-imam | Z75: locales/en/steps/asking-an-imam.json › tinyVersion | AA75: step:asking-an-imam
A76: R0075 | B76: Roadmap step | C76: Ask an imam a good question | D76: Unlocks next | E76: Good questions keep you learning with confidence and keep you from acting on bad advice. | F76: ভালো প্রশ্ন আপনাকে আত্মবিশ্বাসের সাথে শিখতে সাহায্য করে, আর খারাপ পরামর্শে কাজ করা থেকে বাঁচায়। | G76: Translated | H76: Medium | I76: External resource or teacher; Tone and pastoral wording | J76: Scholar; Mentor | K76: source-checked | L76: 3 | M76: seekersguidance — SeekersGuidance (SeekersGuidance) new-muslim-academy — New Muslim Academy (New Muslim Academy) whyislam — WhyIslam (Islamic Circle of North America) | X76: https://www.revertguide.com/en/roadmap/month-3-6/asking-an-imam#unlocks-heading | Y76: asking-an-imam | Z76: locales/en/steps/asking-an-imam.json › unlocksNext | AA76: step:asking-an-imam
A77: R0076 | B77: Roadmap step | C77: Ask an imam a good question | D77: Gentle script: Asking for a beginner answer | E77: Asking for a beginner answer I am a new Muslim and I am trying to do this properly without getting overwhelmed. What is the practical next step for my situation, and what can wait? | F77: নতুনদের উপযোগী উত্তর চাওয়া আমি একজন নতুন মুসলিম, আর হাঁপিয়ে না উঠে কাজটা ঠিকভাবে করার চেষ্টা করছি। আমার অবস্থায় ব্যবহারিক পরের ধাপ কী, আর কী অপেক্ষা করতে পারে? | G77: Translated | H77: Medium | I77: Mental health; External resource or teacher; Tone and pastoral wording | J77: Scholar; Mentor; Mental health professional | K77: source-checked | L77: 3 | M77: seekersguidance — SeekersGuidance (SeekersGuidance) new-muslim-academy — New Muslim Academy (New Muslim Academy) whyislam — WhyIslam (Islamic Circle of North America) | X77: https://www.revertguide.com/en/roadmap/month-3-6/asking-an-imam#scripts-heading | Y77: asking-an-imam | Z77: locales/en/steps/asking-an-imam.json › gentleScripts[0] | AA77: step:asking-an-imam
A78: R0077 | B78: Roadmap step | C78: Ask an imam a good question | D78: Links on this page | E78: • Why Muslims differ → /topics/why-muslims-differ • Who counts as a shaykh or a mufti → /faq#faq-fnd-039 • How to ask for help → /guides/how-to-ask-for-help • Get help → /get-help | F78: • মুসলিমদের মধ্যে কেন ভিন্নতা → /topics/why-muslims-differ • কাকে শায়খ বা মুফতি বলা যায় → /faq#faq-fnd-039 • কীভাবে সাহায্য চাইবেন → /guides/how-to-ask-for-help • সাহায্য নিন → /get-help | G78: Translated | H78: Medium | I78: External resource or teacher; Tone and pastoral wording | J78: Scholar; Mentor | K78: source-checked | L78: 3 | M78: seekersguidance — SeekersGuidance (SeekersGuidance) new-muslim-academy — New Muslim Academy (New Muslim Academy) whyislam — WhyIslam (Islamic Circle of North America) | X78: https://www.revertguide.com/en/roadmap/month-3-6/asking-an-imam#where-next-heading | Y78: asking-an-imam | Z78: locales/en/steps/asking-an-imam.json › relatedLinks | AA78: step:asking-an-imam
A79: R0078 | B79: Roadmap step | C79: Work on your character (akhlaq) | D79: Title | E79: Work on your character (akhlaq) Time estimate: A lifetime. Daily practice, and it keeps going | F79: নিজের চরিত্র নিয়ে কাজ করুন (আখলাক) Time estimate: সারাজীবন। প্রতিদিনের অনুশীলন, যা চলতেই থাকে | G79: Translated | H79: High | I79: Seerah or history; External resource or teacher; Tone and pastoral wording | J79: Scholar; Mentor | K79: review-needed | L79: 4 | M79: sunnah-com — Sunnah.com (Sunnah.com) yaqeen-institute — Yaqeen Institute (Yaqeen Institute for Islamic Research) sunnah-muslim-2749 — Sahih Muslim 2749: people who sin and seek forgiveness (Sunnah.com) sunnah-muslim-2750a — Sahih Muslim 2750a: the hadith of Hanzala (Sunnah.com) | N79: • Quotes 'I was sent to perfect good character', 'best of you have the best character', 'actions are by intentions', the strong-man and 'best to their families' hadith; only generic sunnah-com id. • Cites Muslim 2749 (if people did not sin, Allah would bring people who sin and seek forgiveness), Muslim 2750a (Hanzala feared hypocrisy) and Quran 33:21. • Calls Martin Lings' 'Muhammad: His Life Based on the Earliest Sources' the usual first seerah; confirm it suits (Lings was a Perennialist Sufi). Resource card is Yasir Qadhi's Seerah. • Says nightly self-review (muhasabah) was a companions' practice, and advises 'Inna lillahi wa inna ilayhi raji'un' for everyday impatience such as traffic and queues. | O79: ⚠ Virtue list leads with Arabic: 'Sabr (patience)', 'Sidq (truthfulness)', 'Tawadu (humility)', 'Ihsan', 'Shukr', 'Rahmah'; the naming rule puts plain English first. | X79: https://www.revertguide.com/en/roadmap/month-3-6/character | Y79: character | Z79: locales/en/steps/character.json › title, timeEstimate | AA79: step:character
A80: R0079 | B80: Roadmap step | C80: Work on your character (akhlaq) | D80: Why it matters | E80: The Prophet Muhammad (peace be upon him) said, 'I was sent to perfect good character.' Rituals are part of Islam, and so is how you treat people, how you carry yourself, and who you turn into. Good character (akhlaq) is what real faith grows into. When your prayers and your fasting start changing how you deal with the world, when you catch yourself being more patient or more honest than you used to be, that is Islam showing up in an ordinary day. The Prophet also taught that 'the best among you are those who have the best character,' and 'actions are judged by intentions.' What happens inside you counts as much as what anybody can see. | F80: নবী মুহাম্মদ (সা.) বলেছেন, 'আমাকে উত্তম চরিত্র পূর্ণ করার জন্য পাঠানো হয়েছে।' আচার-অনুষ্ঠান ইসলামের অংশ, আর মানুষের সাথে আপনার আচরণ, আপনার চালচলন, আর আপনি কেমন মানুষ হয়ে উঠছেন, সেটাও। উত্তম চরিত্র (আখলাক) হলো সত্যিকারের ঈমান যা হয়ে বেড়ে ওঠে। আপনার নামাজ আর রোজা যখন পৃথিবীর সাথে আপনার আচরণ বদলাতে শুরু করে, যখন দেখেন আগের চেয়ে বেশি ধৈর্যশীল বা বেশি সৎ হচ্ছেন, সেটাই একটি সাধারণ দিনে ইসলামের প্রকাশ। নবী (সা.) এটাও শিখিয়েছেন যে 'তোমাদের মধ্যে সেই শ্রেষ্ঠ, যার চরিত্র সবচেয়ে সুন্দর,' আর 'কাজের বিচার হয় নিয়ত দিয়ে।' আপনার ভেতরে যা ঘটে, তা বাইরে দেখা যায় এমন কিছুর মতোই গুরুত্বপূর্ণ। | G80: Translated | H80: High | I80: Seerah or history; External resource or teacher; Tone and pastoral wording | J80: Scholar; Mentor | K80: review-needed | L80: 4 | M80: sunnah-com — Sunnah.com (Sunnah.com) yaqeen-institute — Yaqeen Institute (Yaqeen Institute for Islamic Research) sunnah-muslim-2749 — Sahih Muslim 2749: people who sin and seek forgiveness (Sunnah.com) sunnah-muslim-2750a — Sahih Muslim 2750a: the hadith of Hanzala (Sunnah.com) | X80: https://www.revertguide.com/en/roadmap/month-3-6/character#why-heading | Y80: character | Z80: locales/en/steps/character.json › whyMatters | AA80: step:character
A81: R0080 | B81: Roadmap step | C81: Work on your character (akhlaq) | D81: Action 1 of 5 | E81: Learn the core Islamic virtues • Sabr (patience): holding steady through difficulty. Life will test you, and this is the tool you reach for most. • Sidq (truthfulness): honesty in what you say and what you do, including when it costs you something. • Tawadu (humility): knowing every good thing came from Allah, and treating people well whatever their status. • Ihsan (excellence): doing things carefully and sincerely, as though Allah is watching, because He is. • Shukr (gratitude): noticing what you have and thanking Allah and the people around you for it. • Rahmah (mercy and compassion): kindness towards everything Allah made, animals and the land included. | F81: ইসলামের মূল গুণগুলো শিখুন • সবর (ধৈর্য): কষ্টের মধ্যে স্থির থাকা। জীবন আপনাকে পরীক্ষা করবে, আর এই হাতিয়ারটিই আপনার সবচেয়ে বেশি লাগবে। • সিদক (সত্যবাদিতা): কথায় আর কাজে সততা, ক্ষতি হলেও। • তাওয়াদু (বিনয়): জানা যে প্রতিটি ভালো জিনিস আল্লাহর কাছ থেকে এসেছে, আর মর্যাদা যা-ই হোক সবার সাথে ভালো আচরণ করা। • ইহসান (উৎকর্ষ): যত্ন আর আন্তরিকতা নিয়ে কাজ করা, যেন আল্লাহ দেখছেন, কারণ তিনি সত্যিই দেখছেন। • শুকর (কৃতজ্ঞতা): যা আছে তা খেয়াল করা, আর এর জন্য আল্লাহ আর চারপাশের মানুষদের ধন্যবাদ দেওয়া। • রহমাহ (দয়া ও সহমর্মিতা): আল্লাহর সৃষ্টি সবকিছুর প্রতি সদয়তা, পশুপাখি আর প্রকৃতিসহ। | G81: Translated | H81: High | I81: Seerah or history; External resource or teacher; Tone and pastoral wording | J81: Scholar; Mentor | K81: review-needed | L81: 4 | M81: sunnah-com — Sunnah.com (Sunnah.com) yaqeen-institute — Yaqeen Institute (Yaqeen Institute for Islamic Research) sunnah-muslim-2749 — Sahih Muslim 2749: people who sin and seek forgiveness (Sunnah.com) sunnah-muslim-2750a — Sahih Muslim 2750a: the hadith of Hanzala (Sunnah.com) | X81: https://www.revertguide.com/en/roadmap/month-3-6/character#actions-heading | Y81: character | Z81: locales/en/steps/character.json › exactActions[0] | AA81: step:character
A82: R0081 | B82: Roadmap step | C82: Work on your character (akhlaq) | D82: Action 2 of 5 | E82: Study the Prophet as your example • The Prophet Muhammad (peace be upon him) is described in the Quran as 'an excellent example' (33:21). • Read about his character: how gentle he was with children, how fair in business, how kind to his neighbors, how patient with the people who opposed him. • Start with a short biography (seerah). 'Muhammad: His Life Based on the Earliest Sources' by Martin Lings is the one people usually hand you first. • Pay attention to how he handled conflict, treated the poor, and forgave the people who wronged him. • Pick one part of his character each week and work on that in your own life. | F82: নবী (সা.)-কে আদর্শ হিসেবে পড়ুন • কুরআনে নবী মুহাম্মদ (সা.)-কে 'উত্তম আদর্শ' বলা হয়েছে (33:21)। • তাঁর চরিত্র সম্পর্কে পড়ুন: শিশুদের সাথে তিনি কত কোমল ছিলেন, ব্যবসায় কত ন্যায্য, প্রতিবেশীদের প্রতি কত সদয়, আর বিরোধীদের প্রতি কত ধৈর্যশীল। • ছোট একটি জীবনী (সিরাহ) দিয়ে শুরু করুন। মার্টিন লিংসের 'Muhammad: His Life Based on the Earliest Sources' সাধারণত প্রথমেই হাতে দেওয়া হয়। • খেয়াল করুন তিনি কীভাবে বিবাদ সামলাতেন, গরিবদের সাথে কেমন আচরণ করতেন, আর যারা অন্যায় করেছিল তাদের কীভাবে ক্ষমা করতেন। • প্রতি সপ্তাহে তাঁর চরিত্রের একটি দিক বেছে নিন আর নিজের জীবনে তা নিয়ে কাজ করুন। | G82: Translated | H82: High | I82: Seerah or history; External resource or teacher; Tone and pastoral wording | J82: Scholar; Mentor | K82: review-needed | L82: 4 | M82: sunnah-com — Sunnah.com (Sunnah.com) yaqeen-institute — Yaqeen Institute (Yaqeen Institute for Islamic Research) sunnah-muslim-2749 — Sahih Muslim 2749: people who sin and seek forgiveness (Sunnah.com) sunnah-muslim-2750a — Sahih Muslim 2750a: the hadith of Hanzala (Sunnah.com) | X82: https://www.revertguide.com/en/roadmap/month-3-6/character#actions-heading | Y82: character | Z82: locales/en/steps/character.json › exactActions[1] | AA82: step:character
A83: R0082 | B83: Roadmap step | C83: Work on your character (akhlaq) | D83: Action 3 of 5 | E83: Put it into practice every day • Start the day with an intention (niyyah) to hold to one virtue, maybe patience or gratitude. • When you feel anger rising, remember the hadith: 'The strong person is not the one who can wrestle, but the one who controls themselves at the time of anger.' • Do small kind things. Smile at a stranger, help a neighbor, actually listen when someone is talking to you. • Before you act or speak, pause and ask yourself: would the Prophet (peace be upon him) approve of this? • At night, look back over the day. Where did it go well? Where could it have gone better? This self-reflection (muhasabah) was a practice of the companions of the Prophet. | F83: প্রতিদিন তা বাস্তবে করুন • একটি গুণ ধরে রাখার নিয়ত দিয়ে দিন শুরু করুন, হয়তো ধৈর্য বা কৃতজ্ঞতা। • রাগ চড়তে থাকলে হাদিসটি মনে করুন: 'শক্তিশালী সে নয় যে কুস্তিতে জেতে, বরং সে যে রাগের সময় নিজেকে নিয়ন্ত্রণ করে।' • ছোট ছোট সদয় কাজ করুন। অচেনা কারও দিকে হাসুন, প্রতিবেশীকে সাহায্য করুন, কেউ কথা বললে সত্যিই মন দিয়ে শুনুন। • কিছু করার বা বলার আগে থেমে নিজেকে জিজ্ঞেস করুন: নবী (সা.) কি এটা পছন্দ করতেন? • রাতে দিনটার দিকে ফিরে তাকান। কোথায় ভালো গেল? কোথায় আরও ভালো হতে পারত? এই আত্মসমালোচনা (মুহাসাবাহ) নবী (সা.)-এর সাহাবিদের অভ্যাস ছিল। | G83: Translated | H83: High | I83: Quran or hadith citation; Seerah or history; External resource or teacher; Tone and pastoral wording | J83: Scholar; Mentor | K83: review-needed | L83: 4 | M83: sunnah-com — Sunnah.com (Sunnah.com) yaqeen-institute — Yaqeen Institute (Yaqeen Institute for Islamic Research) sunnah-muslim-2749 — Sahih Muslim 2749: people who sin and seek forgiveness (Sunnah.com) sunnah-muslim-2750a — Sahih Muslim 2750a: the hadith of Hanzala (Sunnah.com) | X83: https://www.revertguide.com/en/roadmap/month-3-6/character#actions-heading | Y83: character | Z83: locales/en/steps/character.json › exactActions[2] | AA83: step:character
A84: R0083 | B84: Roadmap step | C84: Work on your character (akhlaq) | D84: Action 4 of 5 | E84: Strengthen your relationships • Islam puts enormous weight on keeping family ties (silat al-rahm), including with family who are not Muslim. • Be at your best with family, neighbors, coworkers, and strangers alike. • The Prophet (peace be upon him) said: 'The best of you are those who are best to their families.' • If someone wrongs you, try to answer with patience instead of getting even. Forgiveness sits near the top of the virtues. • Your character is often the most effective da'wah (invitation to Islam) you will ever do, because people watch how you live. | F84: সম্পর্কগুলো মজবুত করুন • ইসলাম আত্মীয়তার সম্পর্ক রক্ষাকে (সিলাতুর রাহিম) বিশাল গুরুত্ব দেয়, অমুসলিম আত্মীয়দের সাথেও। • পরিবার, প্রতিবেশী, সহকর্মী আর অচেনা মানুষ, সবার সাথে নিজের সেরা রূপে থাকুন। • নবী (সা.) বলেছেন: 'তোমাদের মধ্যে সেই শ্রেষ্ঠ, যে নিজের পরিবারের কাছে শ্রেষ্ঠ।' • কেউ অন্যায় করলে প্রতিশোধ না নিয়ে ধৈর্য দিয়ে জবাব দেওয়ার চেষ্টা করুন। ক্ষমা গুণগুলোর মধ্যে একেবারে ওপরের দিকে। • আপনার চরিত্রই প্রায়ই আপনার করা সবচেয়ে কার্যকর দাওয়াহ (ইসলামের দিকে আহ্বান), কারণ মানুষ দেখে আপনি কীভাবে জীবন কাটান। | G84: Translated | H84: High | I84: Seerah or history; External resource or teacher; Tone and pastoral wording | J84: Scholar; Mentor | K84: review-needed | L84: 4 | M84: sunnah-com — Sunnah.com (Sunnah.com) yaqeen-institute — Yaqeen Institute (Yaqeen Institute for Islamic Research) sunnah-muslim-2749 — Sahih Muslim 2749: people who sin and seek forgiveness (Sunnah.com) sunnah-muslim-2750a — Sahih Muslim 2750a: the hadith of Hanzala (Sunnah.com) | X84: https://www.revertguide.com/en/roadmap/month-3-6/character#actions-heading | Y84: character | Z84: locales/en/steps/character.json › exactActions[3] | AA84: step:character
A85: R0084 | B85: Roadmap step | C85: Work on your character (akhlaq) | D85: Action 5 of 5 | E85: Be kind to yourself about old habits • Everybody brings habits from before Islam that do not fit where they are now. • Change does not happen overnight. Take one habit at a time. • Swap a bad habit for a better one. Gossip, for instance, can become dhikr (remembrance of Allah). • If you slip, make istighfar (ask Allah for forgiveness) and try again. Allah loves those who repent. • Keep company with people whose character you want, because you end up like the people you spend time with. | F85: পুরোনো অভ্যাস নিয়ে নিজের প্রতি নরম থাকুন • প্রত্যেকেই ইসলামের আগের এমন কিছু অভ্যাস নিয়ে আসেন যা এখনকার অবস্থার সাথে মেলে না। • পরিবর্তন রাতারাতি হয় না। এক সময়ে একটি অভ্যাস ধরুন। • খারাপ অভ্যাসের জায়গায় ভালো একটি বসান। যেমন গল্পগুজবের জায়গা নিতে পারে জিকির (আল্লাহর স্মরণ)। • পা পিছলে গেলে ইস্তিগফার (আল্লাহর কাছে ক্ষমা চাওয়া) করুন আর আবার চেষ্টা করুন। আল্লাহ তওবাকারীদের ভালোবাসেন। • যাদের মতো চরিত্র চান তাদের সঙ্গে থাকুন, কারণ যাদের সাথে সময় কাটান আপনি তাদের মতোই হয়ে ওঠেন। | G85: Translated | H85: High | I85: Seerah or history; External resource or teacher; Tone and pastoral wording | J85: Scholar; Mentor | K85: review-needed | L85: 4 | M85: sunnah-com — Sunnah.com (Sunnah.com) yaqeen-institute — Yaqeen Institute (Yaqeen Institute for Islamic Research) sunnah-muslim-2749 — Sahih Muslim 2749: people who sin and seek forgiveness (Sunnah.com) sunnah-muslim-2750a — Sahih Muslim 2750a: the hadith of Hanzala (Sunnah.com) | X85: https://www.revertguide.com/en/roadmap/month-3-6/character#actions-heading | Y85: character | Z85: locales/en/steps/character.json › exactActions[4] | AA85: step:character
A86: R0085 | B86: Roadmap step | C86: Work on your character (akhlaq) | D86: Obstacle 1 of 5 | E86: Problem: I keep falling back into old habits Solution: This is part of being human rather than a sign of failure. The Prophet (peace be upon him) said that if people did not sin, Allah would bring people who sin and then ask His forgiveness, and He would forgive them (Sahih Muslim 2749). Every time you catch a slip and try again, you have grown. Aim at progress instead of perfection. Some habits took years to build and will take a while to unpick, so be gentle with yourself while you do it. | F86: Problem: আমি বারবার পুরোনো অভ্যাসে ফিরে যাই Solution: এটি মানুষ হওয়ারই অংশ, ব্যর্থতার লক্ষণ নয়। নবী (সা.) বলেছেন, মানুষ যদি গুনাহ না করত, আল্লাহ এমন মানুষ আনতেন যারা গুনাহ করে তারপর তাঁর কাছে ক্ষমা চায়, আর তিনি তাদের ক্ষমা করতেন (Sahih Muslim 2749)। প্রতিবার যখন কোনো ভুল ধরতে পেরে আবার চেষ্টা করেন, আপনি বেড়ে ওঠেন। নিখুঁত হওয়ার বদলে অগ্রগতির লক্ষ্য রাখুন। কিছু অভ্যাস গড়তে বছর লেগেছে আর ছাড়তেও কিছুটা সময় লাগবে, তাই সে সময় নিজের প্রতি কোমল থাকুন। | G86: Translated | H86: High | I86: Quran or hadith citation; Seerah or history; External resource or teacher; Tone and pastoral wording | J86: Scholar; Mentor | K86: review-needed | L86: 4 | M86: sunnah-com — Sunnah.com (Sunnah.com) yaqeen-institute — Yaqeen Institute (Yaqeen Institute for Islamic Research) sunnah-muslim-2749 — Sahih Muslim 2749: people who sin and seek forgiveness (Sunnah.com) sunnah-muslim-2750a — Sahih Muslim 2750a: the hadith of Hanzala (Sunnah.com) | X86: https://www.revertguide.com/en/roadmap/month-3-6/character#obstacles-heading | Y86: character | Z86: locales/en/steps/character.json › obstacles[0] | AA86: step:character
A87: R0086 | B87: Roadmap step | C87: Work on your character (akhlaq) | D87: Obstacle 2 of 5 | E87: Problem: I struggle with patience Solution: Patience (sabr) is one of the most mentioned virtues in the Quran, partly because it is one of the hardest. It strengthens with use, like a muscle. When impatience rises, take a breath and say 'Inna lillahi wa inna ilayhi raji'un' (Indeed, to Allah we belong and to Him we return). Start with the small tests, traffic and long queues and minor annoyances, then work up from there. | F87: Problem: ধৈর্য ধরতে আমার কষ্ট হয় Solution: ধৈর্য (সবর) কুরআনে সবচেয়ে বেশি উল্লিখিত গুণগুলোর একটি, আংশিক এই কারণে যে এটি সবচেয়ে কঠিনগুলোর একটি। পেশির মতো ব্যবহারে এটি শক্ত হয়। অধৈর্য জাগলে একটা শ্বাস নিন আর বলুন 'ইন্না লিল্লাহি ওয়া ইন্না ইলাইহি রাজিউন' (নিশ্চয়ই আমরা আল্লাহর, আর তাঁর কাছেই ফিরে যাব)। ছোট পরীক্ষা দিয়ে শুরু করুন, যানজট, লম্বা লাইন আর ছোটখাটো বিরক্তি, তারপর সেখান থেকে এগোন। | G87: Translated | H87: High | I87: Seerah or history; External resource or teacher; Tone and pastoral wording | J87: Scholar; Mentor | K87: review-needed | L87: 4 | M87: sunnah-com — Sunnah.com (Sunnah.com) yaqeen-institute — Yaqeen Institute (Yaqeen Institute for Islamic Research) sunnah-muslim-2749 — Sahih Muslim 2749: people who sin and seek forgiveness (Sunnah.com) sunnah-muslim-2750a — Sahih Muslim 2750a: the hadith of Hanzala (Sunnah.com) | X87: https://www.revertguide.com/en/roadmap/month-3-6/character#obstacles-heading | Y87: character | Z87: locales/en/steps/character.json › obstacles[1] | AA87: step:character
A88: R0087 | B88: Roadmap step | C88: Work on your character (akhlaq) | D88: Obstacle 3 of 5 | E88: Problem: I find non-Muslim social settings hard now Solution: You do not have to withdraw from non-Muslim friends or social circles. Islam encourages good relationships with everyone. Set the boundaries you need, like politely turning down a drink, without preaching at anybody. Your character in those rooms is worship in itself. Most people respect someone who is straightforward about who they are, so be yourself and let your faith steer it. | F88: Problem: অমুসলিম সামাজিক পরিবেশ এখন আমার কাছে কঠিন লাগে Solution: অমুসলিম বন্ধু বা সামাজিক বৃত্ত থেকে সরে আসতে হবে না। ইসলাম সবার সাথে ভালো সম্পর্কে উৎসাহ দেয়। যে সীমা দরকার তা ঠিক করুন, যেমন ভদ্রভাবে পানীয় ফিরিয়ে দেওয়া, কাউকে উপদেশ না দিয়ে। সেই পরিবেশে আপনার চরিত্র নিজেই একটি ইবাদত। নিজের পরিচয় নিয়ে সোজাসাপ্টা মানুষকে বেশিরভাগ মানুষ সম্মান করে, তাই নিজের মতো থাকুন আর ঈমানকে পথ দেখাতে দিন। | G88: Translated | H88: High | I88: Seerah or history; External resource or teacher; Tone and pastoral wording | J88: Scholar; Mentor | K88: review-needed | L88: 4 | M88: sunnah-com — Sunnah.com (Sunnah.com) yaqeen-institute — Yaqeen Institute (Yaqeen Institute for Islamic Research) sunnah-muslim-2749 — Sahih Muslim 2749: people who sin and seek forgiveness (Sunnah.com) sunnah-muslim-2750a — Sahih Muslim 2750a: the hadith of Hanzala (Sunnah.com) | X88: https://www.revertguide.com/en/roadmap/month-3-6/character#obstacles-heading | Y88: character | Z88: locales/en/steps/character.json › obstacles[2] | AA88: step:character
A89: R0088 | B89: Roadmap step | C89: Work on your character (akhlaq) | D89: Obstacle 4 of 5 | E89: Problem: I don't feel like I'm changing fast enough Solution: Spiritual growth is rarely dramatic. It is slow and hard to see from the inside, even while other people notice it. Keep a simple journal and read it back once a month, and you will find progress that was invisible day to day. The companions of the Prophet took years to build their character, and they had the best teacher in history. Trust the process and trust Allah's timing for you. | F89: Problem: মনে হয় আমি যথেষ্ট দ্রুত বদলাচ্ছি না Solution: আত্মিক বেড়ে ওঠা খুব কমই নাটকীয় হয়। এটি ধীর, আর ভেতর থেকে দেখা কঠিন, যদিও অন্যরা তা খেয়াল করে। একটি সহজ ডায়েরি রাখুন আর মাসে একবার ফিরে পড়ুন, দেখবেন দিনে দিনে যে অগ্রগতি অদৃশ্য ছিল তা আছে। নবী (সা.)-এর সাহাবিদের চরিত্র গড়তে বছর লেগেছিল, আর তাদের ছিলেন ইতিহাসের সেরা শিক্ষক। প্রক্রিয়ার ওপর আর আপনার জন্য আল্লাহর সময়ের ওপর ভরসা রাখুন। | G89: Translated | H89: High | I89: Seerah or history; External resource or teacher; Tone and pastoral wording | J89: Scholar; Mentor | K89: review-needed | L89: 4 | M89: sunnah-com — Sunnah.com (Sunnah.com) yaqeen-institute — Yaqeen Institute (Yaqeen Institute for Islamic Research) sunnah-muslim-2749 — Sahih Muslim 2749: people who sin and seek forgiveness (Sunnah.com) sunnah-muslim-2750a — Sahih Muslim 2750a: the hadith of Hanzala (Sunnah.com) | X89: https://www.revertguide.com/en/roadmap/month-3-6/character#obstacles-heading | Y89: character | Z89: locales/en/steps/character.json › obstacles[3] | AA89: step:character
A90: R0089 | B90: Roadmap step | C90: Work on your character (akhlaq) | D90: Obstacle 5 of 5 | E90: Problem: I feel like a hypocrite because my actions don't match my beliefs Solution: Feeling that tension is a sign of healthy faith. A real hypocrite does not care about the gap between what they believe and what they do. The fact that it bothers you means your conscience is awake and working. Close the gap one step at a time, and make du'a for sincerity (ikhlas). Allah is looking at your heart and your effort rather than the tally. The companion Hanzala once feared he was a hypocrite because his feeling of faith faded at home, and the Prophet reassured him (Sahih Muslim 2750a). | F90: Problem: মনে হয় আমি মুনাফিক, কারণ আমার কাজ আমার বিশ্বাসের সাথে মেলে না Solution: এই টানাপোড়েন অনুভব করা সুস্থ ঈমানের লক্ষণ। সত্যিকারের মুনাফিক নিজের বিশ্বাস আর কাজের মধ্যের ফাঁক নিয়ে মাথা ঘামায় না। এটা আপনাকে পীড়া দিচ্ছে মানে আপনার বিবেক জেগে আছে আর কাজ করছে। এক ধাপ এক ধাপ করে ফাঁকটা কমান, আর আন্তরিকতার (ইখলাস) জন্য দোয়া করুন। আল্লাহ হিসাবের খাতার চেয়ে আপনার হৃদয় আর চেষ্টার দিকে তাকান। সাহাবি হানযালা একবার ভয় পেয়েছিলেন যে তিনি মুনাফিক, কারণ ঘরে গেলে তাঁর ঈমানের অনুভূতি মিলিয়ে যেত, আর নবী (সা.) তাঁকে আশ্বস্ত করেছিলেন (Sahih Muslim 2750a)। | G90: Translated | H90: High | I90: Quran or hadith citation; Seerah or history; External resource or teacher; Tone and pastoral wording | J90: Scholar; Mentor | K90: review-needed | L90: 4 | M90: sunnah-com — Sunnah.com (Sunnah.com) yaqeen-institute — Yaqeen Institute (Yaqeen Institute for Islamic Research) sunnah-muslim-2749 — Sahih Muslim 2749: people who sin and seek forgiveness (Sunnah.com) sunnah-muslim-2750a — Sahih Muslim 2750a: the hadith of Hanzala (Sunnah.com) | X90: https://www.revertguide.com/en/roadmap/month-3-6/character#obstacles-heading | Y90: character | Z90: locales/en/steps/character.json › obstacles[4] | AA90: step:character
A91: R0090 | B91: Roadmap step | C91: Work on your character (akhlaq) | D91: Tiny version | E91: Take one virtue for the week. Be more patient, or more honest, or more grateful. Character is Islam in motion. | F91: সপ্তাহের জন্য একটি গুণ বেছে নিন। একটু বেশি ধৈর্যশীল, বা বেশি সৎ, বা বেশি কৃতজ্ঞ হোন। চরিত্র হলো চলমান ইসলাম। | G91: Translated | H91: High | I91: Seerah or history; External resource or teacher; Tone and pastoral wording | J91: Scholar; Mentor | K91: review-needed | L91: 4 | M91: sunnah-com — Sunnah.com (Sunnah.com) yaqeen-institute — Yaqeen Institute (Yaqeen Institute for Islamic Research) sunnah-muslim-2749 — Sahih Muslim 2749: people who sin and seek forgiveness (Sunnah.com) sunnah-muslim-2750a — Sahih Muslim 2750a: the hadith of Hanzala (Sunnah.com) | X91: https://www.revertguide.com/en/roadmap/month-3-6/character#obstacles-heading | Y91: character | Z91: locales/en/steps/character.json › tinyVersion | AA91: step:character
... A93: R0092 | B93: Roadmap step | C93: Work on your character (akhlaq) | D93: Links on this page | E93: • Charity and service all year → /seasonal/year-round-charity-service | F93: • সারা বছর দান ও সেবা → /seasonal/year-round-charity-service | G93: Translated | H93: High | I93: Seerah or history; External resource or teacher; Tone and pastoral wording | J93: Scholar; Mentor | K93: review-needed | L93: 4 | M93: sunnah-com — Sunnah.com (Sunnah.com) yaqeen-institute — Yaqeen Institute (Yaqeen Institute for Islamic Research) sunnah-muslim-2749 — Sahih Muslim 2749: people who sin and seek forgiveness (Sunnah.com) sunnah-muslim-2750a — Sahih Muslim 2750a: the hadith of Hanzala (Sunnah.com) | X93: https://www.revertguide.com/en/roadmap/month-3-6/character#where-next-heading | Y93: character | Z93: locales/en/steps/character.json › relatedLinks | AA93: step:character
A94: R0093 | B94: Roadmap step | C94: Find your local Muslim community | D94: Title | E94: Find your local Muslim community Time estimate: An hour or two a week, building over time | F94: আপনার এলাকার মুসলিম কমিউনিটি খুঁজুন Time estimate: সপ্তাহে এক বা দুই ঘণ্টা, সময়ের সাথে বাড়তে থাকে | G94: Translated | H94: Medium | I94: Mental health; External resource or teacher; Tone and pastoral wording | J94: Mentor; Mental health professional | K94: source-checked | L94: 5 | M94: whyislam — WhyIslam (Islamic Circle of North America) icna — ICNA (Islamic Circle of North America) yaqeen-becoming-muslim — Becoming Muslim: The Lives of American Converts to Islam (Yaqeen Institute) islam-care-centre-convert-care — Convert Care (Islam Care Centre, Ottawa) (Islam Care Centre, Ottawa) masjid-toronto-programs — Masjid Toronto programs: New Muslims (Muslim Association of Canada) | N94: • Names Convert Care at Islam Care Centre (Ottawa) and Convert Connect at MAC Masjid Toronto as convert programmes; confirm both still run and details are current. • Recommends Khalil Center, a Muslim mental health service (online only per its source note; clinicians' provincial registration not listed); confirm suitability. • Suggests joining a local WhatsApp or Telegram group for Muslims in your area; the step itself adds no privacy or safety caveat. • Recommends ICNA New Muslim Support (US-based), WhyIslam and AboutIslam's new-Muslim pages. | O94: ⚠ The JSON has two 'relatedLinks' keys; the second replaces the first, so 'Religion or custom? Examples' and 'Everyday phrases and how to reply' never show. | X94: https://www.revertguide.com/en/roadmap/week-1/community | Y94: community | Z94: locales/en/steps/community.json › title, timeEstimate | AA94: step:community
A95: R0094 | B95: Roadmap step | C95: Find your local Muslim community | D95: Why it matters | E95: Islam was never meant to be practiced alone. The Muslim community (ummah) works something like a family: people celebrate with you, stay with you through the hard parts, and help you keep growing. Finding your local community is one of the most useful things you can do as a new Muslim. One friend or mentor who has been where you are can be the difference between feeling lost and feeling at home. | F95: ইসলাম কখনো একা পালনের জন্য ছিল না। মুসলিম সমাজ (উম্মাহ) অনেকটা পরিবারের মতো: মানুষ আপনার সাথে আনন্দ করে, কঠিন সময়ে পাশে থাকে, আর আপনাকে বেড়ে উঠতে সাহায্য করে। নতুন মুসলিম হিসেবে নিজের এলাকার কমিউনিটি খুঁজে পাওয়া আপনার করা সবচেয়ে কাজের বিষয়গুলোর একটি। আপনার জায়গায় আগে দাঁড়িয়েছিলেন এমন একজন বন্ধু বা মেন্টরই হারিয়ে যাওয়া আর আপন মনে হওয়ার মধ্যে পার্থক্য গড়ে দিতে পারেন। | G95: Translated | H95: Medium | I95: Mental health; External resource or teacher; Tone and pastoral wording | J95: Mentor; Mental health professional | K95: source-checked | L95: 5 | M95: whyislam — WhyIslam (Islamic Circle of North America) icna — ICNA (Islamic Circle of North America) yaqeen-becoming-muslim — Becoming Muslim: The Lives of American Converts to Islam (Yaqeen Institute) islam-care-centre-convert-care — Convert Care (Islam Care Centre, Ottawa) (Islam Care Centre, Ottawa) masjid-toronto-programs — Masjid Toronto programs: New Muslims (Muslim Association of Canada) | X95: https://www.revertguide.com/en/roadmap/week-1/community#why-heading | Y95: community | Z95: locales/en/steps/community.json › whyMatters | AA95: step:community
A96: R0095 | B96: Roadmap step | C96: Find your local Muslim community | D96: Action 1 of 4 | E96: Look for a programme for new Muslims • Many masjids and centres run something for converts, such as a weekly beginners' class or a convert support group. • Some Canadian masjids run named programmes for converts, such as Convert Care at Islam Care Centre in Ottawa or Convert Connect at MAC Masjid Toronto. The community topic lists more across Canada. Confirm times before you go. • Ask at your masjid, or phone one near you, and ask what they run for new Muslims. | F96: নতুন মুসলিমদের জন্য একটি কর্মসূচি খুঁজুন • অনেক মসজিদ আর কেন্দ্র নতুন মুসলিমদের জন্য কিছু চালায়, যেমন নতুনদের সাপ্তাহিক ক্লাস বা নতুন মুসলিমদের সহায়তা দল। • কানাডার কিছু মসজিদ নতুন মুসলিমদের জন্য নাম দেওয়া কর্মসূচি চালায়, যেমন অটোয়ার Islam Care Centre-এর Convert Care বা MAC Masjid Toronto-র Convert Connect। কমিউনিটি বিষয়ক পৃষ্ঠায় সারা কানাডার আরও কর্মসূচির তালিকা আছে। যাওয়ার আগে সময় নিশ্চিত করে নিন। • আপনার মসজিদে জিজ্ঞেস করুন, বা কাছের একটিতে ফোন করুন, আর তারা নতুন মুসলিমদের জন্য কী চালায় তা জানতে চান। | G96: Translated | H96: Medium | I96: Mental health; External resource or teacher; Tone and pastoral wording | J96: Mentor; Mental health professional | K96: source-checked | L96: 5 | M96: whyislam — WhyIslam (Islamic Circle of North America) icna — ICNA (Islamic Circle of North America) yaqeen-becoming-muslim — Becoming Muslim: The Lives of American Converts to Islam (Yaqeen Institute) islam-care-centre-convert-care — Convert Care (Islam Care Centre, Ottawa) (Islam Care Centre, Ottawa) masjid-toronto-programs — Masjid Toronto programs: New Muslims (Muslim Association of Canada) | X96: https://www.revertguide.com/en/roadmap/week-1/community#actions-heading | Y96: community | Z96: locales/en/steps/community.json › exactActions[0] | AA96: step:community
A97: R0096 | B97: Roadmap step | C97: Find your local Muslim community | D97: Action 2 of 4 | E97: Introduce yourself to the imam or community leader • The imam leads the prayer and is often the person people go to for guidance. Most are glad to meet a new Muslim. • Tell them you recently took your Shahada. • Ask about programs, classes, or study circles for new Muslims. • Ask your questions. Imams expect them and would rather you asked. | F97: ইমাম বা কমিউনিটির নেতার সাথে পরিচিত হোন • ইমাম নামাজে ইমামতি করেন, আর প্রায়ই মানুষ পরামর্শের জন্য তার কাছেই যায়। বেশিরভাগ ইমাম নতুন মুসলিমের সাথে দেখা হলে খুশি হন। • তাকে বলুন আপনি সম্প্রতি শাহাদা পড়েছেন। • নতুন মুসলিমদের জন্য অনুষ্ঠান, ক্লাস বা পাঠচক্র আছে কি না জিজ্ঞেস করুন। • আপনার প্রশ্নগুলো করুন। ইমামরা প্রশ্ন আশা করেন, আর আপনি জিজ্ঞেস করলেই খুশি হন। | G97: Translated | H97: Medium | I97: Mental health; External resource or teacher; Tone and pastoral wording | J97: Mentor; Mental health professional | K97: source-checked | L97: 5 | M97: whyislam — WhyIslam (Islamic Circle of North America) icna — ICNA (Islamic Circle of North America) yaqeen-becoming-muslim — Becoming Muslim: The Lives of American Converts to Islam (Yaqeen Institute) islam-care-centre-convert-care — Convert Care (Islam Care Centre, Ottawa) (Islam Care Centre, Ottawa) masjid-toronto-programs — Masjid Toronto programs: New Muslims (Muslim Association of Canada) | X97: https://www.revertguide.com/en/roadmap/week-1/community#actions-heading | Y97: community | Z97: locales/en/steps/community.json › exactActions[1] | AA97: step:community
A98: R0097 | B98: Roadmap step | C98: Find your local Muslim community | D98: Action 3 of 4 | E98: Find a mentor or a study buddy • Ask the imam or people at the masjid whether someone could mentor you. • A mentor answers your day-to-day questions, prays with you, and keeps you going. • Look for someone patient who knows their material and will not judge you. • A friend who is also still learning makes a good study partner too. • If local options are thin, online convert groups can fill some of the gap. | F98: একজন মেন্টর বা পড়ার সঙ্গী খুঁজুন • ইমাম বা মসজিদের মানুষদের জিজ্ঞেস করুন কেউ আপনার মেন্টর হতে পারবেন কি না। • মেন্টর আপনার প্রতিদিনের প্রশ্নের উত্তর দেন, আপনার সাথে নামাজ পড়েন, আর আপনাকে এগিয়ে যেতে সাহায্য করেন। • এমন কাউকে খুঁজুন যিনি ধৈর্যশীল, বিষয় জানেন, আর আপনাকে বিচার করবেন না। • যে বন্ধুও এখনো শিখছেন, তিনিও ভালো পড়ার সঙ্গী হতে পারেন। • স্থানীয় বিকল্প কম হলে অনলাইনের নতুন মুসলিমদের গ্রুপ কিছুটা ফাঁক পূরণ করতে পারে। | G98: Translated | H98: Medium | I98: Mental health; External resource or teacher; Tone and pastoral wording | J98: Mentor; Mental health professional | K98: source-checked | L98: 5 | M98: whyislam — WhyIslam (Islamic Circle of North America) icna — ICNA (Islamic Circle of North America) yaqeen-becoming-muslim — Becoming Muslim: The Lives of American Converts to Islam (Yaqeen Institute) islam-care-centre-convert-care — Convert Care (Islam Care Centre, Ottawa) (Islam Care Centre, Ottawa) masjid-toronto-programs — Masjid Toronto programs: New Muslims (Muslim Association of Canada) | X98: https://www.revertguide.com/en/roadmap/week-1/community#actions-heading | Y98: community | Z98: locales/en/steps/community.json › exactActions[2] | AA98: step:community
A99: R0098 | B99: Roadmap step | C99: Find your local Muslim community | D99: Action 4 of 4 | E99: Go to one class or one event • Many masjids run weekly halaqas (study circles), potlucks, or social nights. • These are the easiest places to meet people and learn without pressure. • Bring a dish to a potluck. It gives you something to talk about. • If big gatherings are too much, start with a small class or a one-on-one meeting. | F99: একটি ক্লাস বা একটি অনুষ্ঠানে যান • অনেক মসজিদ সাপ্তাহিক হালাকা (পাঠচক্র), সবাই মিলে খাবার আনার ভোজ বা সামাজিক সন্ধ্যা চালায়। • চাপ ছাড়া মানুষের সাথে পরিচিত হতে আর শিখতে এগুলোই সবচেয়ে সহজ জায়গা। • সবাই মিলে খাবার আনার ভোজে একটি পদ নিয়ে যান। এতে কথা বলার একটা বিষয় পাওয়া যায়। • বড় সমাবেশ বেশি মনে হলে ছোট একটি ক্লাস বা একান্ত সাক্ষাৎ দিয়ে শুরু করুন। | G99: Translated | H99: Medium | I99: Mental health; External resource or teacher; Tone and pastoral wording | J99: Mentor; Mental health professional | K99: source-checked | L99: 5 | M99: whyislam — WhyIslam (Islamic Circle of North America) icna — ICNA (Islamic Circle of North America) yaqeen-becoming-muslim — Becoming Muslim: The Lives of American Converts to Islam (Yaqeen Institute) islam-care-centre-convert-care — Convert Care (Islam Care Centre, Ottawa) (Islam Care Centre, Ottawa) masjid-toronto-programs — Masjid Toronto programs: New Muslims (Muslim Association of Canada) | X99: https://www.revertguide.com/en/roadmap/week-1/community#actions-heading | Y99: community | Z99: locales/en/steps/community.json › exactActions[3] | AA99: step:community
A100: R0099 | B100: Roadmap step | C100: Find your local Muslim community | D100: Obstacle 1 of 3 | E100: Problem: I feel like I don't fit in Solution: Islam spans more cultures than almost any other religion. Muslims in Canada come from dozens of countries. You belong here as much as the person standing next to you. It can take a few visits before it feels ordinary. Give yourself room and keep turning up, because that is how connection actually builds. | F100: Problem: মনে হয় আমি খাপ খাই না Solution: প্রায় অন্য যেকোনো ধর্মের চেয়ে ইসলাম বেশি সংস্কৃতি জুড়ে ছড়ানো। কানাডার মুসলিমরা কয়েক ডজন দেশ থেকে এসেছেন। পাশে দাঁড়ানো মানুষটির মতোই আপনিও এখানকার। স্বাভাবিক লাগতে কয়েকবার যেতে হতে পারে। নিজেকে সময় দিন আর আসতে থাকুন, কারণ সংযোগ আসলে এভাবেই গড়ে ওঠে। | G100: Translated | H100: Medium | I100: Mental health; External resource or teacher; Tone and pastoral wording | J100: Mentor; Mental health professional | K100: source-checked | L100: 5 | M100: whyislam — WhyIslam (Islamic Circle of North America) icna — ICNA (Islamic Circle of North America) yaqeen-becoming-muslim — Becoming Muslim: The Lives of American Converts to Islam (Yaqeen Institute) islam-care-centre-convert-care — Convert Care (Islam Care Centre, Ottawa) (Islam Care Centre, Ottawa) masjid-toronto-programs — Masjid Toronto programs: New Muslims (Muslim Association of Canada) | X100: https://www.revertguide.com/en/roadmap/week-1/community#obstacles-heading | Y100: community | Z100: locales/en/steps/community.json › obstacles[0] | AA100: step:community
A101: R0100 | B101: Roadmap step | C101: Find your local Muslim community | D101: Obstacle 2 of 3 | E101: Problem: I don't have any Muslim friends Solution: That is what this step is for. Every Muslim friend you will ever have starts out as a stranger. Masjid events, new Muslim classes, and online groups are all places to start. Be open and give it time. Even one solid connection changes how all of this feels. A local WhatsApp or Telegram group for Muslims in your area is worth joining too. | F101: Problem: আমার কোনো মুসলিম বন্ধু নেই Solution: এই ধাপ ঠিক সেজন্যই। আপনার ভবিষ্যতের প্রতিটি মুসলিম বন্ধু একসময় অচেনা থাকে। মসজিদের অনুষ্ঠান, নতুন মুসলিমদের ক্লাস আর অনলাইন গ্রুপ, সবই শুরুর জায়গা। খোলা মনে থাকুন আর সময় দিন। একটিমাত্র মজবুত সংযোগও পুরো ব্যাপারটার অনুভূতি বদলে দেয়। আপনার এলাকার মুসলিমদের একটি WhatsApp বা Telegram গ্রুপে যোগ দেওয়াও ভালো। | G101: Translated | H101: Medium | I101: Mental health; External resource or teacher; Tone and pastoral wording | J101: Mentor; Mental health professional | K101: source-checked | L101: 5 | M101: whyislam — WhyIslam (Islamic Circle of North America) icna — ICNA (Islamic Circle of North America) yaqeen-becoming-muslim — Becoming Muslim: The Lives of American Converts to Islam (Yaqeen Institute) islam-care-centre-convert-care — Convert Care (Islam Care Centre, Ottawa) (Islam Care Centre, Ottawa) masjid-toronto-programs — Masjid Toronto programs: New Muslims (Muslim Association of Canada) | X101: https://www.revertguide.com/en/roadmap/week-1/community#obstacles-heading | Y101: community | Z101: locales/en/steps/community.json › obstacles[1] | AA101: step:community
...

Sheet Items
A1: Item key | B1: Area | C1: Item | D1: Priority | E1: Review needed | F1: Suggested reviewer | G1: Current status (site) | H1: Key points to check | I1: Pre-check flags | J1: Sources (n) | K1: Sources used (id — title — link) | L1: Text rows | M1: Rows done | N1: Rows approved (EN) | O1: Rows approved (BN) | P1: Progress | Q1: Assigned reviewer(s) | R1: Item verdict | S1: Item notes | T1: Page URL | U1: JSON file
A2: stage:day-0-1 | B2: Roadmap stage | C2: Faith and a fresh start | D2: High | E2: Fiqh ruling; Safety or abuse; External resource or teacher; Tone and pastoral wording | F2: Scholar; Mentor | G2: not tracked | H2: • Says changing your name is not required (scholars usually add: unless the name's meaning conflicts with Islam). • Says make Ghusl 'when you feel ready'; the wudu-ghusl tool says it is required before prayer if you were in a state needing ghusl. • Recommends Mustafa Umar's 'Welcome to Islam', described as a free 32-page guide on his website; confirm page count and free access. • Ask-for-help triggers include not feeling safe telling family and needing a witness or certificate; no contacts are named. | J2: 3 | K2: new-muslim-academy — New Muslim Academy (New Muslim Academy) — https://www.newmuslimacademy.org/ whyislam — WhyIslam (Islamic Circle of North America) — https://www.whyislam.org/ new-muslim-guide — New Muslim Guide (New Muslim Guide) — https://newmuslimguide.com/en | L2: =COUNTIF('Review rows'!$AA$2:$AA$2058,$A2) -> 11 | M2: =COUNTIFS('Review rows'!$AA$2:$AA$2058,$A2,'Review rows'!$V$2:$V$2058,"Yes") -> 0 | N2: =COUNTIFS('Review rows'!$AA$2:$AA$2058,$A2,'Review rows'!$P$2:$P$2058,"Approved") -> 0 | O2: =COUNTIFS('Review rows'!$AA$2:$AA$2058,$A2,'Review rows'!$S$2:$S$2058,"Approved") -> 0 | P2: =IF(L2=0,"",IF(M2=L2,"Done",IF(M2>0,"In progress","Not started"))) -> Not started | T2: https://www.revertguide.com/en/roadmap/day-0-1 | U2: locales/en/stages.json
A3: stage:week-1 | B3: Roadmap stage | C3: Getting the basics in place | D3: Medium | E3: External resource or teacher; Tone and pastoral wording | F3: Scholar; Mentor | G3: not tracked | H3: • Says missing prayers while still learning is normal, and optional practices can wait until the required ones feel steady. • Recommends Quran.com's free 'Seven Days, Seven Verses' Al-Fatihah plan, readable without an account. • Recommends the New Muslim Academy prayer course and says it needs an account and the site uses analytics and an advertising pixel; confirm still true. | J3: 3 | K3: new-muslim-guide — New Muslim Guide (New Muslim Guide) — https://newmuslimguide.com/en seekersguidance — SeekersGuidance (SeekersGuidance) — https://seekersguidance.org/ whyislam — WhyIslam (Islamic Circle of North America) — https://www.whyislam.org/ | L3: =COUNTIF('Review rows'!$AA$2:$AA$2058,$A3) -> 11 | M3: =COUNTIFS('Review rows'!$AA$2:$AA$2058,$A3,'Review rows'!$V$2:$V$2058,"Yes") -> 0 | N3: =COUNTIFS('Review rows'!$AA$2:$AA$2058,$A3,'Review rows'!$P$2:$P$2058,"Approved") -> 0 | O3: =COUNTIFS('Review rows'!$AA$2:$AA$2058,$A3,'Review rows'!$S$2:$S$2058,"Approved") -> 0 | P3: =IF(L3=0,"",IF(M3=L3,"Done",IF(M3>0,"In progress","Not started"))) -> Not started | T3: https://www.revertguide.com/en/roadmap/week-1 | U3: locales/en/stages.json
A4: stage:week-2-3 | B4: Roadmap stage | C4: Settling into practice | D4: Medium | E4: External resource or teacher; Tone and pastoral wording | F4: Scholar; Mentor | G4: not tracked | H4: • Recommends a masjid Arabic-reading class (letters, vowels, joining, short surahs) with The Clear Quran or Abdel Haleem's translation. • Recommends New Muslim Academy live Quran classes: free, evenings Eastern time, brothers and sisters taught separately, sign-up form first. • Ask-for-help triggers include family pressure turning unsafe or controlling and doubts that stop you functioning; no contacts are named. • Guardrails: free before paid, and be careful with one-to-one tutoring from academies you cannot check. | J4: 3 | K4: quran-com — Quran.com (Quran Foundation) — https://quran.com/ yaqeen-institute — Yaqeen Institute (Yaqeen Institute for Islamic Research) — https://yaqeeninstitute.org/ seekersguidance — SeekersGuidance (SeekersGuidance) — https://seekersguidance.org/ | L4: =COUNTIF('Review rows'!$AA$2:$AA$2058,$A4) -> 11 | M4: =COUNTIFS('Review rows'!$AA$2:$AA$2058,$A4,'Review rows'!$V$2:$V$2058,"Yes") -> 0 | N4: =COUNTIFS('Review rows'!$AA$2:$AA$2058,$A4,'Review rows'!$P$2:$P$2058,"Approved") -> 0 | O4: =COUNTIFS('Review rows'!$AA$2:$AA$2058,$A4,'Review rows'!$S$2:$S$2058,"Approved") -> 0 | P4: =IF(L4=0,"",IF(M4=L4,"Done",IF(M4>0,"In progress","Not started"))) -> Not started | T4: https://www.revertguide.com/en/roadmap/week-2-3 | U4: locales/en/stages.json
A5: stage:month-1-2 | B5: Roadmap stage | C5: Islam in daily life | D5: Medium | E5: Canadian services or contacts; External resource or teacher; Tone and pastoral wording | F5: Scholar; Mentor | G5: not tracked | H5: • Recommends New Muslim Academy core courses or SeekersGuidance's free live 'Essentials of Faith, Worship, and Spirituality', Saturdays 10:00 Eastern; confirm the schedule. • Recommends Quran.com learning plans for short surahs such as Al-Ikhlas, Al-Falaq and An-Nas. • Ask-for-help triggers: food or clothing pressure risking safety at home, a medical condition affecting fasting, a ruling on work, school or money. • Guardrail: choose a prayer times app that keeps your location on your phone and has no ads. | J5: 2 | K5: new-muslim-guide — New Muslim Guide (New Muslim Guide) — https://newmuslimguide.com/en seekersguidance — SeekersGuidance (SeekersGuidance) — https://seekersguidance.org/ | L5: =COUNTIF('Review rows'!$AA$2:$AA$2058,$A5) -> 11 | M5: =COUNTIFS('Review rows'!$AA$2:$AA$2058,$A5,'Review rows'!$V$2:$V$2058,"Yes") -> 0 | N5: =COUNTIFS('Review rows'!$AA$2:$AA$2058,$A5,'Review rows'!$P$2:$P$2058,"Approved") -> 0 | O5: =COUNTIFS('Review rows'!$AA$2:$AA$2058,$A5,'Review rows'!$S$2:$S$2058,"Approved") -> 0 | P5: =IF(L5=0,"",IF(M5=L5,"Done",IF(M5>0,"In progress","Not started"))) -> Not started | T5: https://www.revertguide.com/en/roadmap/month-1-2 | U5: locales/en/stages.json
A6: stage:month-3-6 | B6: Roadmap stage | C6: Character and steady learning | D6: Medium | E6: External resource or teacher; Tone and pastoral wording | F6: Scholar; Mentor | G6: not tracked | H6: • Recommends Yaqeen Institute's free ebook 'Qur'an 30 for 30: Thematic Tafsir' by Dr. Omar Suleiman and Sh. Ismail Kamdar. • Recommends a local halaqa; guardrails say learn from a teacher you can meet or check, and skip debate channels in the first months. | J6: 3 | K6: seekersguidance — SeekersGuidance (SeekersGuidance) — https://seekersguidance.org/ yaqeen-institute — Yaqeen Institute (Yaqeen Institute for Islamic Research) — https://yaqeeninstitute.org/ sunnah-com — Sunnah.com (Sunnah.com) — https://sunnah.com/ | L6: =COUNTIF('Review rows'!$AA$2:$AA$2058,$A6) -> 11 | M6: =COUNTIFS('Review rows'!$AA$2:$AA$2058,$A6,'Review rows'!$V$2:$V$2058,"Yes") -> 0 | N6: =COUNTIFS('Review rows'!$AA$2:$AA$2058,$A6,'Review rows'!$P$2:$P$2058,"Approved") -> 0 | O6: =COUNTIFS('Review rows'!$AA$2:$AA$2058,$A6,'Review rows'!$S$2:$S$2058,"Approved") -> 0 | P6: =IF(L6=0,"",IF(M6=L6,"Done",IF(M6>0,"In progress","Not started"))) -> Not started | T6: https://www.revertguide.com/en/roadmap/month-3-6 | U6: locales/en/stages.json
A7: stage:month-6-plus | B7: Roadmap stage | C7: Growth over a lifetime | D7: High | E7: Fiqh ruling; Financial (zakat, riba, money); External resource or teacher | F7: Scholar; Mentor | G7: not tracked | H7: • Says Hajj is not owed until you are able to go, and zakat does not apply below the threshold (nisab). • Recommends MAC eLearning, free online courses from the Muslim Association of Canada. • Recommends Tafsir Ibn Kathir abridged (30th part), a paid Darussalam print book. | J7: 3 | K7: quran-zakat-9-60 — Quran 9:60 - Zakat recipient categories (Quran.com) — https://quran.com/9/60 cra-charities-listing — List of charities and other qualified donees (Canada Revenue Agency) — https://www.canada.ca/en/revenue-agency/services/charities-giving/list-charities/list-charities-other-qualified-donees.html seekersguidance — SeekersGuidance (SeekersGuidance) — https://seekersguidance.org/ | L7: =COUNTIF('Review rows'!$AA$2:$AA$2058,$A7) -> 11 | M7: =COUNTIFS('Review rows'!$AA$2:$AA$2058,$A7,'Review rows'!$V$2:$V$2058,"Yes") -> 0 | N7: =COUNTIFS('Review rows'!$AA$2:$AA$2058,$A7,'Review rows'!$P$2:$P$2058,"Approved") -> 0 | O7: =COUNTIFS('Review rows'!$AA$2:$AA$2058,$A7,'Review rows'!$S$2:$S$2058,"Approved") -> 0 | P7: =IF(L7=0,"",IF(M7=L7,"Done",IF(M7>0,"In progress","Not started"))) -> Not started | T7: https://www.revertguide.com/en/roadmap/month-6-plus | U7: locales/en/stages.json
A8: step:asking-an-imam | B8: Roadmap step | C8: Ask an imam a good question | D8: Medium | E8: External resource or teacher; Tone and pastoral wording | F8: Scholar; Mentor | G8: source-checked | H8: • Says marriage, divorce, inheritance, zakat, abuse, medical and legal matters all need careful review, with professional help for medical, legal or financial issues. • Says online answers often differ because they follow different schools or someone else's situation, so note the source and school of each. • Recommends SeekersGuidance, New Muslim Academy and ICNA New Muslim Support (a US-based organisation) as resource cards. | J8: 3 | K8: seekersguidance — SeekersGuidance (SeekersGuidance) — https://seekersguidance.org/ new-muslim-academy — New Muslim Academy (New Muslim Academy) — https://www.newmuslimacademy.org/ whyislam — WhyIslam (Islamic Circle of North America) — https://www.whyislam.org/ | L8: =COUNTIF('Review rows'!$AA$2:$AA$2058,$A8) -> 11 | M8: =COUNTIFS('Review rows'!$AA$2:$AA$2058,$A8,'Review rows'!$V$2:$V$2058,"Yes") -> 0 | N8: =COUNTIFS('Review rows'!$AA$2:$AA$2058,$A8,'Review rows'!$P$2:$P$2058,"Approved") -> 0 | O8: =COUNTIFS('Review rows'!$AA$2:$AA$2058,$A8,'Review rows'!$S$2:$S$2058,"Approved") -> 0 | P8: =IF(L8=0,"",IF(M8=L8,"Done",IF(M8>0,"In progress","Not started"))) -> Not started | T8: https://www.revertguide.com/en/roadmap/month-3-6/asking-an-imam | U8: locales/en/steps/asking-an-imam.json
A9: step:character | B9: Roadmap step | C9: Work on your character (akhlaq) | D9: High | E9: Quran or hadith citation; Seerah or history; Arabic text or transliteration; External resource or teacher; Tone and pastoral wording | F9: Scholar; Mentor | G9: review-needed | H9: • Quotes 'I was sent to perfect good character', 'best of you have the best character', 'actions are by intentions', the strong-man and 'best to their families' hadith; only generic sunnah-com id. • Cites Muslim 2749 (if people did not sin, Allah would bring people who sin and seek forgiveness), Muslim 2750a (Hanzala feared hypocrisy) and Quran 33:21. • Calls Martin Lings' 'Muhammad: His Life Based on the Earliest Sources' the usual first seerah; confirm it suits (Lings was a Perennialist Sufi). Resource card is Yasir Qadhi's Seerah. • Says nightly self-review (muhasabah) was a companions' practice, and advises 'Inna lillahi wa inna ilayhi raji'un' for everyday impatience such as traffic and queues. | I9: ⚠ Virtue list leads with Arabic: 'Sabr (patience)', 'Sidq (truthfulness)', 'Tawadu (humility)', 'Ihsan', 'Shukr', 'Rahmah'; the naming rule puts plain English first. | J9: 4 | K9: sunnah-com — Sunnah.com (Sunnah.com) — https://sunnah.com/ yaqeen-institute — Yaqeen Institute (Yaqeen Institute for Islamic Research) — https://yaqeeninstitute.org/ sunnah-muslim-2749 — Sahih Muslim 2749: people who sin and seek forgiveness (Sunnah.com) — https://sunnah.com/muslim:2749 sunnah-muslim-2750a — Sahih Muslim 2750a: the hadith of Hanzala (Sunnah.com) — https://sunnah.com/muslim:2750a | L9: =COUNTIF('Review rows'!$AA$2:$AA$2058,$A9) -> 15 | M9: =COUNTIFS('Review rows'!$AA$2:$AA$2058,$A9,'Review rows'!$V$2:$V$2058,"Yes") -> 0 | N9: =COUNTIFS('Review rows'!$AA$2:$AA$2058,$A9,'Review rows'!$P$2:$P$2058,"Approved") -> 0 | O9: =COUNTIFS('Review rows'!$AA$2:$AA$2058,$A9,'Review rows'!$S$2:$S$2058,"Approved") -> 0 | P9: =IF(L9=0,"",IF(M9=L9,"Done",IF(M9>0,"In progress","Not started"))) -> Not started | T9: https://www.revertguide.com/en/roadmap/month-3-6/character | U9: locales/en/steps/character.json
A10: step:community | B10: Roadmap step | C10: Find your local Muslim community | D10: Medium | E10: Mental health; Canadian services or contacts; External resource or teacher; Tone and pastoral wording | F10: Mentor; Mental health professional | G10: source-checked | H10: • Names Convert Care at Islam Care Centre (Ottawa) and Convert Connect at MAC Masjid Toronto as convert programmes; confirm both still run and details are current. • Recommends Khalil Center, a Muslim mental health service (online only per its source note; clinicians' provincial registration not listed); confirm suitability. • Suggests joining a local WhatsApp or Telegram group for Muslims in your area; the step itself adds no privacy or safety caveat. • Recommends ICNA New Muslim Support (US-based), WhyIslam and AboutIslam's new-Muslim pages. | I10: ⚠ The JSON has two 'relatedLinks' keys; the second replaces the first, so 'Religion or custom? Examples' and 'Everyday phrases and how to reply' never show. | J10: 5 | K10: whyislam — WhyIslam (Islamic Circle of North America) — https://www.whyislam.org/ icna — ICNA (Islamic Circle of North America) — https://icna.org/ yaqeen-becoming-muslim — Becoming Muslim: The Lives of American Converts to Islam (Yaqeen Institute) — https://yaqeeninstitute.org/read/data/reports/becoming-muslim-lives-of-american-converts-to-islam islam-care-centre-convert-care — Convert Care (Islam Care Centre, Ottawa) (Islam Care Centre, Ottawa) — https://islamcare.ca/services/convert-care/ masjid-toronto-programs — Masjid Toronto programs: New Muslims (Muslim Association of Canada) — https://centres.macnet.ca/masjidtoronto/programs/ | L10: =COUNTIF('Review rows'!$AA$2:$AA$2058,$A10) -> 12 | M10: =COUNTIFS('Review rows'!$AA$2:$AA$2058,$A10,'Review rows'!$V$2:$V$2058,"Yes") -> 0 | N10: =COUNTIFS('Review rows'!$AA$2:$AA$2058,$A10,'Review rows'!$P$2:$P$2058,"Approved") -> 0 | O10: =COUNTIFS('Review rows'!$AA$2:$AA$2058,$A10,'Review rows'!$S$2:$S$2058,"Approved") -> 0 | P10: =IF(L10=0,"",IF(M10=L10,"Done",IF(M10>0,"In progress","Not started"))) -> Not started | T10: https://www.revertguide.com/en/roadmap/week-1/community | U10: locales/en/steps/community.json
A11: step:daily-dua-dhikr | B11: Roadmap step | C11: Daily remembrance habit (dua and dhikr) | D11: Medium | E11: Fiqh ruling; External resource or teacher; Tone and pastoral wording | F11: Scholar; Mentor | G11: review-needed | H11: • Says you can make dua in your own language, with no note that the Hanafi school restricts non-Arabic dua inside the prayer (the dua tool limits it to outside fixed recitation). • Recommends Fortress of the Muslim (Darussalam) as a sourced dua collection, plus Quran.com and New Muslim Academy. | J11: 3 | K11: quran-com — Quran.com (Quran Foundation) — https://quran.com/ sunnah-com — Sunnah.com (Sunnah.com) — https://sunnah.com/ darussalam — Darussalam UK store (Darussalam UK) — https://darussalam.com/ | L11: =COUNTIF('Review rows'!$AA$2:$AA$2058,$A11) -> 11 | M11: =COUNTIFS('Review rows'!$AA$2:$AA$2058,$A11,'Review rows'!$V$2:$V$2058,"Yes") -> 0 | N11: =COUNTIFS('Review rows'!$AA$2:$AA$2058,$A11,'Review rows'!$P$2:$P$2058,"Approved") -> 0 | O11: =COUNTIFS('Review rows'!$AA$2:$AA$2058,$A11,'Review rows'!$S$2:$S$2058,"Approved") -> 0 | P11: =IF(L11=0,"",IF(M11=L11,"Done",IF(M11>0,"In progress","Not started"))) -> Not started | T11: https://www.revertguide.com/en/roadmap/week-1/daily-dua-dhikr | U11: locales/en/steps/daily-dua-dhikr.json
A12: step:family-and-friends | B12: Roadmap step | C12: Tell your family and friends | D12: High | E12: Aqidah (belief); Quran or hadith citation; Safety or abuse; Family, marriage or intimacy; Tone and pastoral wording | F12: Scholar; Mentor | G12: review-needed | H12: • Script for a Christian relative: 'Muslims believe he is the Messiah and a great prophet, and we honour Mary... God is one and has no son' (Quran 29:46 cited). • Says Islam holds you to good character and to keeping family ties, not cutting them. • Safety note: if telling someone could cost you housing or risk harm or control, speak to a local support person first; no named service or contact is given. • Online script: you do not owe anyone your story; wait until settled before posting about your Shahada (links the red flags guide). | J12: 4 | K12: whyislam — WhyIslam (Islamic Circle of North America) — https://www.whyislam.org/ yaqeen-becoming-muslim — Becoming Muslim: The Lives of American Converts to Islam (Yaqeen Institute) — https://yaqeeninstitute.org/read/data/reports/becoming-muslim-lives-of-american-converts-to-islam khalil-center — Khalil Center (Khalil Center) — https://khalilcenter.ca/ quran-29-46 — Quran 29:46: Speak with the People of the Book in the best way (Quran.com) — https://quran.com/29/46 | L12: =COUNTIF('Review rows'!$AA$2:$AA$2058,$A12) -> 21 | M12: =COUNTIFS('Review rows'!$AA$2:$AA$2058,$A12,'Review rows'!$V$2:$V$2058,"Yes") -> 0 | N12: =COUNTIFS('Review rows'!$AA$2:$AA$2058,$A12,'Review rows'!$P$2:$P$2058,"Approved") -> 0 | O12: =COUNTIFS('Review rows'!$AA$2:$AA$2058,$A12,'Review rows'!$S$2:$S$2058,"Approved") -> 0 | P12: =IF(L12=0,"",IF(M12=L12,"Done",IF(M12>0,"In progress","Not started"))) -> Not started | T12: https://www.revertguide.com/en/roadmap/week-2-3/family-and-friends | U12: locales/en/steps/family-and-friends.json
A13: step:fasting | B13: Roadmap step | C13: Learn how fasting works (sawm) | D13: High | E13: Fiqh ruling; Quran or hadith citation; Medical or health; Tone and pastoral wording | F13: Scholar; Medical professional | G13: review-needed | H13: • Says 'in the Hanafi school' kissing or touching that leads to ejaculation breaks the fast; the other schools hold the same, so the attribution may mislead. • Exemptions: travel, illness, pregnancy or nursing at risk, menstruation (made up), fidyah only if never able; Diabetes Canada: see a doctor 1 to 3 months before Ramadan. • Says eating or drinking by forgetting does not break the fast (the Prophet called it a provision from Allah), and a Toronto winter fast is roughly ten hours. • Quotes Quran 2:183 but the specific id is 2:184; forgetful-eating and dates-and-water hadith have no ids; Nasa'i 2420 and Muslim 1164 are cited but not used in the text. | I13: ⚠ Validity line says a fast counts only if 'you are not in an exempt category' and omits intercourse; earlier the step lets travellers fast and lists intercourse as breaking it. | J13: 9 | K13: quran-com — Quran.com (Quran Foundation) — https://quran.com/ sunnah-com — Sunnah.com (Sunnah.com) — https://sunnah.com/ yaqeen-institute — Yaqeen Institute (Yaqeen Institute for Islamic Research) — https://yaqeeninstitute.org/ quran-2-184 — Quran 2:184: Who may skip fasting, make-up days and fidyah (Quran.com) — https://quran.com/2/184 diabetes-canada-ramadan — Ramadan and diabetes (health-care provider tools) (Diabetes Canada) — https://www.diabetes.ca/for-professionals/health-care-provider-tools/ramadan-and-diabetes sunnah-tirmidhi-747 — Jami at-Tirmidhi 747: Fasting on Mondays and Thursdays (Sunnah.com) — https://sunnah.com/tirmidhi:747 sunnah-nasai-2420 — Sunan an-Nasa'i 2420: Fasting three days each month (Sunnah.com) — https://sunnah.com/nasai:2420 sunnah-muslim-1164 — Sahih Muslim 1164: Six days of Shawwal (Sunnah.com) — https://sunnah.com/muslim:1164 seekersguidance-complete-guide-fasting — The Complete Guide to Fasting (SeekersGuidance) — https://seekersguidance.org/answers/general-counsel/the-complete-guide-to-fasting/ | L13: =COUNTIF('Review rows'!$AA$2:$AA$2058,$A13) -> 15 | M13: =COUNTIFS('Review rows'!$AA$2:$AA$2058,$A13,'Review rows'!$V$2:$V$2058,"Yes") -> 0 | N13: =COUNTIFS('Review rows'!$AA$2:$AA$2058,$A13,'Review rows'!$P$2:$P$2058,"Approved") -> 0 | O13: =COUNTIFS('Review rows'!$AA$2:$AA$2058,$A13,'Review rows'!$S$2:$S$2058,"Approved") -> 0 | P13: =IF(L13=0,"",IF(M13=L13,"Done",IF(M13>0,"In progress","Not started"))) -> Not started | T13: https://www.revertguide.com/en/roadmap/month-1-2/fasting | U13: locales/en/steps/fasting.json
A14: step:first-24-hours | B14: Roadmap step | C14: Your first day as a Muslim | D14: Medium | E14: Fiqh ruling; Safety or abuse; External resource or teacher; Tone and pastoral wording | F14: Scholar; Mentor | G14: source-checked | H14: • Says a Shahada certificate can help later for marriage, Hajj, Umrah or community records, but your Islam does not depend on paperwork. • Advises a safety plan before telling family if safety at home is a concern, and a trusted mentor first if hostility is expected; links red flags guide and Get help. • Says to start with faith, purification, the basics of prayer and someone to ask, and to ask a mentor for help with Ghusl. • Recommends New Muslim Academy, WhyIslam and Mustafa Umar's 'Welcome to Islam'. | J14: 3 | K14: new-muslim-academy — New Muslim Academy (New Muslim Academy) — https://www.newmuslimacademy.org/ whyislam — WhyIslam (Islamic Circle of North America) — https://www.whyislam.org/ new-muslim-guide — New Muslim Guide (New Muslim Guide) — https://newmuslimguide.com/en | L14: =COUNTIF('Review rows'!$AA$2:$AA$2058,$A14) -> 16 | M14: =COUNTIFS('Review rows'!$AA$2:$AA$2058,$A14,'Review rows'!$V$2:$V$2058,"Yes") -> 0 | N14: =COUNTIFS('Review rows'!$AA$2:$AA$2058,$A14,'Review rows'!$P$2:$P$2058,"Approved") -> 0 | O14: =COUNTIFS('Review rows'!$AA$2:$AA$2058,$A14,'Review rows'!$S$2:$S$2058,"Approved") -> 0 | P14: =IF(L14=0,"",IF(M14=L14,"Done",IF(M14>0,"In progress","Not started"))) -> Not started | T14: https://www.revertguide.com/en/roadmap/day-0-1/first-24-hours | U14: locales/en/steps/first-24-hours.json
A15: step:first-jumuah | B15: Roadmap step | C15: Go to your first Friday prayer | D15: High | E15: Fiqh ruling; Quran or hadith citation; Tone and pastoral wording | F15: Scholar; Mentor | G15: review-needed | H15: • Says Friday prayer is an obligation for adult men and not required of women (Abu Dawud 1067); if a woman attends, it takes the place of Dhuhr. • Reports a Hanafi answer (Mufti Muhammad ibn Adam) that a job regularly preventing Jumuah attendance is not permitted, and tells readers to ask a scholar. • Says the Friday ghusl is recommended, not a condition, and wudu alone is valid (Abu Dawud 354); say Ameen with the imam after Al-Fatihah (Bukhari 780). • Says scholars differ on praying two rak'ahs when arriving during the sermon (Muslim 875c); do not step over people (Abu Dawud 1118). | J15: 15 | K15: new-muslim-guide — New Muslim Guide (New Muslim Guide) — https://newmuslimguide.com/en seekersguidance — SeekersGuidance (SeekersGuidance) — https://seekersguidance.org/ whyislam — WhyIslam (Islamic Circle of North America) — https://www.whyislam.org/ sunnah-bukhari-934 — Sahih al-Bukhari 934: Silence during the Friday sermon (Sunnah.com) — https://sunnah.com/bukhari:934 sunnah-abudawud-1118 — Sunan Abi Dawud 1118: Do not step over people at Jumu'ah (Sunnah.com) — https://sunnah.com/abudawud:1118 sunnah-muslim-875c — Sahih Muslim 875c: Two rak'ahs for a man who arrived during the Friday sermon (Sunnah.com) — https://sunnah.com/muslim:875c sunnah-bukhari-780 — Sahih al-Bukhari 780: Say Ameen when the imam says it (Sunnah.com) — https://sunnah.com/bukhari:780 sunnah-bukhari-877 — Sahih al-Bukhari 877 - The full-body wash for Friday prayer (Sunnah.com) — https://sunnah.com/bukhari:877 sunnah-abudawud-354 — Sunan Abi Dawud 354 - Wudu is fine on Friday, the full-body wash is better (Sunnah.com) — https://sunnah.com/abudawud:354 seekersguidance-friday-ghusl-hanafi — The Ritual Bath (Ghusl) on Friday: What Is It a Sunna For? (Hanafi) (SeekersGuidance) — https://seekersguidance.org/answers/hanafi-fiqh/the-ritual-bath-ghusl-on-friday-what-is-it-a-sunna-for/ sunnah-bukhari-636 — Sahih al-Bukhari 636: Pray what you catch and complete what you missed (Sunnah.com) — https://sunnah.com/bukhari:636 sunnah-abudawud-1067 — Sunan Abi Dawud 1067 - Who Friday prayer is obligatory on (Sunnah.com) — https://sunnah.com/abudawud:1067 seekersguidance-friday-prayer-rulings — The Detailed Rulings Related to Friday Prayer (Hanafi) (SeekersGuidance) — https://seekersguidance.org/answers/hanafi-fiqh/the-rulings-related-to-friday-prayer/ seekersguidance-missing-jumuah-for-work — Is It Permissible to Miss the Friday Prayer in the West Because of Work? (Hanafi) (SeekersGuidance) — https://seekersguidance.org/answers/hanafi-fiqh/is-it-permissible-to-miss-the-friday-prayer-in-the-west-because-of-work/ quran-62-9-friday-call — Quran 62:9 - The call to Friday prayer (Quran.com) — https://quran.com/62/9 | L15: =COUNTIF('Review rows'!$AA$2:$AA$2058,$A15) -> 14 | M15: =COUNTIFS('Review rows'!$AA$2:$AA$2058,$A15,'Review rows'!$V$2:$V$2058,"Yes") -> 0 | N15: =COUNTIFS('Review rows'!$AA$2:$AA$2058,$A15,'Review rows'!$P$2:$P$2058,"Approved") -> 0 | O15: =COUNTIFS('Review rows'!$AA$2:$AA$2058,$A15,'Review rows'!$S$2:$S$2058,"Approved") -> 0 | P15: =IF(L15=0,"",IF(M15=L15,"Done",IF(M15>0,"In progress","Not started"))) -> Not started | T15: https://www.revertguide.com/en/roadmap/week-1/first-jumuah | U15: locales/en/steps/first-jumuah.json
A16: step:first-masjid-visit | B16: Roadmap step | C16: Visit a masjid for the first time | D16: Medium | E16: Canadian services or contacts; External resource or teacher; Tone and pastoral wording | F16: Mentor | G16: source-checked | H16: • Says Convert Care at Islam Care Centre (Ottawa) and Convert Connect at MAC Masjid Toronto can arrange a guide for a first visit; confirm both are current. • Dress advice: men wear long pants and a sleeved shirt; women bring a scarf to enter the prayer area; many masjids keep spare scarves. • Etiquette: do not walk in front of someone praying (Bukhari 510); people repeat the adhan softly (Muslim 384); men and women usually pray separately. • Recommends ICNA New Muslim Support (US-based), WhyIslam and New Muslim Guide, and points to the in-app Masjid Finder. | J16: 7 | K16: whyislam — WhyIslam (Islamic Circle of North America) — https://www.whyislam.org/ icna — ICNA (Islamic Circle of North America) — https://icna.org/ new-muslim-guide — New Muslim Guide (New Muslim Guide) — https://newmuslimguide.com/en islam-care-centre-convert-care — Convert Care (Islam Care Centre, Ottawa) (Islam Care Centre, Ottawa) — https://islamcare.ca/services/convert-care/ masjid-toronto-programs — Masjid Toronto programs: New Muslims (Muslim Association of Canada) — https://centres.macnet.ca/masjidtoronto/programs/ sunnah-bukhari-510 — Sahih al-Bukhari 510: Do not pass in front of someone praying (Sunnah.com) — https://sunnah.com/bukhari:510 sunnah-muslim-384 — Sahih Muslim 384 - Replying to the adhan (Sunnah.com) — https://sunnah.com/muslim:384 | L16: =COUNTIF('Review rows'!$AA$2:$AA$2058,$A16) -> 13 | M16: =COUNTIFS('Review rows'!$AA$2:$AA$2058,$A16,'Review rows'!$V$2:$V$2058,"Yes") -> 0 | N16: =COUNTIFS('Review rows'!$AA$2:$AA$2058,$A16,'Review rows'!$P$2:$P$2058,"Approved") -> 0 | O16: =COUNTIFS('Review rows'!$AA$2:$AA$2058,$A16,'Review rows'!$S$2:$S$2058,"Approved") -> 0 | P16: =IF(L16=0,"",IF(M16=L16,"Done",IF(M16>0,"In progress","Not started"))) -> Not started | T16: https://www.revertguide.com/en/roadmap/week-1/first-masjid-visit | U16: locales/en/steps/first-masjid-visit.json
A17: step:ghusl | B17: Roadmap step | C17: Make the full-body wash (ghusl) | D17: High | E17: Fiqh ruling; Medical or health; Tone and pastoral wording | F17: Scholar | G17: review-needed | H17: • Says ghusl is 'recommended' after Shahada; does not say it is required if you were in a state needing ghusl, or that Maliki/Hanbali require it (the wudu-ghusl tool does). • Says the minimum is water over the whole body plus intention; the Hanafi school also requires rinsing the mouth and nose and does not make intention a condition. • Its wudu sub-steps (face, arms, head, feet) leave out rinsing the mouth and nose, which the prayer step and the wudu tool include. • Says tayammum takes the place of ghusl when water is unavailable or unusable; only generic sources (New Muslim Guide, SeekersGuidance) are cited. | J17: 2 | K17: new-muslim-guide — New Muslim Guide (New Muslim Guide) — https://newmuslimguide.com/en seekersguidance — SeekersGuidance (SeekersGuidance) — https://seekersguidance.org/ | L17: =COUNTIF('Review rows'!$AA$2:$AA$2058,$A17) -> 13 | M17: =COUNTIFS('Review rows'!$AA$2:$AA$2058,$A17,'Review rows'!$V$2:$V$2058,"Yes") -> 0 | N17: =COUNTIFS('Review rows'!$AA$2:$AA$2058,$A17,'Review rows'!$P$2:$P$2058,"Approved") -> 0 | O17: =COUNTIFS('Review rows'!$AA$2:$AA$2058,$A17,'Review rows'!$S$2:$S$2058,"Approved") -> 0 | P17: =IF(L17=0,"",IF(M17=L17,"Done",IF(M17>0,"In progress","Not started"))) -> Not started | T17: https://www.revertguide.com/en/roadmap/day-0-1/ghusl | U17: locales/en/steps/ghusl.json
A18: step:halal-eating-practical | B18: Roadmap step | C18: Eat halal day to day | D18: High | E18: Fiqh ruling; External resource or teacher; Tone and pastoral wording | F18: Scholar; Mentor | G18: review-needed | H18: • Recommends seafood as an easy early option, twice, with no note that the Hanafi school allows fish only (the halal-haram step says other seafood differs). • Says buy halal-certified meat when you can and look for certifiers you recognise locally; gelatin, enzymes, cross-contamination and standards vary. | J18: 2 | K18: new-muslim-guide — New Muslim Guide (New Muslim Guide) — https://newmuslimguide.com/en seekersguidance — SeekersGuidance (SeekersGuidance) — https://seekersguidance.org/ | L18: =COUNTIF('Review rows'!$AA$2:$AA$2058,$A18) -> 12 | M18: =COUNTIFS('Review rows'!$AA$2:$AA$2058,$A18,'Review rows'!$V$2:$V$2058,"Yes") -> 0 | N18: =COUNTIFS('Review rows'!$AA$2:$AA$2058,$A18,'Review rows'!$P$2:$P$2058,"Approved") -> 0 | O18: =COUNTIFS('Review rows'!$AA$2:$AA$2058,$A18,'Review rows'!$S$2:$S$2058,"Approved") -> 0 | P18: =IF(L18=0,"",IF(M18=L18,"Done",IF(M18>0,"In progress","Not started"))) -> Not started | T18: https://www.revertguide.com/en/roadmap/month-1-2/halal-eating-practical | U18: locales/en/steps/halal-eating-practical.json
A19: step:halal-haram | B19: Roadmap step | C19: Learn the halal and haram basics | D19: High | E19: Fiqh ruling; Quran or hadith citation; Canadian services or contacts; Tone and pastoral wording | F19: Scholar; Mentor | G19: review-needed | H19: • Says the Hanafi school allows tiny non-wine alcohol in flavourings (e.g. vanilla extract) when it cannot intoxicate; cooking wine is out; alcohol-free is the careful choice. • Says many scholars and Canadian certifiers accept only zabiha, while others accept People of the Book meat under Quran 5:5 (AMJA fatwa cited). • Says fish is halal in every school and other seafood differs; everything is halal unless prohibited; leave doubtful matters; eating haram unknowingly carries no sin. • Says a Canadian halal label must name its certifier (CFIA), and names HMA and ISNA Canada Halal as common certifiers whose standards differ. | J19: 7 | K19: new-muslim-guide — New Muslim Guide (New Muslim Guide) — https://newmuslimguide.com/en seekersguidance — SeekersGuidance (SeekersGuidance) — https://seekersguidance.org/ quran-5-5 — Quran 5:5: The food of the People of the Book (Quran.com) — https://quran.com/5/5 amja-eating-the-meat-of-the — Eating The Meat Of The People Of The Book (AMJA fatwa 80178) (Assembly of Muslim Jurists of America (AMJA)) — https://www.amjaonline.org/fatwa/en/80178/eating-the-meat-of-the-people-of-the-book seekersguidance-is-vanilla-extract-permissible-if — Is Vanilla Extract Permissible If It was Extracted with Non-Wine Alcohol? (SeekersGuidance) — https://seekersguidance.org/answers/halal-and-haram/is-vanilla-extract-permissible-if-it-was-extracted-with-non-wine-alcohol/ hma-what-is-halal — What is halal (HMA) (Halal Monitoring Authority (HMA)) — https://hmacanada.org/what-is-halal/ cfia-method-production-claims — Method of production claims on food labels (section: Halal and kosher claims) (Canadian Food Inspection Agency) — https://inspection.canada.ca/en/food-labels/labelling/industry/method-production-claims | L19: =COUNTIF('Review rows'!$AA$2:$AA$2058,$A19) -> 15 | M19: =COUNTIFS('Review rows'!$AA$2:$AA$2058,$A19,'Review rows'!$V$2:$V$2058,"Yes") -> 0 | N19: =COUNTIFS('Review rows'!$AA$2:$AA$2058,$A19,'Review rows'!$P$2:$P$2058,"Approved") -> 0 | O19: =COUNTIFS('Review rows'!$AA$2:$AA$2058,$A19,'Review rows'!$S$2:$S$2058,"Approved") -> 0 | P19: =IF(L19=0,"",IF(M19=L19,"Done",IF(M19>0,"In progress","Not started"))) -> Not started | T19: https://www.revertguide.com/en/roadmap/month-1-2/halal-haram | U19: locales/en/steps/halal-haram.json
A20: step:knowledge | B20: Roadmap step | C20: Keep learning | D20: Medium | E20: Quran or hadith citation; External resource or teacher; Tone and pastoral wording | F20: Scholar; Mentor | G20: source-checked | H20: • Recommends Tariq Ramadan's 'In the Footsteps of the Prophet'; a Geneva appeals court convicted Ramadan of rape in 2024. Confirm the team still wants it listed. • Recommends AlMaghrib, Yaqeen, SeekersGuidance, Bayyinah (Nouman Ali Khan), and books by Asad Tarsin, Safiur Rahman Mubarakpuri and Hamza Yusuf. • Quotes 'Seeking knowledge is an obligation upon every Muslim' (Ibn Majah 224, grading disputed), 'Whoever travels a path...' (Muslim 2699) and 'The cure for ignorance is to ask'. • Those hadith and 'the first word revealed was Iqra' have no specific ids; the only hadith-collection id is Ibn Sirin's saying in Muslim's introduction. | J20: 5 | K20: seekersguidance — SeekersGuidance (SeekersGuidance) — https://seekersguidance.org/ yaqeen-institute — Yaqeen Institute (Yaqeen Institute for Islamic Research) — https://yaqeeninstitute.org/ new-muslim-academy — New Muslim Academy (New Muslim Academy) — https://www.newmuslimacademy.org/ sunnah-muslim-introduction-26 — Sahih Muslim, Introduction 26: Consider from whom you take your religion (Sunnah.com) — https://sunnah.com/muslim/introduction/25 seekersguidance-qualities-of-a-teacher — What Are the Qualities One Should Seek in a Teacher? (SeekersGuidance (Shaykh Dr. Muhammad Abu Bakr Badhib)) — https://seekersguidance.org/answers/scholars-answers/what-are-the-qualities-one-should-seek-in-a-teacher/ | L20: =COUNTIF('Review rows'!$AA$2:$AA$2058,$A20) -> 16 | M20: =COUNTIFS('Review rows'!$AA$2:$AA$2058,$A20,'Review rows'!$V$2:$V$2058,"Yes") -> 0 | N20: =COUNTIFS('Review rows'!$AA$2:$AA$2058,$A20,'Review rows'!$P$2:$P$2058,"Approved") -> 0 | O20: =COUNTIFS('Review rows'!$AA$2:$AA$2058,$A20,'Review rows'!$S$2:$S$2058,"Approved") -> 0 | P20: =IF(L20=0,"",IF(M20=L20,"Done",IF(M20>0,"In progress","Not started"))) -> Not started | T20: https://www.revertguide.com/en/roadmap/month-3-6/knowledge | U20: locales/en/steps/knowledge.json
A21: step:modesty-and-clothing | B21: Roadmap step | C21: Take modesty one step at a time | D21: High | E21: Fiqh ruling; Quran or hadith citation; Safety or abuse; Tone and pastoral wording | F21: Scholar; Mentor | G21: review-needed | H21: • States the minimum: men cover navel to knee; women cover all but face and hands in front of men who are not close relatives, all day (SeekersGuidance, Quran 24:30-31). • Scholar to confirm the 'all but face and hands' wording against school differences, e.g. Hanafi on the feet and the Hanbali view on the face. • If a visible change could provoke hostility or danger at home, talk to a local mentor or get support first; no named service is given. • Workplace dress rules: find out what is religiously required first, then make a specific accommodation request with local advice. | J21: 5 | K21: new-muslim-guide — New Muslim Guide (New Muslim Guide) — https://newmuslimguide.com/en seekersguidance — SeekersGuidance (SeekersGuidance) — https://seekersguidance.org/ seekersguidance-awra-for-men — What is Considered Awra (Nakedness) for Men? (SeekersGuidance) — https://seekersguidance.org/answers/hanafi-fiqh/what-is-considered-awra-nakedness-for-men/ seekersguidance-interacting-with-opposite-sex — Guidelines for Interacting With the Opposite Sex (SeekersGuidance) — https://seekersguidance.org/answers/modesty/guidelines-for-interacting-with-the-opposite-sex/ quran-24-30-31 — Quran 24:30-31: Lowering the gaze and covering (Quran.com) — https://quran.com/24/30-31 | L21: =COUNTIF('Review rows'!$AA$2:$AA$2058,$A21) -> 11 | M21: =COUNTIFS('Review rows'!$AA$2:$AA$2058,$A21,'Review rows'!$V$2:$V$2058,"Yes") -> 0 | N21: =COUNTIFS('Review rows'!$AA$2:$AA$2058,$A21,'Review rows'!$P$2:$P$2058,"Approved") -> 0 | O21: =COUNTIFS('Review rows'!$AA$2:$AA$2058,$A21,'Review rows'!$S$2:$S$2058,"Approved") -> 0 | P21: =IF(L21=0,"",IF(M21=L21,"Done",IF(M21>0,"In progress","Not started"))) -> Not started | T21: https://www.revertguide.com/en/roadmap/month-1-2/modesty-and-clothing | U21: locales/en/steps/modesty-and-clothing.json
A22: step:prayer-on-ramp | B22: Roadmap step | C22: Ease into prayer without shame | D22: High | E22: Fiqh ruling; External resource or teacher; Tone and pastoral wording | F22: Scholar; Mentor | G22: review-needed | H22: • Says Hanafis count holding and reading a Quran in prayer 'strongly disliked'; al-Hidayah reports Abu Hanifa held it invalidates the prayer. Says Shafi'is let a learner read Al-Fatihah. • Rung plan has beginners pray all five prayers in 'simple form', saying remembrance phrases before they know Al-Fatihah and before learning the tashahhud (rung 3). • For missed prayers, tells readers to ask a teacher how to make them up; recommends the Pillars app, New Muslim Guide and an Islamwise rak'ah video. | J22: 7 | K22: new-muslim-guide — New Muslim Guide (New Muslim Guide) — https://newmuslimguide.com/en seekersguidance — SeekersGuidance (SeekersGuidance) — https://seekersguidance.org/ sunnah-bukhari-prayed-badly — Sahih al-Bukhari 757 - The man who prayed badly (Sunnah.com) — https://sunnah.com/bukhari:757 sunnah-abudawud-dhikr-instead — Sunan Abi Dawud 832 - Remembrance for one who cannot recite (Sunnah.com) — https://sunnah.com/abudawud:832 seekersguidance-recite-in-english — Can I Recite Prayer in English? (SeekersGuidance) — https://seekersguidance.org/answers/hanafi-fiqh/can-i-recite-prayer-in-english/ seekersguidance-reading-from-mushaf — Can New Muslims Hold the Qur'an and Recite from It During Prayer? (Hanafi) (SeekersGuidance) — https://seekersguidance.org/answers/hanafi-fiqh/can-new-muslims-hold-the-quran-and-recite-from-it-during-prayer/ newmuslims-recent-convert-prayer — How to Pray for a Recent Convert (part 2 of 2) (NewMuslims.com) — https://www.newmuslims.com/lessons/92/how-to-pray-for-recent-convert-part-2 | L22: =COUNTIF('Review rows'!$AA$2:$AA$2058,$A22) -> 15 | M22: =COUNTIFS('Review rows'!$AA$2:$AA$2058,$A22,'Review rows'!$V$2:$V$2058,"Yes") -> 0 | N22: =COUNTIFS('Review rows'!$AA$2:$AA$2058,$A22,'Review rows'!$P$2:$P$2058,"Approved") -> 0 | O22: =COUNTIFS('Review rows'!$AA$2:$AA$2058,$A22,'Review rows'!$S$2:$S$2058,"Approved") -> 0 | P22: =IF(L22=0,"",IF(M22=L22,"Done",IF(M22>0,"In progress","Not started"))) -> Not started | T22: https://www.revertguide.com/en/roadmap/week-1/prayer-on-ramp | U22: locales/en/steps/prayer-on-ramp.json
A23: step:prayer | B23: Roadmap step | C23: Start praying five times a day | D23: High | E23: Fiqh ruling; Arabic text or transliteration; Legal (Canada); External resource or teacher; Tone and pastoral wording | F23: Scholar; Mentor; Legal professional | G23: review-needed | H23: • Wudu: once is the minimum, three times Sunnah, head wiped once (the Shafi'i school makes three wipes Sunnah); broken by toilet, gas or deep sleep; bleeding differs. • If you lose count, take the lower number and add sujud al-sahw (the Hanafi rule differs for a first-time doubt); rak'ah counts 2, 4, 4, 3, 4. • Transliterations 'Subhana Rabbiyal Adheem', 'Subhana Rabbiyal A'la', 'As-salamu alaykum wa rahmatullah'; says the qibla from most of Canada is roughly northeast. • Says 'You have the right to pray' at work or school, and that schools differ on combining prayers for work (AMJA; SeekersGuidance Hanafi answer). | J23: 7 | K23: new-muslim-guide — New Muslim Guide (New Muslim Guide) — https://newmuslimguide.com/en sunnah-com — Sunnah.com (Sunnah.com) — https://sunnah.com/ seekersguidance — SeekersGuidance (SeekersGuidance) — https://seekersguidance.org/ sunnah-abudawud-dhikr-instead — Sunan Abi Dawud 832 - Remembrance for one who cannot recite (Sunnah.com) — https://sunnah.com/abudawud:832 seekersguidance-recite-in-english — Can I Recite Prayer in English? (SeekersGuidance) — https://seekersguidance.org/answers/hanafi-fiqh/can-i-recite-prayer-in-english/ amja-combining-for-job — Is It Permissible For Me To Combine My Prayers Because Of My Job? (Assembly of Muslim Jurists of America (AMJA)) — https://www.amjaonline.org/fatwa/en/22038/is-it-permissible-for-me-to-combine-my-prayers-because-of-my-job seekersguidance-combining-hanafi — Is Combining Prayers in the Hanafi School Possible? (SeekersGuidance) — https://seekersguidance.org/answers/hanafi-fiqh/combining-prayers-hanafi-school-possible/ | L23: =COUNTIF('Review rows'!$AA$2:$AA$2058,$A23) -> 17 | M23: =COUNTIFS('Review rows'!$AA$2:$AA$2058,$A23,'Review rows'!$V$2:$V$2058,"Yes") -> 0 | N23: =COUNTIFS('Review rows'!$AA$2:$AA$2058,$A23,'Review rows'!$P$2:$P$2058,"Approved") -> 0 | O23: =COUNTIFS('Review rows'!$AA$2:$AA$2058,$A23,'Review rows'!$S$2:$S$2058,"Approved") -> 0 | P23: =IF(L23=0,"",IF(M23=L23,"Done",IF(M23>0,"In progress","Not started"))) -> Not started | T23: https://www.revertguide.com/en/roadmap/week-1/prayer | U23: locales/en/steps/prayer.json
A24: step:questions-and-doubts | B24: Roadmap step | C24: Handle questions and doubts well | D24: High | E24: Aqidah (belief); Quran or hadith citation; Mental health; Tone and pastoral wording | F24: Scholar; Mentor; Mental health professional | G24: review-needed | H24: • Cites Hanzala fearing he was a hypocrite when his feeling of faith faded at home, and the Prophet reassuring him (Sahih Muslim 2750a). • Says feeling unsettled or having doubts does not make you a bad Muslim, and to keep praying while waiting for answers. • Advises stepping away from content that leaves you anxious or hopeless; gives no mental health referral in the step itself (Get help is linked). • Recommends Yaqeen Institute, SeekersGuidance and New Muslim Academy for questions. | J24: 4 | K24: yaqeen-institute — Yaqeen Institute (Yaqeen Institute for Islamic Research) — https://yaqeeninstitute.org/ seekersguidance — SeekersGuidance (SeekersGuidance) — https://seekersguidance.org/ new-muslim-academy — New Muslim Academy (New Muslim Academy) — https://www.newmuslimacademy.org/ sunnah-muslim-2750a — Sahih Muslim 2750a: the hadith of Hanzala (Sunnah.com) — https://sunnah.com/muslim:2750a | L24: =COUNTIF('Review rows'!$AA$2:$AA$2058,$A24) -> 12 | M24: =COUNTIFS('Review rows'!$AA$2:$AA$2058,$A24,'Review rows'!$V$2:$V$2058,"Yes") -> 0 | N24: =COUNTIFS('Review rows'!$AA$2:$AA$2058,$A24,'Review rows'!$P$2:$P$2058,"Approved") -> 0 | O24: =COUNTIFS('Review rows'!$AA$2:$AA$2058,$A24,'Review rows'!$S$2:$S$2058,"Approved") -> 0 | P24: =IF(L24=0,"",IF(M24=L24,"Done",IF(M24>0,"In progress","Not started"))) -> Not started | T24: https://www.revertguide.com/en/roadmap/week-2-3/questions-and-doubts | U24: locales/en/steps/questions-and-doubts.json
A25: step:quran | B25: Roadmap step | C25: Start reading the Quran | D25: Medium | E25: Aqidah (belief); Quran or hadith citation; External resource or teacher; Tone and pastoral wording | F25: Scholar; Mentor | G25: source-checked | H25: • Recommends The Clear Quran (Mustafa Khattab), The Gracious Quran (Ahmad Zaki Hammad), Quran.com, an unnamed 'Al-Quran app' and the Tarteel AI app. • Recommends reciters Mishary Rashid Alafasy, Abdul Rahman Al-Sudais and Omar Hisham Al-Arabi. • Facts to confirm: revealed over 23 years; Al-Ikhlas has four verses; Al-Kawthar is the shortest surah (three verses); 114 chapters; Juz Amma is the 30th part. • Says reading a translation on its own is 'completely valid' while the Arabic is out of reach (for understanding, not for recitation in prayer). | J25: 3 | K25: quran-com — Quran.com (Quran Foundation) — https://quran.com/ clear-quran — The Clear Quran (Dr. Mustafa Khattab / The Clear Quran) — https://www.theclearquran.org/ tanzil — Tanzil Project (Tanzil) — https://tanzil.ca/docs/tanzil_project | L25: =COUNTIF('Review rows'!$AA$2:$AA$2058,$A25) -> 15 | M25: =COUNTIFS('Review rows'!$AA$2:$AA$2058,$A25,'Review rows'!$V$2:$V$2058,"Yes") -> 0 | N25: =COUNTIFS('Review rows'!$AA$2:$AA$2058,$A25,'Review rows'!$P$2:$P$2058,"Approved") -> 0 | O25: =COUNTIFS('Review rows'!$AA$2:$AA$2058,$A25,'Review rows'!$S$2:$S$2058,"Approved") -> 0 | P25: =IF(L25=0,"",IF(M25=L25,"Done",IF(M25>0,"In progress","Not started"))) -> Not started | T25: https://www.revertguide.com/en/roadmap/week-2-3/quran | U25: locales/en/steps/quran.json
A26: step:shahada | B26: Roadmap step | C26: Declare your faith (Shahada) | D26: High | E26: Fiqh ruling; Aqidah (belief); Arabic text or transliteration; External resource or teacher; Tone and pastoral wording | F26: Scholar; Mentor | G26: review-needed | H26: • Transliteration 'Ash-hadu an la ilaha ill-Allah, wa ash-hadu anna Muhammadan rasul-Allah' and its English meaning; no Arabic script is shown. • Says the Shahada wipes away what came before and counts said alone; 'Islam wipes out what came before' (Muslim 121) is not among this step's sources. • Tiny version lets someone say it in their own words ('I believe there is only one God and Muhammad is His messenger') with the Arabic later; confirm this counts. • Reports SeekersGuidance answers: Shireen Ahmed (better before others, not required), Abdurragmaan Khan (online Shahada valid), Yama Niazi ('ashhadu' more cautious). | J26: 6 | K26: whyislam — WhyIslam (Islamic Circle of North America) — https://www.whyislam.org/ new-muslim-academy — New Muslim Academy (New Muslim Academy) — https://www.newmuslimacademy.org/ sunnah-com — Sunnah.com (Sunnah.com) — https://sunnah.com/ seekersguidance-convert-shahada-publicly — Should a Convert Do His Shahada Publicly? (SeekersGuidance) — https://seekersguidance.org/answers/general-counsel/convert-shahada-publicly/ seekersguidance-shahada-online — Shahada Online (SeekersGuidance) — https://seekersguidance.org/answers/general-counsel/shahada-online/ seekersguidance-do-i-need-to-say-ashhadu — Do I Need to Say 'Ashhadu' When Converting to Islam? (SeekersGuidance) — https://seekersguidance.org/answers/general-answers-feeds/do-i-need-to-say-ashhadu-when-converting-to-islam/ | L26: =COUNTIF('Review rows'!$AA$2:$AA$2058,$A26) -> 17 | M26: =COUNTIFS('Review rows'!$AA$2:$AA$2058,$A26,'Review rows'!$V$2:$V$2058,"Yes") -> 0 | N26: =COUNTIFS('Review rows'!$AA$2:$AA$2058,$A26,'Review rows'!$P$2:$P$2058,"Approved") -> 0 | O26: =COUNTIFS('Review rows'!$AA$2:$AA$2058,$A26,'Review rows'!$S$2:$S$2058,"Approved") -> 0 | P26: =IF(L26=0,"",IF(M26=L26,"Done",IF(M26>0,"In progress","Not started"))) -> Not started | T26: https://www.revertguide.com/en/roadmap/day-0-1/shahada | U26: locales/en/steps/shahada.json
A27: step:zakat-hajj | B27: Roadmap step | C27: Charity (zakat) and the pilgrimage (Hajj) | D27: High | E27: Fiqh ruling; Quran or hadith citation; Financial (zakat, riba, money); Canadian services or contacts | F27: Scholar; Mentor | G27: review-needed | H27: • Zakat: 2.5% of qualifying wealth above nisab held a lunar year; nisab 87.48 g gold or 612.36 g silver (Islamic Relief Canada); home, car and belongings excluded. • Says subtract debts due now, with long-term debts treated differently; names NZF Canada and Muslim Welfare Canada calculators; check charities on the CRA list. • Travel advice is dated: 'checked September 23, 2026, page last updated September 17, 2026, avoid non-essential travel'; the source note says updated September 24. • Hajj: once if physically and financially able; says it 'lasts five to six days' and 'ends with Eid al-Adha' (Eid is 10 Dhul Hijjah; rites run to the 12th or 13th). | I27: ⚠ Heading 'Understand Sadaqah (voluntary charity)' puts the Arabic term first; the naming rule wants plain English first, e.g. 'Understand voluntary charity (sadaqah)'. | J27: 10 | K27: quran-zakat-9-60 — Quran 9:60 - Zakat recipient categories (Quran.com) — https://quran.com/9/60 irc-nisab — Nisab value: what is nisab? (Islamic Relief Canada) — https://www.islamicreliefcanada.org/our-work/zakat/nisab nzf-canada-rrsp-tfsa — How do I calculate zakat on my retirement savings, RRSP and TFSA? (National Zakat Foundation Canada) — https://www.nzfcanada.com/zakat-faq/how-do-i-calculate-zakat-on-my-retirement-savings-rrsp-and-tfsa mwc-zakat-calculator — Zakat calculator (Muslim Welfare Canada) — https://mwcanada.org/zakat-calculator/ cra-charities-listing — List of charities and other qualified donees (Canada Revenue Agency) — https://www.canada.ca/en/revenue-agency/services/charities-giving/list-charities/list-charities-other-qualified-donees.html sunnah-muslim-goodness-charity — Sahih Muslim 1005 - Every good act is charity (Sunnah.com) — https://sunnah.com/muslim:1005 sunnah-bukhari-6464-regular-deeds — Sahih al-Bukhari 6464: the most beloved deeds are the regular ones (Sunnah.com) — https://sunnah.com/bukhari:6464 seekersguidance — SeekersGuidance (SeekersGuidance) — https://seekersguidance.org/ travel-gc-saudi-arabia — Travel advice and advisories for Saudi Arabia (Government of Canada) — https://travel.gc.ca/destinations/saudi-arabia nusuk-hajj — Nusuk Hajj Official Platform (Saudi Ministry of Hajj and Umrah) — https://hajj.nusuk.sa/ | L27: =COUNTIF('Review rows'!$AA$2:$AA$2058,$A27) -> 15 | M27: =COUNTIFS('Review rows'!$AA$2:$AA$2058,$A27,'Review rows'!$V$2:$V$2058,"Yes") -> 0 | N27: =COUNTIFS('Review rows'!$AA$2:$AA$2058,$A27,'Review rows'!$P$2:$P$2058,"Approved") -> 0 | O27: =COUNTIFS('Review rows'!$AA$2:$AA$2058,$A27,'Review rows'!$S$2:$S$2058,"Approved") -> 0 | P27: =IF(L27=0,"",IF(M27=L27,"Done",IF(M27>0,"In progress","Not started"))) -> Not started | T27: https://www.revertguide.com/en/roadmap/month-6-plus/zakat-hajj | U27: locales/en/steps/zakat-hajj.json
A28: topic:beliefs | B28: Topic | C28: Core beliefs in Islam | D28: High | E28: Fiqh ruling; Aqidah (belief); Quran or hadith citation; Mental health; Suicide-safe language; Safety or abuse; Family, marriage or intimacy; Canadian services or contacts; External resource or teacher | F28: Scholar; Mentor; Mental health professional | G28: review-needed | H28: • Church weddings and funerals: summarises Dar al-Ifta and AMJA (may attend), SeekersGuidance Hanafi (gathering only) and IslamQA (strict); check each summary • Named SeekersGuidance answers: Jamir Meah (statues), Ilyas Patel (prasad), Abdullah Anik Misra (karma), Faraz Rabbani (yoga quote), Irshaad Sedick (smudging) • Creed claims: Quran names 25 prophets; prophets protected from major sins but small errors possible; angels made from light; Mika'il over rain and provision • Amulets: says most scholars (per Islamweb) forbid even Quran-only taweez; a SeekersGuidance Shafi'i answer allows 3 conditions; cites Abu Dawud 3883 • Hadith to check: Muslim 121, 2188, 2200, 2230 (prayer unaccepted 40 nights), 2261a (spit left 3 times); Bukhari 1385, 2276, 3432, 3448, 4485 • Cites a 2025 Yaqeen survey (618 US converts: 60% raised Christian, ~19% no religion) and a 2013 Psychiatrist paper; 911 then 9-8-8 order is correct | I28: ⚠ Quotes 7:156 ('My mercy encompasses all things') but quran-7-156 is not in sourceIds (the entry exists in sources.json) ⚠ Headings lead with Arabic: 'Tawhid: the oneness of God', 'Qadar: understanding divine decree'; card 'Dua and dhikr' (nav: 'Supplication and remembrance') | J28: 51 | K28: quran-al-ikhlas-112 — Quran 112 - Surah al-Ikhlas (Quran.com) — https://quran.com/112 quran-al-fatihah-1 — Quran 1 - Surah al-Fatihah (Quran.com) — https://quran.com/1 quran-19-30 — Quran 19:30: Jesus says, I am the servant of Allah (Quran.com) — https://quran.com/19/30 quran-4-48 — Quran 4:48: Allah forgives what is less than associating partners with Him (Quran.com) — https://quran.com/4/48 quran-8-38 — Quran 8:38: Past wrongs forgiven for those who stop (Quran.com) — https://quran.com/8/38 quran-31-15 — Quran 31:15: Keep your parents' company kindly (Quran.com) — https://quran.com/31/15 quran-60-8 — Quran 60:8: Kindness and fairness to those who do not fight you (Quran.com) — https://quran.com/60/8 quran-21-107-mercy-worlds — Quran 21:107 - Mercy to the worlds (Quran.com) — https://quran.com/21/107 sunnah-muslim-121 — Sahih Muslim 121: Islam wipes out what came before (Sunnah.com) — https://sunnah.com/muslim:121 sunnah-muslim-8a — Sahih Muslim 8a: The hadith of Jibril (Sunnah.com) — https://sunnah.com/muslim:8a new-muslim-guide-64245f26c664a — The Six Pillars of Faith (Eemaan) (New Muslim Guide) — https://newmuslimguide.com/en/categories/your-faith/64245f26c664a yaqeen-who-is-jesus-in-islam — Who is Jesus in Islam? (Yaqeen Institute) — https://yaqeeninstitute.org/read/blog/who-is-jesus-in-islam new-muslim-guide-640fc1197525f — No Intermediaries between God and Man (New Muslim Guide) — https://newmuslimguide.com/en/preliminaries/640fc1197525f newmuslims-belief-in-allah-part-2 — Belief in Allah (part 2 of 2): shirk, the opposite of tawheed (NewMuslims.com) — https://www.newmuslims.com/lessons/12/belief-in-allah-part-2 yaqeen-why-is-shirk-the-greatest — Why Is Shirk the Greatest Sin of All? (Yaqeen Institute) — https://yaqeeninstitute.org/read/paper/why-is-shirk-the-greatest-sin-of-all dar-alifta-a-muslim-attending-the-funeral — A Muslim attending the funeral of a non-Muslim (Dar al-Ifta al-Misriyyah (Egypt)) — https://www.dar-alifta.org/en/fatwa/details/5935/a-muslim-attending-the-funeral-of-a-non-muslim amja-can-a-muslim-attend-a — Can A Muslim Attend A Non-Muslim Funeral? (Assembly of Muslim Jurists of America (AMJA)) — https://www.amjaonline.org/fatwa/en/78565/can-a-muslim-attend-a-non-muslim-funeral seekersguidance-attending-christmas-festivities-of-ones — Attending Christmas Festivities of One's Non-Muslim Family (SeekersGuidance) — https://seekersguidance.org/answers/hanafi-fiqh/attending-christmas-festivities-of-ones-non-muslim-family/ seekersguidance-can-i-go-to-church — Can I Go to Church with a Friend? (SeekersGuidance) — https://seekersguidance.org/answers/general-counsel/can-i-go-to-church-with-a-friend/ islamqa-6992 — Convert attending his brother's wedding party (Islam Question and Answer) — https://islamqa.info/en/answers/6992 seekersguidance-owning-books-on-other-religions — Owning or Gifting Books on Other Religions (SeekersGuidance) — https://seekersguidance.org/answers/calling-to-islam/owning-or-gifting-books-on-other-religions/ quran-6-108 — Quran 6:108: Do not insult what others worship (Quran.com) — https://quran.com/6/108 yaqeen-becoming-muslim — Becoming Muslim: The Lives of American Converts to Islam (Yaqeen Institute) — https://yaqeeninstitute.org/read/data/reports/becoming-muslim-lives-of-american-converts-to-islam seekersguidance-stay-at-house-with-hindu-idols-shafii — Is It Permissible for a Muslim to Permanently Stay at a House Containing Hindu Idols? [Shafi'i] (SeekersGuidance) — https://seekersguidance.org/answers/shafii-fiqh/permissible-muslim-permanently-stay-house-containing-hindu-idols-shafii/ seekersguidance-prasad-received-by-mistake — Can Mistakenly Received Prasad Be Given to a Poor Non-Muslim or Must It Be Discarded? (SeekersGuidance) — https://seekersguidance.org/answers/general-counsel/can-mistakenly-received-prasad-be-given-to-a-poor-non-muslim-or-must-it-be-discarded/ seekersguidance-karma-in-islam — Does the Concept of Karma Exist in Islam? (SeekersGuidance) — https://seekersguidance.org/answers/general-counsel/does-the-concept-of-karma-exist-in-islam/ quran-99-7-8 — Quran 99:7-8: An atom's weight of good or evil (Quran.com) — https://quran.com/99/7-8 seekersguidance-ruling-of-yoga — What is the Ruling of Yoga? (SeekersGuidance) — https://seekersguidance.org/answers/general-counsel/what-is-the-ruling-of-yoga/ seekersguidance-smudging — Is It Permissible for Muslims to Participate in Smudging? (SeekersGuidance) — https://seekersguidance.org/answers/islamic-belief/is-it-permissible-for-muslims-to-participate-in-smudging/ sunnah-bukhari-1385 — Sahih al-Bukhari 1385: Every child is born on the fitrah (Sunnah.com) — https://sunnah.com/bukhari:1385 quran-30-30 — Quran 30:30: The fitrah of Allah (Quran.com) — https://quran.com/30/30 quran-4-157 — Quran 4:157: Jesus was not killed or crucified (Quran.com) — https://quran.com/4/157 quran-4-171 — Quran 4:171: Jesus the Messiah, messenger and word of Allah (Quran.com) — https://quran.com/4/171 quran-3-45 — Quran 3:45: Jesus honoured in this world and the next (Quran.com) — https://quran.com/3/45 quran-5-46 — Quran 5:46: The Gospel given to Jesus (Quran.com) — https://quran.com/5/46 quran-29-46 — Quran 29:46: Speak with the People of the Book in the best way (Quran.com) — https://quran.com/29/46 sunnah-bukhari-4485 — Sahih al-Bukhari 4485: Neither believe nor disbelieve the People of the Book (Sunnah.com) — https://sunnah.com/bukhari:4485 sunnah-bukhari-3432 — Sahih al-Bukhari 3432: Mary among the best of women (Sunnah.com) — https://sunnah.com/bukhari:3432 sunnah-bukhari-3448 — Sahih al-Bukhari 3448: The return of Jesus (Sunnah.com) — https://sunnah.com/bukhari:3448 seekersguidance-reading-the-bible — What is the Ruling of Reading the Jewish and Christian Bible? (SeekersGuidance) — https://seekersguidance.org/answers/education/what-is-the-ruling-of-reading-the-jewish-and-christian-bible/ sunnah-muslim-2188 — Sahih Muslim 2188: The evil eye is real (Sunnah.com) — https://sunnah.com/muslim:2188 sunnah-muslim-2200 — Sahih Muslim 2200: No harm in ruqya without shirk (Sunnah.com) — https://sunnah.com/muslim:2200 sunnah-bukhari-2276 — Sahih al-Bukhari 2276: Payment for ruqya with Al-Fatiha (Sunnah.com) — https://sunnah.com/bukhari:2276 sunnah-abudawud-3883 — Sunan Abi Dawud 3883: Spells, charms and love potions are shirk (Sunnah.com) — https://sunnah.com/abudawud:3883 sunnah-muslim-2230 — Sahih Muslim 2230: Visiting a diviner (Sunnah.com) — https://sunnah.com/muslim:2230 sunnah-muslim-2261a — Sahih Muslim 2261a: Good dreams and bad dreams (Sunnah.com) — https://sunnah.com/muslim:2261a islamweb-fatwa-6029 — Quranic amulets and paying for Ruqyah (Fatwa 6029) (Islamweb Fatwa Centre) — https://www.islamweb.net/en/fatwa/6029/quranic-amulets-and-paying-for-ruqyah seekersguidance-ruqya-and-amulets — Can I Use Protective or Healing Words (Ruqya) and Amulets (Tawiz) Using Numbers? (SeekersGuidance (Shaykh Irshaad Sedick, checked by Shaykh Faraz Rabbani)) — https://seekersguidance.org/answers/shafii-fiqh/can-i-use-protective-or-healing-words-ruqya-and-amulets-tawiz-using-numbers/ dein-illaiee-2013-jinn-mental-health — Jinn and mental health: looking at jinn possession in modern psychiatric practice (The Psychiatrist 37(9):290-293 (Simon Dein and Abdool Samad Illaiee)) — https://www.cambridge.org/core/journals/the-psychiatrist/article/jinn-and-mental-health-looking-at-jinn-possession-in-modern-psychiatric-practice/0012DFF288FA8958C7A52CAB2F29B679 988-canada — 9-8-8: Suicide Crisis Helpline (Centre for Addiction and Mental Health (CAMH), funded by the Government of Canada) — https://988.ca/ emergency-911-canada — Get help with mental health (Public Health Agency of Canada) — https://www.canada.ca/en/public-health/services/mental-health-services/mental-health-get-help.html | L28: =COUNTIF('Review rows'!$AA$2:$AA$2058,$A28) -> 19 | M28: =COUNTIFS('Review rows'!$AA$2:$AA$2058,$A28,'Review rows'!$V$2:$V$2058,"Yes") -> 0 | N28: =COUNTIFS('Review rows'!$AA$2:$AA$2058,$A28,'Review rows'!$P$2:$P$2058,"Approved") -> 0 | O28: =COUNTIFS('Review rows'!$AA$2:$AA$2058,$A28,'Review rows'!$S$2:$S$2058,"Approved") -> 0 | P28: =IF(L28=0,"",IF(M28=L28,"Done",IF(M28>0,"In progress","Not started"))) -> Not started | T28: https://www.revertguide.com/en/topics/beliefs | U28: locales/en/topics/beliefs.json
